Workbook

Sheet Léame
A1: BOMAG Compare Hub — Matriz de datos y análisis financiero
A2: Exportado desde el código fuente de la aplicación (src/data/*, src/utils/financialFields.ts, src/utils/productLineFinancial.ts, src/components/MachineComparison.tsx, ArticulationJointCostAnalysis.tsx).
A4: Convención de colores
A5: Texto azul | B5: Dato de entrada / supuesto editable (valor fijo tomado de la app).
A6: Texto negro | B6: Fórmula calculada — no sobrescribir.
A7: Texto verde | B7: Vínculo a otra hoja (p. ej. precio y consumo tomados de la hoja de datos).
A8: Relleno amarillo | B8: Supuestos clave globales (hoja Supuestos) y selectores del Comparador.
A10: Hojas
A11: Supuestos | B11: Parámetros globales: precio del diésel, horas de operación, eficiencia, volumen, tipo de suelo, junta articulada, parámetros de pavimentadoras y fresadoras, tasas de cambio.
A12: Datos SDR / LTR / HTR | B12: Matriz completa de especificaciones de rodillos (textos en español). Precio, consumo y mantenimiento alimentan los análisis.
A13: Datos Fresadoras | B13: Especificaciones y variables financieras de fresadoras en frío.
A14: Datos Pavimentadoras | B14: Especificaciones y bloque financiero (consumo, CO₂, calentamiento, reemplazos de plancha).
A15: Análisis Compactación | B15: TCO por máquina (SDR+LTR+HTR): combustible, mantenimiento, junta articulada, rendimiento y costo por volumen.
A16: Análisis Fresadoras | B16: TCO con BMS15L (reducción de desgaste), desgaste de herramientas y horas de trabajo por volumen.
A17: Análisis Pavimentadoras | B17: TCO con ECOMODE / modos de ahorro, MAGMALIFE (combustible de calentamiento y desgaste de plancha).
A18: Junta Articulada | B18: Análisis de costo de engrase: competidor vs BOMAG.
A19: TCO Progresivo | B19: TCO acumulado a 0…10.000 h por máquina (todas las líneas).
A20: Comparador | B20: Elija hasta 4 máquinas de compactación (lista desplegable) para verlas lado a lado, como en la app.
A21: Tablas Rendimiento | B21: Tablas de rendimiento y altura de capa por peso y tipo de suelo.
A22: Mant. BM 1000-20 | B22: Rutina y costos de mantenimiento preventivo de la fresadora BM 1000/20.
... A29: Monedas | B29: Todos los montos se guardan en USD (igual que la app). La columna "TCO (moneda sel.)" convierte con la tasa elegida en Supuestos.
A31: Notas importantes
A32: Rendimiento base | B32: La app calcula el rendimiento con una interpolación por peso (correctedPerformanceData.ts). Los 4 valores por suelo se exportaron tal cual (azul) y la fórmula elige el del suelo seleccionado.
A33: Desgaste de plancha | B33: En la app, "~24.000 €" se interpreta como 24 € (el punto de miles se lee como decimal), dando ~$0,009/h. Este Excel usa el importe correcto (24.000 € → $8,64/h). Puede cambiar el monto en la hoja Análisis Pavimentadoras.
A34: Precios en 0 | B34: Fresadoras y pavimentadoras no tienen precio cargado en la app (0). Ingréselos en azul para obtener un TCO completo.

Sheet Supuestos
A1: Supuestos globales
A3: Parámetro | B3: Valor | C3: Unidad | D3: Fuente / nota
A4: Operación (todas las líneas)
A5: Precio del diésel | B5: 1.2 | C5: USD/L | D5: Valor por defecto de la app (fuelPriceUSD).
A6: Tiempo de operación a analizar | B6: 3000 | C6: h | D6: Valor por defecto de la app (operationTimeHours).
A7: Compactación (SDR / LTR / HTR)
A8: Tipo de suelo seleccionado | B8: Suelo mixto | D8: Roca / Grava / Suelo mixto / Arcilla. Por defecto en la app: suelo mixto.
A9: Eficiencia de trabajo | B9: 1 | C9: % | D9: workEfficiency (0–100 %). Por defecto 100 %.
A10: Volumen a compactar | B10: 0 | C10: m³ | D10: Ingrese el volumen (Largo × Ancho × Alto) para calcular horas y costo del trabajo.
A11: Multiplicador tecnología BOMAG (Economizer/Terrameter) | B11: 1.25 | C11: x | D11: Se aplica al rendimiento solo si la máquina es BOMAG y la tecnología está activa.
A12: Junta articulada (solo SDR)
A13: Tarifa técnico | B13: 35 | C13: USD/h | D13: aj_technicianRate
A14: Costo máquina parada | B14: 120 | C14: USD/h | D14: aj_machineIdleRate
A15: Costo de grasa por intervención | B15: 15 | C15: USD | D15: aj_greaseCostPerIntervention
A16: Intervalo de engrase del competidor | B16: 50 | C16: h | D16: Tabla BOMAG: cada 50 h (o semanal).
A17: Tiempo por engrase | B17: 0.5 | C17: h | D17: Tabla BOMAG: 30 minutos.
A18: Fresadoras
A19: Volumen a fresar | B19: 0 | C19: m³ | D19: millingVolumeM3
A20: Reducción de desgaste BMS15L (por defecto) | B20: 0.2 | C20: % | D20: MILLING_BMS15L_WEAR_REDUCTION
A21: Pavimentadoras
A22: Tipo de cambio EUR → USD (datos en €) | B22: 1.08 | C22: USD/EUR | D22: EUR_TO_USD en financialFields.ts
A23: Horas por turno | B23: 10 | C23: h | D23: PAVER_HOURS_PER_SHIFT
A24: Ahorro de combustible ECOMODE (BOMAG) | B24: 0.17 | C24: % | D24: PAVER_ECOMODE_FUEL_SAVINGS
A25: Factor consumo EcoPlus (Vögele) | B25: 0.75 | C25: x | D25: productLineFinancial.ts
A26: Factor consumo VarioSpeed (Dynapac) | B26: 0.9 | C26: x | D26: productLineFinancial.ts
A27: Factor consumo Eco-mode (Caterpillar) | B27: 0.9 | C27: x | D27: productLineFinancial.ts
A28: Combustible de calentamiento competidor | B28: 10.5 | C28: L/turno | D28: PAVER_COMPETITOR_SETUP_FUEL_L
A29: Combustible de calentamiento MAGMALIFE | B29: 3.5 | C29: L/turno | D29: PAVER_MAGMALIFE_SETUP_FUEL_L
A30: Reemplazos de plancha competidor (3 años) | B30: 24000 | C30: EUR | D30: PAVER_COMPETITOR_WEAR_3Y_EUR (~24.000 €)
A31: Horas de operación por año (plancha) | B31: 1000 | C31: h/año | D31: PAVER_WEAR_HOURS_PER_YEAR
A32: Minutos de calentamiento sin MAGMALIFE | B32: 60 | C32: min | D32: Valor por defecto de la app
A34: Monedas (unidades por 1 USD)
A35: Moneda | B35: Tasa por USD | D35: Nota
A36: USD | B36: 1 | D36: Tasas de respaldo de la app (CurrencyContext.tsx). La app las actualiza en línea; edítelas aquí.
A37: EUR | B37: 0.92
A38: IDR | B38: 16500
A39: KRW | B39: 1380
A40: THB | B40: 33.5
A41: VND | B41: 25500
A42: MYR | B42: 4.45
A43: PHP | B43: 58
A45: Moneda seleccionada | B45: USD
A46: Tasa aplicada (por USD) | B46: =INDEX($B$36:$B$43,MATCH(Moneda,$A$36:$A$43,0)) -> 1

Sheet Datos SDR
A1: ID | B1: Marca | C1: Modelo | D1: N.º material | E1: Peso (kg) | F1: Motor | G1: Ancho de compactación (m) | H1: Potencia (HP) | I1: Amplitud (mm) | J1: Carga lineal estática (kg/cm) | K1: Gradeabilidad (%) | L1: País de origen | M1: Asistente de compactación | N1: Telemetría | O1: Tecnologías innovadoras | P1: USP | Q1: USP 1 | R1: USP 2 | S1: USP 3 | T1: USP 4 | U1: USP 5 | V1: USP 6 | W1: Profundidad de compactación máx. | X1: Rendimiento en compactación (m³/h, ficha) | Y1: Consumo de combustible (L/h) | Z1: Precio CIF (USD) | AA1: Mant. preventivo (USD/h) | AB1: Mant. correctivo (USD/h) | AC1: Tiempo de uso (h) | AD1: TCO estático app (USD) | AE1: Línea de tiempo TCO (datos app)
A2: =B2&" | "&C2 -> BOMAG | BW211 D-5 SL | B2: BOMAG | C2: BW211 D-5 SL | D2: 93500000 | E2: 10630 | F2: Cummins 4BT 3.9 | G2: 2.1 | H2: 100 | I2: 1.80 / 0.95 | J2: 28.4 | K2: 45 | L2: India | M2: BOMAG ECONOMIZER Sistema visual que permite a los operadores medir el progreso de la compactación en tiempo real. Utiliza una escala LED en la cabina para mostrar el nivel de compactación alcanzado, ayudando a evitar sobrecompacción o subcompactación. (Estandar) BOMAG TERRAMETER Sistema que mide la rigidez del suelo mediante la vibración del tambor. Ofrece una lectura en tiempo real del módulo de elasticidad del material compactado, lo que facilita el control preciso de la compactación y la trazabilidad de los trabajos. Evib - MN/m2 | N2: Telematics | O2: Economizer, TERRAMETER (Evib real), VARIOCONTROL, ECOMODE, TELEMATIC | Q2: Operación Intuitiva * Un switch para cada función * Símbolos intuitivos facilitan la operación | R2: Rendimiento de compactación más alto * Máximas amplitudes para un efecto de compactación más profundo (Larger amplitud 2,2 mm) * Flexibilidad en el montaje del kit pata de cabra | S2: Junta de articulación libre de mantenimiento | T2: Trabajo comfortable y seguro * Espacio de trabajo amplio y con excelente visibilidad | U2: Compactación eficiente Medición y documentación en tiempo real usando: ECONOMIZER, TERRAMETER y BOMAP | V2: Fácil mantenimiento * Todos los componentes dispuestos para un fácil acceso * Menos mantenimiento en el sistema de refrigeración debido al el punto alto de entrada de aire, menos propenso a contaminación | W2: 60 | X2: 270 - 540 | Y2: 11.8 | Z2: 57592.78 | AA2: 1 | AB2: 2 | AC2: 3000 | AD2: 109072.78 | AE2: 1000 h: precio 42800 / TCO 109072.78; 1500 h: precio 50200 / TCO 109072.78; 2000 h: precio 57600 / TCO 109072.78; 2500 h: precio 65000 / TCO 109072.78; 3000 h: precio 72400 / TCO 109072.78
A3: =B3&" | "&C3 -> BOMAG | BW211 D-5 SL | B3: BOMAG | C3: BW211 D-5 SL | D3: 93500004 | E3: 10630 | F3: Cummins 4BTAA 3.9 | G3: 2.1 | H3: 110 | I3: 1.80 / 0.95 | J3: 28.4 | K3: 45 | L3: India | M3: BOMAG ECONOMIZER Sistema visual que permite a los operadores medir el progreso de la compactación en tiempo real. Utiliza una escala LED en la cabina para mostrar el nivel de compactación alcanzado, ayudando a evitar sobrecompacción o subcompactación. (Estandar) BOMAG TERRAMETER Sistema que mide la rigidez del suelo mediante la vibración del tambor. Ofrece una lectura en tiempo real del módulo de elasticidad del material compactado, lo que facilita el control preciso de la compactación y la trazabilidad de los trabajos. Evib - MN/m2 | N3: Telematics | O3: Economizer, TERRAMETER (Evib real), VARIOCONTROL, ECOMODE, TELEMATIC | Q3: Operación Intuitiva * Un switch para cada función * Símbolos intuitivos facilitan la operación | R3: Rendimiento de compactación más alto * Máximas amplitudes para un efecto de compactación más profundo (Larger amplitud 2,2 mm) * Flexibilidad en el montaje del kit pata de cabra | S3: Junta de articulación libre de mantenimiento | T3: Trabajo comfortable y seguro * Espacio de trabajo amplio y con excelente visibilidad | U3: Compactación eficiente Medición y documentación en tiempo real usando: ECONOMIZER, TERRAMETER y BOMAP | V3: Fácil mantenimiento * Todos los componentes dispuestos para un fácil acceso * Menos mantenimiento en el sistema de refrigeración debido al el punto alto de entrada de aire, menos propenso a contaminación | W3: 60 | X3: 270 - 540 | Y3: 11.8 | Z3: 59374 | AA3: 1 | AB3: 2 | AC3: 3000 | AD3: 110854 | AE3: 1000 h: precio 44430 / TCO 110854; 1500 h: precio 51830 / TCO 110854; 2000 h: precio 59230 / TCO 110854; 2500 h: precio 66630 / TCO 110854; 3000 h: precio 74030 / TCO 110854
A4: =B4&" | "&C4 -> BOMAG | BW211 D-5 SL | B4: BOMAG | C4: BW211 D-5 SL | D4: 58400031 | E4: 10630 | F4: Deutz BF4M 2012 C | G4: 2.1 | H4: 132 | I4: 1.80 / 0.95 | J4: 28.4 | K4: 45 | L4: China | M4: BOMAG ECONOMIZER Sistema visual que permite a los operadores medir el progreso de la compactación en tiempo real. Utiliza una escala LED en la cabina para mostrar el nivel de compactación alcanzado, ayudando a evitar sobrecompacción o subcompactación. (Estandar) BOMAG TERRAMETER Sistema que mide la rigidez del suelo mediante la vibración del tambor. Ofrece una lectura en tiempo real del módulo de elasticidad del material compactado, lo que facilita el control preciso de la compactación y la trazabilidad de los trabajos. Evib - MN/m2 | N4: Telematics | O4: Economizer, TERRAMETER (Evib real), VARIOCONTROL, ECOMODE, TELEMATIC | Q4: Operación Intuitiva * Un switch para cada función * Símbolos intuitivos facilitan la operación | R4: Rendimiento de compactación más alto * Máximas amplitudes para un efecto de compactación más profundo (Larger amplitud 2,2 mm) * Flexibilidad en el montaje del kit pata de cabra | S4: Junta de articulación libre de mantenimiento | T4: Trabajo comfortable y seguro * Espacio de trabajo amplio y con excelente visibilidad | U4: Compactación eficiente Medición y documentación en tiempo real usando: ECONOMIZER, TERRAMETER y BOMAP | V4: Fácil mantenimiento * Todos los componentes dispuestos para un fácil acceso * Menos mantenimiento en el sistema de refrigeración debido al el punto alto de entrada de aire, menos propenso a contaminación | W4: 60 | X4: 270 - 540 | Y4: 12.4 | Z4: 63530.18 | AA4: 1 | AB4: 2 | AC4: 3000 | AD4: 117170.18 | AE4: 1000 h: precio 44980 / TCO 117170.18; 1500 h: precio 52680 / TCO 117170.18; 2000 h: precio 60380 / TCO 117170.18; 2500 h: precio 68080 / TCO 117170.18; 3000 h: precio 75780 / TCO 117170.18
A5: =B5&" | "&C5 -> BOMAG | BW211 D-5 SL | B5: BOMAG | C5: BW211 D-5 SL | D5: 58400033 | E5: 10630 | F5: Deutz TCD 2012 L04 2V | G5: 2.13 | H5: 140 | I5: 1.80 / 0.96 | J5: 26.8 | K5: 45 | L5: China | M5: BOMAG ECONOMIZER Sistema visual que permite a los operadores medir el progreso de la compactación en tiempo real. Utiliza una escala LED en la cabina para mostrar el nivel de compactación alcanzado, ayudando a evitar sobrecompacción o subcompactación. (Estandar) BOMAG TERRAMETER Sistema que mide la rigidez del suelo mediante la vibración del tambor. Ofrece una lectura en tiempo real del módulo de elasticidad del material compactado, lo que facilita el control preciso de la compactación y la trazabilidad de los trabajos. Evib - MN/m2 | N5: Telematics | O5: Economizer, TERRAMETER (Evib real), VARIOCONTROL, ECOMODE, TELEMATIC | Q5: Operación Intuitiva * Un switch para cada función * Símbolos intuitivos facilitan la operación | R5: Rendimiento de compactación más alto * Máximas amplitudes para un efecto de compactación más profundo (Larger amplitud 2,2 mm) * Flexibilidad en el montaje del kit pata de cabra | S5: Junta de articulación libre de mantenimiento | T5: Trabajo comfortable y seguro * Espacio de trabajo amplio y con excelente visibilidad | U5: Compactación eficiente Medición y documentación en tiempo real usando: ECONOMIZER, TERRAMETER y BOMAP | V5: Fácil mantenimiento * Todos los componentes dispuestos para un fácil acceso * Menos mantenimiento en el sistema de refrigeración debido al el punto alto de entrada de aire, menos propenso a contaminación | W5: 60 | X5: 270 - 540 | Y5: 12.4 | Z5: 66500 | AA5: 1 | AB5: 2 | AC5: 3000 | AD5: 120140 | AE5: 1000 h: precio 44980 / TCO 120140; 1500 h: precio 52680 / TCO 120140; 2000 h: precio 60380 / TCO 120140; 2500 h: precio 68080 / TCO 120140; 3000 h: precio 75780 / TCO 120140
A6: =B6&" | "&C6 -> BOMAG | BW212 D-5 SL | B6: BOMAG | C6: BW212 D-5 SL | D6: 58400036 | E6: 11490 | F6: Deutz BF4M 2012 C | G6: 2.13 | H6: 132 | I6: 1.80 / 0.96 | J6: 32.4 | K6: 45 | L6: China | M6: BOMAG ECONOMIZER Sistema visual que permite a los operadores medir el progreso de la compactación en tiempo real. Utiliza una escala LED en la cabina para mostrar el nivel de compactación alcanzado, ayudando a evitar sobrecompacción o subcompactación. (Estandar) BOMAG TERRAMETER Sistema que mide la rigidez del suelo mediante la vibración del tambor. Ofrece una lectura en tiempo real del módulo de elasticidad del material compactado, lo que facilita el control preciso de la compactación y la trazabilidad de los trabajos. Evib - MN/m2 | N6: Telematics | O6: Economizer, TERRAMETER (Evib real), VARIOCONTROL, ECOMODE, TELEMATIC | Q6: Operación Intuitiva * Un switch para cada función * Símbolos intuitivos facilitan la operación | R6: Rendimiento de compactación más alto * Máximas amplitudes para un efecto de compactación más profundo (Larger amplitud 2,2 mm) * Flexibilidad en el montaje del kit pata de cabra | S6: Junta de articulación libre de mantenimiento | T6: Trabajo comfortable y seguro * Espacio de trabajo amplio y con excelente visibilidad | U6: Compactación eficiente Medición y documentación en tiempo real usando: ECONOMIZER, TERRAMETER y BOMAP | V6: Fácil mantenimiento * Todos los componentes dispuestos para un fácil acceso * Menos mantenimiento en el sistema de refrigeración debido al el punto alto de entrada de aire, menos propenso a contaminación | W6: 60 | X6: 270 - 540 | Y6: 12.4 | Z6: 68684 | AA6: 1 | AB6: 2 | AC6: 3000 | AD6: 122324 | AE6: 1000 h: precio 688700 / TCO 122324; 1500 h: precio 802660 / TCO 122324; 2000 h: precio 916620 / TCO 122324; 2500 h: precio 1030580 / TCO 122324; 3000 h: precio 1144540 / TCO 122324
A7: =B7&" | "&C7 -> BOMAG | BW213 D-5 SL | B7: BOMAG | C7: BW213 D-5 SL | D7: 58400041 | E7: 12320 | F7: Deutz BF4M 2012 C | G7: 2.13 | H7: 132 | I7: 1.80 / 0.96 | J7: 37.1 | K7: 45 | L7: China | M7: BOMAG ECONOMIZER Sistema visual que permite a los operadores medir el progreso de la compactación en tiempo real. Utiliza una escala LED en la cabina para mostrar el nivel de compactación alcanzado, ayudando a evitar sobrecompacción o subcompactación. (Estandar) BOMAG TERRAMETER Sistema que mide la rigidez del suelo mediante la vibración del tambor. Ofrece una lectura en tiempo real del módulo de elasticidad del material compactado, lo que facilita el control preciso de la compactación y la trazabilidad de los trabajos. Evib - MN/m2 | N7: Telematics | O7: Economizer, TERRAMETER (Evib real), VARIOCONTROL, ECOMODE, TELEMATIC | Q7: Operación Intuitiva * Un switch para cada función * Símbolos intuitivos facilitan la operación | R7: Rendimiento de compactación más alto * Máximas amplitudes para un efecto de compactación más profundo (Larger amplitud 2,2 mm) * Flexibilidad en el montaje del kit pata de cabra | S7: Junta de articulación libre de mantenimiento | T7: Trabajo comfortable y seguro * Espacio de trabajo amplio y con excelente visibilidad | U7: Compactación eficiente Medición y documentación en tiempo real usando: ECONOMIZER, TERRAMETER y BOMAP | V7: Fácil mantenimiento * Todos los componentes dispuestos para un fácil acceso * Menos mantenimiento en el sistema de refrigeración debido al el punto alto de entrada de aire, menos propenso a contaminación | W7: 60 | X7: 270 - 540 | Y7: 12.4 | Z7: 72948 | AA7: 1 | AB7: 2 | AC7: 3000 | AD7: 126588 | AE7: 1000 h: precio 713802 / TCO 126588; 1500 h: precio 827762 / TCO 126588; 2000 h: precio 941722 / TCO 126588; 2500 h: precio 1055682 / TCO 126588; 3000 h: precio 1169642 / TCO 126588
A8: =B8&" | "&C8 -> BOMAG | BW213 D-5 SL TCD | B8: BOMAG | C8: BW213 D-5 SL TCD | D8: 58400041 | E8: 11960 | F8: Deutz TCD 2021 L04 2V | G8: 2.13 | H8: 140 | I8: 1.90 / 0.96 | J8: 37 | K8: 45 | L8: China | M8: BOMAG ECONOMIZER Sistema visual que permite a los operadores medir el progreso de la compactación en tiempo real. Utiliza una escala LED en la cabina para mostrar el nivel de compactación alcanzado, ayudando a evitar sobrecompacción o subcompactación. (Estandar) BOMAG TERRAMETER Sistema que mide la rigidez del suelo mediante la vibración del tambor. Ofrece una lectura en tiempo real del módulo de elasticidad del material compactado, lo que facilita el control preciso de la compactación y la trazabilidad de los trabajos. Evib - MN/m2 | N8: Telematics | O8: Economizer, TERRAMETER (Evib real), VARIOCONTROL, ECOMODE, TELEMATIC | Q8: Operación Intuitiva * Un switch para cada función * Símbolos intuitivos facilitan la operación | R8: Rendimiento de compactación más alto * Máximas amplitudes para un efecto de compactación más profundo (Larger amplitud 2,2 mm) * Flexibilidad en el montaje del kit pata de cabra | S8: Junta de articulación libre de mantenimiento | T8: Trabajo comfortable y seguro * Espacio de trabajo amplio y con excelente visibilidad | U8: Compactación eficiente Medición y documentación en tiempo real usando: ECONOMIZER, TERRAMETER y BOMAP | V8: Fácil mantenimiento * Todos los componentes dispuestos para un fácil acceso * Menos mantenimiento en el sistema de refrigeración debido al el punto alto de entrada de aire, menos propenso a contaminación | W8: 60 | X8: 270 - 540 | Y8: 12.4 | Z8: 72948 | AA8: 1 | AB8: 2 | AC8: 3000 | AD8: 126588
A9: =B9&" | "&C9 -> BOMAG | BW216 D-5 SL | B9: BOMAG | C9: BW216 D-5 SL | E9: 14850 | F9: Deutz TCD 2013 L04 | G9: 2.13 | H9: 162 | I9: 1.90 / 0.96 | J9: 50.2 | L9: - | M9: BOMAG ECONOMIZER Sistema visual que permite a los operadores medir el progreso de la compactación en tiempo real. Utiliza una escala LED en la cabina para mostrar el nivel de compactación alcanzado, ayudando a evitar sobrecompacción o subcompactación. (Estandar) BOMAG TERRAMETER Sistema que mide la rigidez del suelo mediante la vibración del tambor. Ofrece una lectura en tiempo real del módulo de elasticidad del material compactado, lo que facilita el control preciso de la compactación y la trazabilidad de los trabajos. Evib - MN/m2 | N9: Telematics | O9: Economizer, TERRAMETER (Evib real), VARIOCONTROL, ECOMODE, TELEMATIC | Q9: Operación Intuitiva * Un switch para cada función * Símbolos intuitivos facilitan la operación | R9: Rendimiento de compactación más alto * Máximas amplitudes para un efecto de compactación más profundo (Larger amplitud 2,2 mm) * Flexibilidad en el montaje del kit pata de cabra | S9: Junta de articulación libre de mantenimiento | T9: Trabajo comfortable y seguro * Espacio de trabajo amplio y con excelente visibilidad | U9: Compactación eficiente Medición y documentación en tiempo real usando: ECONOMIZER, TERRAMETER y BOMAP | V9: Fácil mantenimiento * Todos los componentes dispuestos para un fácil acceso * Menos mantenimiento en el sistema de refrigeración debido al el punto alto de entrada de aire, menos propenso a contaminación | X9: - | Y9: 0 | Z9: 0 | AA9: 1 | AB9: 2 | AC9: 3000 | AD9: 0
A10: =B10&" | "&C10 -> BOMAG | BW219 D-5 PL | B10: BOMAG | C10: BW219 D-5 PL | E10: 19400 | F10: Deutz TCD 2012 L06 | G10: 2.13 | H10: 202 | I10: 2.10 / 1.20 | J10: 60.1 | L10: - | M10: BOMAG ECONOMIZER Sistema visual que permite a los operadores medir el progreso de la compactación en tiempo real. Utiliza una escala LED en la cabina para mostrar el nivel de compactación alcanzado, ayudando a evitar sobrecompacción o subcompactación. (Estandar) BOMAG TERRAMETER Sistema que mide la rigidez del suelo mediante la vibración del tambor. Ofrece una lectura en tiempo real del módulo de elasticidad del material compactado, lo que facilita el control preciso de la compactación y la trazabilidad de los trabajos. Evib - MN/m2 | N10: Telematics | O10: Economizer, TERRAMETER (Evib real), VARIOCONTROL, ECOMODE, TELEMATIC | Q10: Operación Intuitiva * Un switch para cada función * Símbolos intuitivos facilitan la operación | R10: Rendimiento de compactación más alto * Máximas amplitudes para un efecto de compactación más profundo (Larger amplitud 2,2 mm) * Flexibilidad en el montaje del kit pata de cabra | S10: Junta de articulación libre de mantenimiento | T10: Trabajo comfortable y seguro * Espacio de trabajo amplio y con excelente visibilidad | U10: Compactación eficiente Medición y documentación en tiempo real usando: ECONOMIZER, TERRAMETER y BOMAP | V10: Fácil mantenimiento * Todos los componentes dispuestos para un fácil acceso * Menos mantenimiento en el sistema de refrigeración debido al el punto alto de entrada de aire, menos propenso a contaminación | X10: - | Y10: 0 | Z10: 0 | AA10: 1 | AB10: 2 | AC10: 3000 | AD10: 0
A11: =B11&" | "&C11 -> BOMAG | BW220 D-5 PL | B11: BOMAG | C11: BW220 D-5 PL | E11: 20100 | F11: Deutz TCD 2012 L06 | G11: 2.13 | H11: 202 | I11: 2.10 / 1.20 | J11: 61.8 | L11: - | M11: BOMAG ECONOMIZER Sistema visual que permite a los operadores medir el progreso de la compactación en tiempo real. Utiliza una escala LED en la cabina para mostrar el nivel de compactación alcanzado, ayudando a evitar sobrecompacción o subcompactación. (Estandar) BOMAG TERRAMETER Sistema que mide la rigidez del suelo mediante la vibración del tambor. Ofrece una lectura en tiempo real del módulo de elasticidad del material compactado, lo que facilita el control preciso de la compactación y la trazabilidad de los trabajos. Evib - MN/m2 | N11: Telematics | O11: Economizer, TERRAMETER (Evib real), VARIOCONTROL, ECOMODE, TELEMATIC | Q11: Operación Intuitiva * Un switch para cada función * Símbolos intuitivos facilitan la operación | R11: Rendimiento de compactación más alto * Máximas amplitudes para un efecto de compactación más profundo (Larger amplitud 2,2 mm) * Flexibilidad en el montaje del kit pata de cabra | S11: Junta de articulación libre de mantenimiento | T11: Trabajo comfortable y seguro * Espacio de trabajo amplio y con excelente visibilidad | U11: Compactación eficiente Medición y documentación en tiempo real usando: ECONOMIZER, TERRAMETER y BOMAP | V11: Fácil mantenimiento * Todos los componentes dispuestos para un fácil acceso * Menos mantenimiento en el sistema de refrigeración debido al el punto alto de entrada de aire, menos propenso a contaminación | X11: - | Y11: 0 | Z11: 0 | AA11: 1 | AB11: 2 | AC11: 3000 | AD11: 0
A12: =B12&" | "&C12 -> SAKAI | SV521D | B12: SAKAI | C12: SV521D | E12: 10720 | F12: ISUZU 4BG1T (Tier 2) | G12: 2.3 | H12: 118 | I12: 2.05/0.90 | J12: 28 | L12: - | M12: No aplica | N12: - | Q12: Especificaciones técnicas * Motor ISUZU 4BG1T (Tier 2) * 118 HP * Peso operativo 10,720 kg | R12: Rendimiento de compactación * Amplitud 2.05/0.90 mm * Fuerza centrífuga 260/ kN * Carga lineal estática 28 kg/cm | X12: - | Y12: 0 | Z12: 0 | AA12: 1 | AB12: 2 | AC12: 3000 | AD12: 0
A13: =B13&" | "&C13 -> SAKAI | SV621D | B13: SAKAI | C13: SV621D | E13: 13020 | F13: ISUZU 4BG1T (Tier 2) | G13: 2.3 | H13: 131 | I13: 2.03/0.90 | J13: 34 | L13: - | M13: No aplica | N13: - | Q13: Especificaciones técnicas * Motor ISUZU 4BG1T (Tier 2) * 131 HP * Peso operativo 13,020 kg | R13: Rendimiento de compactación * Amplitud 2.03/0.90 mm * Fuerza centrífuga 260/ kN * Carga lineal estática 34 kg/cm | X13: - | Y13: 0 | Z13: 0 | AA13: 1 | AB13: 2 | AC13: 3000 | AD13: 0
A14: =B14&" | "&C14 -> SAKAI | SV700D | B14: SAKAI | C14: SV700D | E14: 14950 | F14: ISUZU BB-6BG1TRJ | G14: 2.13 | H14: 217 | I14: 2.0 / 0.9 | J14: 39.9 | L14: India | M14: No aplica | N14: - | Q14: Especificaciones técnicas * Motor ISUZU BB-6BG1TRJ * 217 HP * Peso operativo 14,950 kg | R14: Rendimiento de compactación * Amplitud 2.0 / 0.9 mm * Fuerza centrífuga 275 / 220 kN * Carga lineal estática 39.9 kg/cm | X14: - | Y14: 0 | Z14: 0 | AA14: 1 | AB14: 2 | AC14: 3000 | AD14: 0
A15: =B15&" | "&C15 -> SAKAI | SV900-1 | B15: SAKAI | C15: SV900-1 | E15: 19350 | F15: ISUZU AH-4HK1XYLB-01 | G15: 2.13 | H15: 166 | I15: 1.9 / 1.0 | J15: 51.4 | L15: - | M15: No aplica | N15: - | Q15: Especificaciones técnicas * Motor ISUZU AH-4HK1XYLB-01 * 166 HP * Peso operativo 19,350 kg | R15: Rendimiento de compactación * Amplitud 1.9 / 1.0 mm * Fuerza centrífuga 343 / 245 kN * Carga lineal estática 51.4 kg/cm | X15: - | Y15: 0 | Z15: 0 | AA15: 1 | AB15: 2 | AC15: 3000 | AD15: 0
A16: =B16&" | "&C16 -> DYNAPAC | CA25 D-Rhino | B16: DYNAPAC | C16: CA25 D-Rhino | E16: 10400 | F16: Cummins QSF3.8 (T3) | G16: 2.13 | H16: 130 | I16: 1.8/0.9 | J16: 51.4 | K16: 41 | L16: Suecia/Brasil | M16: No aplica Dynapac Compaction Meter (DCM) utiliza un sensor acelerómetro montado en el tambor del compactador, que mide las vibraciones generadas durante la operación. Estas señales se procesan y se presentan como CMV Cuando el CMV deja de aumentar, se considera que se ha alcanzado la compactación | N16: Dyn@lizer | O16: Dynapac Compaction meter (DCM), Dyn@lyzer | Q16: Controles intuitivos: Palancas simples y panel de instrumentos con indicadores claros, fáciles de operar incluso por personal con poca experiencia. | R16: Compactación efectiva * Gracias a su peso operativo y potencia, logra una compactación eficiente en menos pasadas. * Amplitud dual: Permite seleccionar entre alta y baja amplitud para distintos materiales (granulares vs cohesivos), optimizando el rendimiento. | S16: Junta de articulación Ofrece un radio de giro estrecho y seguimiento preciso del terreno. | T16: Control y confort de operación * Ofrece visibilidad total del tambor y área de trabajo. El DCM utiliza un sensor acelerómetro montado en el tambor del compactador, que mide las vibraciones generadas durante la operación | V16: Mantenimiento y Servicio Diseño de fácil acceso: El capó del motor se abre completamente, permitiendo un acceso rápido a los puntos de mantenimiento diario (filtros, niveles, correas). | W16: 55 | X16: 220 - 350 | Y16: 13.6 | Z16: 90000 | AA16: 1 | AB16: 2 | AC16: 3000 | AD16: 160200
A17: =B17&" | "&C17 -> DYNAPAC | CA35 D-Rhino | B17: DYNAPAC | C17: CA35 D-Rhino | E17: 12200 | F17: Cummins QSF3.8 | G17: 2.13 | H17: 130 | I17: 1.7/0.8 | J17: 35 | K17: 46 | L17: Suecia/Brasil | M17: No aplica Dynapac Compaction Meter (DCM) utiliza un sensor acelerómetro montado en el tambor del compactador, que mide las vibraciones generadas durante la operación. Estas señales se procesan y se presentan como CMV Cuando el CMV deja de aumentar, se considera que se ha alcanzado la compactación | N17: Dyn@lizer | O17: Dynapac Compaction meter (DCM), Dyn@lyzer | Q17: Controles intuitivos: Palancas simples y panel de instrumentos con indicadores claros, fáciles de operar incluso por personal con poca experiencia. | R17: Compactación efectiva * Gracias a su peso operativo y potencia, logra una compactación eficiente en menos pasadas. * Amplitud dual: Permite seleccionar entre alta y baja amplitud para distintos materiales (granulares vs cohesivos), optimizando el rendimiento. | S17: Junta de articulación Ofrece un radio de giro estrecho y seguimiento preciso del terreno. | T17: Control y confort de operación * Ofrece visibilidad total del tambor y área de trabajo. El DCM utiliza un sensor acelerómetro montado en el tambor del compactador, que mide las vibraciones generadas durante la operación | V17: Mantenimiento y Servicio Diseño de fácil acceso: El capó del motor se abre completamente, permitiendo un acceso rápido a los puntos de mantenimiento diario (filtros, niveles, correas). | W17: 55 | X17: 220 - 350 | Y17: 13.6 | Z17: 90000 | AA17: 1 | AB17: 2 | AC17: 3000 | AD17: 160200
A18: =B18&" | "&C18 -> DYNAPAC | CA2500D | B18: DYNAPAC | C18: CA2500D | E18: 10000 | F18: Cummins QSB4.5 | G18: 2.13 | H18: 130 | I18: 1.80/0.90 | J18: 26 | L18: - | M18: No aplica | N18: - | Q18: Especificaciones técnicas * Motor Cummins QSB4.5 * 130 HP * Peso operativo 10,000 kg | R18: Rendimiento de compactación * Amplitud 1.80/0.90 mm * Fuerza centrífuga 205/100 kN * Carga lineal estática 26 kg/cm | X18: - | Y18: 0 | Z18: 0 | AA18: 1 | AB18: 2 | AC18: 3000 | AD18: 0
A19: =B19&" | "&C19 -> DYNAPAC | CA3500D | B19: DYNAPAC | C19: CA3500D | E19: 16000 | F19: Cummins QSB6.7 | G19: 2.13 | H19: 174 | I19: 2.00/0.95 | J19: 37.5 | K19: 46 | L19: Suecia/Brasil | M19: No aplica Dynapac Compaction Meter (DCM) utiliza un sensor acelerómetro montado en el tambor del compactador, que mide las vibraciones generadas durante la operación. Estas señales se procesan y se presentan como CMV Cuando el CMV deja de aumentar, se considera que se ha alcanzado la compactación | N19: Dyn@lizer | O19: Dynapac Compaction meter (DCM), Dyn@lyzer | Q19: Controles intuitivos: Palancas simples y panel de instrumentos con indicadores claros, fáciles de operar incluso por personal con poca experiencia. | R19: Compactación efectiva * Gracias a su peso operativo y potencia, logra una compactación eficiente en menos pasadas. * Amplitud dual: Permite seleccionar entre alta y baja amplitud para distintos materiales (granulares vs cohesivos), optimizando el rendimiento. | S19: Junta de articulación Ofrece un radio de giro estrecho y seguimiento preciso del terreno. | T19: Control y confort de operación * Ofrece visibilidad total del tambor y área de trabajo. El DCM utiliza un sensor acelerómetro montado en el tambor del compactador, que mide las vibraciones generadas durante la operación | V19: Mantenimiento y Servicio Diseño de fácil acceso: El capó del motor se abre completamente, permitiendo un acceso rápido a los puntos de mantenimiento diario (filtros, niveles, correas). | W19: 55 | X19: 220 - 350 | Y19: 13.6 | Z19: 90000 | AA19: 1 | AB19: 2 | AC19: 3000 | AD19: 160200
A20: =B20&" | "&C20 -> DYNAPAC | CA4500D | B20: DYNAPAC | C20: CA4500D | E20: 21000 | F20: Cummins QSC8.3 | G20: 2.13 | H20: 250 | I20: 2.10/1.05 | J20: 49.3 | L20: - | M20: No aplica | N20: - | Q20: Especificaciones técnicas * Motor Cummins QSC8.3 * 250 HP * Peso operativo 21,000 kg | R20: Rendimiento de compactación * Amplitud 2.10/1.05 mm * Fuerza centrífuga 340/170 kN * Carga lineal estática 49.3 kg/cm | X20: - | Y20: 0 | Z20: 0 | AA20: 1 | AB20: 2 | AC20: 3000 | AD20: 0
A21: =B21&" | "&C21 -> DYNAPAC REDLINE | DRS120D | B21: DYNAPAC REDLINE | C21: DRS120D | E21: 11400 | F21: Dynapac 4-cyl turbo | G21: 2.13 | H21: 105 | I21: - | J21: 32 | L21: India | M21: No aplica | N21: - | Q21: Especificaciones técnicas * Motor Dynapac 4-cyl turbo * 105 HP * Peso operativo 11,400 kg | R21: Rendimiento de compactación * Carga lineal estática 32 kg/cm | X21: - | Y21: 0 | Z21: 0 | AA21: 1 | AB21: 2 | AC21: 3000 | AD21: 0
A22: =B22&" | "&C22 -> HAMM | HC110 | B22: HAMM | C22: HC110 | E22: 11765 | F22: JDPS 4045PTE | G22: 2.14 | H22: 135.4 | I22: 1.95/0.85 | J22: 29.81 | K22: 58 | L22: Alemania | M22: No aplica HAMM SmartCompaction Value (Solo si es Serie VA) El sistema determina el valor de capacidad de carga actual SCV (Smart Compaction Value) del suelo en MN/m². A continuación, el asistente de compactación coloca automáticamente el sistema de desequilibrio en el tambor VA especialmente desarrollado en todas las situaciones, de modo que siempre oscile con la amplitud óptima | N22: Smart Doc | O22: EcoStop, SmartCompaction, vibración adaptativa | Q22: Conducción y maniobrabilidad * Bloqueo integrado de la articulación pendular * Control de tracción para una óptima transmisión de potencia | R22: Calidad de compactación * Asistente Smart Compact para el ajuste automático de la potencia de compactación *Alta carga lineal y fuerza centrífuga | S22: Articulación pendular de 3 puntos para una estabilidad direccional superior | T22: Control y confort * Gran espacio y comodidad de uso * Condiciones de trabajo ergonómicamente optimizadas gracias a su concepto operativo Easy Drive | U22: Sistema de asistencia de compactación Interfaces digitales * John Deere Operations CenterTM * Track Assist & WPT Compacting * Smart Compact | V22: Mantenimiento eficiente Todos los puntos de mantenimiento, la refrigeración de aceite y de agua y la batería son cómodamente accesibles y están concentrados en un lado de la máquina | W22: 60 | X22: 250 - 400 | Y22: 13.6 | Z22: 91845.1 | AA22: 1 | AB22: 2 | AC22: 3000 | AD22: 149805.1
A23: =B23&" | "&C23 -> HAMM | HC119 | B23: HAMM | C23: HC119 | E23: 11745 | F23: Cummins QSB4.5 | G23: 2.14 | H23: 121 | I23: 1.90/0.90 | J23: 29.1 | K23: 58 | L23: Alemania | M23: No aplica HAMM SmartCompaction Value (Solo si es Serie VA) El sistema determina el valor de capacidad de carga actual SCV (Smart Compaction Value) del suelo en MN/m². A continuación, el asistente de compactación coloca automáticamente el sistema de desequilibrio en el tambor VA especialmente desarrollado en todas las situaciones, de modo que siempre oscile con la amplitud óptima | N23: Smart Doc | O23: EcoStop, SmartCompaction, vibración adaptativa | Q23: Conducción y maniobrabilidad * Bloqueo integrado de la articulación pendular * Control de tracción para una óptima transmisión de potencia | R23: Calidad de compactación * Asistente Smart Compact para el ajuste automático de la potencia de compactación *Alta carga lineal y fuerza centrífuga | S23: Articulación pendular de 3 puntos para una estabilidad direccional superior | T23: Control y confort * Gran espacio y comodidad de uso * Condiciones de trabajo ergonómicamente optimizadas gracias a su concepto operativo Easy Drive | U23: Sistema de asistencia de compactación Interfaces digitales * John Deere Operations CenterTM * Track Assist & WPT Compacting * Smart Compact | V23: Mantenimiento eficiente Todos los puntos de mantenimiento, la refrigeración de aceite y de agua y la batería son cómodamente accesibles y están concentrados en un lado de la máquina | W23: 60 | X23: 250 - 400 | Y23: 13.6 | Z23: 91845.1 | AA23: 1 | AB23: 2 | AC23: 3000 | AD23: 149805.1
A24: =B24&" | "&C24 -> HAMM | H13i | B24: HAMM | C24: H13i | E24: 12600 | F24: Deutz TCD2012 | G24: 2.13 | H24: 130 | I24: 1.90/0.80 | J24: 29.6 | L24: - | M24: No aplica | N24: - | Q24: Especificaciones técnicas * Motor Deutz TCD2012 * 130 HP * Peso operativo 12,600 kg | R24: Rendimiento de compactación * Amplitud 1.90/0.80 mm * Fuerza centrífuga 213/90 kN * Carga lineal estática 29.6 kg/cm | X24: - | Y24: 0 | Z24: 0 | AA24: 1 | AB24: 2 | AC24: 3000 | AD24: 0
A25: =B25&" | "&C25 -> HAMM | H16i | B25: HAMM | C25: H16i | E25: 16430 | F25: Deutz TCD3.6 L6 | G25: 2.14 | H25: 168 | I25: 2.13/0.95 | J25: 38.4 | L25: India | M25: No aplica | N25: - | Q25: Especificaciones técnicas * Motor Deutz TCD3.6 L6 * 168 HP * Peso operativo 16,430 kg | R25: Rendimiento de compactación * Amplitud 2.13/0.95 mm * Fuerza centrífuga 328/150 kN * Carga lineal estática 38.4 kg/cm | X25: - | Y25: 0 | Z25: 0 | AA25: 1 | AB25: 2 | AC25: 3000 | AD25: 0
A26: =B26&" | "&C26 -> HAMM | H18i | B26: HAMM | C26: H18i | E26: 18000 | F26: Deutz TCD3.6 | G26: 2.14 | H26: 215 | I26: 2.10/0.90 | J26: 42.1 | L26: India | M26: No aplica | N26: - | Q26: Especificaciones técnicas * Motor Deutz TCD3.6 * 215 HP * Peso operativo 18,000 kg | R26: Rendimiento de compactación * Amplitud 2.10/0.90 mm * Fuerza centrífuga 354/160 kN * Carga lineal estática 42.1 kg/cm | X26: - | Y26: 0 | Z26: 0 | AA26: 1 | AB26: 2 | AC26: 3000 | AD26: 0
A27: =B27&" | "&C27 -> HAMM | H25i | B27: HAMM | C27: H25i | E27: 24925 | F27: Liebherr D946 | G27: 2.14 | H27: 215 | I27: 2.00/0.90 | J27: 58.3 | L27: - | M27: No aplica | N27: - | Q27: Especificaciones técnicas * Motor Liebherr D946 * 215 HP * Peso operativo 24,925 kg | R27: Rendimiento de compactación * Amplitud 2.00/0.90 mm * Fuerza centrífuga 380/190 kN * Carga lineal estática 58.3 kg/cm | X27: - | Y27: 0 | Z27: 0 | AA27: 1 | AB27: 2 | AC27: 3000 | AD27: 0
A28: =B28&" | "&C28 -> CATERPILLAR | CS10GC | B28: CATERPILLAR | C28: CS10GC | E28: 10492 | F28: Cat C4.4 | G28: 2.13 | H28: 112.4 | I28: 2.0/1.0 | J28: 27.3 | K28: 55 | L28: China | M28: CAT Machine Drive Power (MDP) Este sistema mide la resistencia del terreno durante la compactación, proporcionando datos en tiempo real sobre la capacidad de trabajo del equipo y las condiciones del suelo. Permite ajustar la intensidad de la compactación para evitar sobrecarga en el motor y mejorar la eficiencia. (Opcional) CAT Compaction Meter Value (CMV) Sistema que mide en tiempo real la rigidez del suelo a medida que el tambor vibrante pasa sobre él. El valor se muestra en la cabina, permitiendo a los operadores monitorear el progreso de la compactación. | N28: Vision Link | O28: MDP, CMV, AccuGrade Compaction, Eco-mode, Vision Link | Q28: Controles ergonómicos y simples: * Palanca de control única para avance, vibración y dirección. * Instrumentación digital fácil de leer. | R28: Mayor carga lineal estática Tambor de alto peso y excelente contacto con el suelo para lograr profundidad efectiva de compactación. | S28: Junta de articulación libre de mantenimiento | T28: Plataforma con asiento ajustable, controles a mano, y excelente visibilidad de 360°. Vibración automática (Auto Vibe): El sistema puede activar/desactivar la vibración de forma automática según la velocidad del rodillo o si está detenido, mejorando el control del proces | U28: * Amplitud más alta del mercado * MDP exclusivo de CAT: Mide la resistencia al avance del tambor como un indicador directo del nivel de compactación (ventaja clave frente a modelos tradicionales). | V28: Mantenimiento y Servicio Diseño orientado a bajo mantenimiento: * Intervalos de mantenimiento extendidos. * Reducción de puntos de lubricación gracias al uso de componentes sellados. | W28: 60 | X28: 200 | Y28: 14.5 | Z28: 105298.85 | AA28: 1 | AB28: 2 | AC28: 3000 | AD28: 179548.85
A29: =B29&" | "&C29 -> CATERPILLAR | CS11GC | B29: CATERPILLAR | C29: CS11GC | E29: 10900 | F29: Cat C4.4 (Tier 3) | G29: 2.13 | H29: 74 | I29: 1.88/0.91 | J29: 25.6 | K29: 55 | L29: China | M29: CAT Machine Drive Power (MDP) Este sistema mide la resistencia del terreno durante la compactación, proporcionando datos en tiempo real sobre la capacidad de trabajo del equipo y las condiciones del suelo. Permite ajustar la intensidad de la compactación para evitar sobrecarga en el motor y mejorar la eficiencia. (Opcional) CAT Compaction Meter Value (CMV) Sistema que mide en tiempo real la rigidez del suelo a medida que el tambor vibrante pasa sobre él. El valor se muestra en la cabina, permitiendo a los operadores monitorear el progreso de la compactación. | N29: Vision Link | O29: CMV, AccuGrade Compaction, Eco-mode, Vision Link | Q29: Controles ergonómicos y simples: * Palanca de control única para avance, vibración y dirección. * Pantalla integranda en palanca de control. * Cambio de velocidad asistida * Instrumentación digital fácil de leer. | R29: Mayor carga lineal estática Tambor de alto peso y excelente contacto con el suelo para lograr profundidad efectiva de compactación. | S29: Junta de articulación libre de mantenimiento | T29: Plataforma con asiento ajustable, controles a mano, y excelente visibilidad de 360°. Vibración automática (Auto Vibe): El sistema puede activar/desactivar la vibración de forma automática según la velocidad del rodillo o si está detenido, mejorando el control del proces | U29: * Amplitud más alta del mercado * MDP exclusivo de CAT: Mide la resistencia al avance del tambor como un indicador directo del nivel de compactación (ventaja clave frente a modelos tradicionales). | V29: Mantenimiento y Servicio Diseño orientado a bajo mantenimiento: * Intervalos de mantenimiento extendidos. * Reducción de puntos de lubricación gracias al uso de componentes sellados. | W29: 60 | X29: 200 | Y29: 14.5 | Z29: 105298.85 | AA29: 1 | AB29: 2 | AC29: 3000 | AD29: 179548.85
A30: =B30&" | "&C30 -> CATERPILLAR | CS12 | B30: CATERPILLAR | C30: CS12 | E30: 11743 | F30: Cat C7.1 | G30: 2.13 | H30: 157.6 | I30: 2.1/0.98 | J30: 29.7 | K30: 57 | L30: China | M30: No aplica CAT Compaction Meter Value (CMV) Sistema que mide en tiempo real la rigidez del suelo a medida que el tambor vibrante pasa sobre él. El valor se muestra en la cabina, permitiendo a los operadores monitorear el progreso de la compactación. | N30: Vision Link | O30: MDP, CMV, AccuGrade Compaction, Eco-mode, Vision Link | Q30: Controles ergonómicos y simples: * Palanca de control única para avance, vibración y dirección. * Instrumentación digital fácil de leer. | R30: Diseñado con un sistema de propulsión de doble bomba, las dos bombas suministran un flujo separado y dedicado al motor de accionamiento del tambor y al motor del eje trasero, lo que garantiza una capacidad de ascenso y tracción excepcionales tanto en avance como en retroceso | S30: Junta de articulación libre de mantenimiento | T30: Plataforma con asiento ajustable, controles a mano, y excelente visibilidad de 360°. Vibración automática (Auto Vibe): El sistema puede activar/desactivar la vibración de forma automática según la velocidad del rodillo o si está detenido, mejorando el control del proces | U30: * Amplitud más alta del mercado | V30: Mantenimiento y Servicio Diseño orientado a bajo mantenimiento: * Intervalos de mantenimiento extendidos. * Reducción de puntos de lubricación gracias al uso de componentes sellados. | W30: 60 | X30: 200 | Y30: 14.5 | Z30: 105298.85 | AA30: 1 | AB30: 2 | AC30: 3000 | AD30: 179548.85
A31: =B31&" | "&C31 -> CATERPILLAR | CS13GC | B31: CATERPILLAR | C31: CS13GC | E31: 12700 | F31: Cat C4.4 (Tier 3) | G31: 2.13 | H31: 100 | I31: 2.10/1.05 | J31: 30 | L31: India | M31: No aplica | N31: - | Q31: Especificaciones técnicas * Motor Cat C4.4 (Tier 3) * 100 HP * Peso operativo 12,700 kg | R31: Rendimiento de compactación * Amplitud 2.10/1.05 mm * Fuerza centrífuga 208/100 kN * Carga lineal estática 30 kg/cm | X31: - | Y31: 0 | Z31: 0 | AA31: 1 | AB31: 2 | AC31: 3000 | AD31: 0
A32: =B32&" | "&C32 -> XCMG | XS113E | B32: XCMG | C32: XS113E | E32: 10400 | F32: Weichai WP4 | G32: 2.13 | H32: 110 | I32: 1.80/0.90 | J32: 0 | K32: 45 | L32: Brasil | M32: No aplica No aplica | N32: - | O32: XCMG Telematics | Q32: Diseño robusto, excelente acceso a mantenimiento y componentes estandarizados para máxima disponibilidad en campo. | R32: Calidad de Compactación * Rendimiento adecuado para compactación de capas gruesas y materiales cohesivos. * Diseño del tambor que reduce rebotes y mejora la uniformidad. | S32: Junta de Articulación Articulación oscilante de diseño robusto. | T32: Control y Confort * Cabina opcional con buena visibilidad. * Panel de instrumentos digital con indicadores de trabajo. * Asiento ajustable, pero menor confort que modelos premium. | U32: - | V32: Mantenimiento y Servicio Capó lateral basculante, acceso rápido a motor y componentes hidráulicos. Módulos eléctricos centralizados. Motores Weichai o Cummins con buena cobertura de repuestos. | W32: 50 | X32: 250 - 400 | Y32: 13.6 | Z32: 54786 | AA32: 1 | AB32: 2 | AC32: 3000 | AD32: 124986
A33: =B33&" | "&C33 -> XCMG | XS123 | B33: XCMG | C33: XS123 | E33: 12000 | F33: Cummins QSF3.8 | G33: 2.13 | H33: 139 | I33: 1.8/0.9 | J33: 31.5 | K33: 45 | L33: Brasil | M33: No aplica No aplica | N33: - | O33: XCMG Telematics | Q33: Diseño robusto, excelente acceso a mantenimiento y componentes estandarizados para máxima disponibilidad en campo. | R33: Calidad de Compactación * Rendimiento adecuado para compactación de capas gruesas y materiales cohesivos. * Diseño del tambor que reduce rebotes y mejora la uniformidad. | S33: Junta de Articulación Articulación oscilante de diseño robusto. | T33: Control y Confort * Cabina opcional con buena visibilidad. * Panel de instrumentos digital con indicadores de trabajo. * Asiento ajustable, pero menor confort que modelos premium. | U33: - | V33: Mantenimiento y Servicio Capó lateral basculante, acceso rápido a motor y componentes hidráulicos. Módulos eléctricos centralizados. Motores Weichai o Cummins con buena cobertura de repuestos. | W33: 50 | X33: 250 - 400 | Y33: 13.6 | Z33: 54786 | AA33: 1 | AB33: 2 | AC33: 3000 | AD33: 124986
A34: =B34&" | "&C34 -> XCMG | XS143J | B34: XCMG | C34: XS143J | E34: 14000 | F34: Cummins B5.9 | G34: 2.13 | H34: 150 | I34: 1.90/0.95 | J34: 0 | L34: India | M34: No aplica | N34: - | Q34: Especificaciones técnicas * Motor Cummins B5.9 * 150 HP * Peso operativo 14,000 kg | R34: Rendimiento de compactación * Amplitud 1.90/0.95 mm * Fuerza centrífuga 230/115 kN | X34: - | Y34: 0 | Z34: 0 | AA34: 1 | AB34: 2 | AC34: 3000 | AD34: 0
A35: =B35&" | "&C35 -> XCMG | XS162J | B35: XCMG | C35: XS162J | E35: 16000 | F35: Cummins B5.9 | G35: 2.13 | H35: 161 | I35: 2.00/0.95 | J35: 0 | L35: - | M35: No aplica | N35: - | Q35: Especificaciones técnicas * Motor Cummins B5.9 * 161 HP * Peso operativo 16,000 kg | R35: Rendimiento de compactación * Amplitud 2.00/0.95 mm * Fuerza centrífuga 260/130 kN | X35: - | Y35: 0 | Z35: 0 | AA35: 1 | AB35: 2 | AC35: 3000 | AD35: 0
A36: =B36&" | "&C36 -> XCMG | XS182 | B36: XCMG | C36: XS182 | E36: 18000 | F36: Cummins B5.9 | G36: 2.13 | H36: 174 | I36: 1.86/ | J36: 53.9 | L36: - | M36: No aplica | N36: - | Q36: Especificaciones técnicas * Motor Cummins B5.9 * 174 HP * Peso operativo 18,000 kg | R36: Rendimiento de compactación * Amplitud 1.86/ mm * Carga lineal estática 53.9 kg/cm | X36: - | Y36: 0 | Z36: 0 | AA36: 1 | AB36: 2 | AC36: 3000 | AD36: 0
A37: =B37&" | "&C37 -> XCMG | XS203J | B37: XCMG | C37: XS203J | E37: 20000 | F37: Cummins QSB6.7 | G37: 2.13 | H37: 200 | I37: 2.00/1.00 | J37: 0 | L37: - | M37: No aplica | N37: - | Q37: Especificaciones técnicas * Motor Cummins QSB6.7 * 200 HP * Peso operativo 20,000 kg | R37: Rendimiento de compactación * Amplitud 2.00/1.00 mm * Fuerza centrífuga 310/155 kN | X37: - | Y37: 0 | Z37: 0 | AA37: 1 | AB37: 2 | AC37: 3000 | AD37: 0
A38: =B38&" | "&C38 -> SANY | SSR120C-8 | B38: SANY | C38: SSR120C-8 | E38: 11580 | F38: Cummins QSB4.5 | G38: 2.13 | H38: 145 | I38: 1.80/0.90 | J38: 0 | L38: India | M38: No aplica | N38: - | Q38: Especificaciones técnicas * Motor Cummins QSB4.5 * 145 HP * Peso operativo 11,580 kg | R38: Rendimiento de compactación * Amplitud 1.80/0.90 mm * Fuerza centrífuga 190/95 kN | X38: - | Y38: 0 | Z38: 0 | AA38: 1 | AB38: 2 | AC38: 3000 | AD38: 0
A39: =B39&" | "&C39 -> SANY | SSR120C-10 | B39: SANY | C39: SSR120C-10 | E39: 12000 | F39: ISUZU 4JJ1 | G39: 2.13 | H39: 130 | I39: 1.80/0.90 | J39: 0 | L39: India | M39: No aplica | N39: - | Q39: Especificaciones técnicas * Motor ISUZU 4JJ1 * 130 HP * Peso operativo 12,000 kg | R39: Rendimiento de compactación * Amplitud 1.80/0.90 mm * Fuerza centrífuga 205/100 kN | X39: - | Y39: 0 | Z39: 0 | AA39: 1 | AB39: 2 | AC39: 3000 | AD39: 0
A40: =B40&" | "&C40 -> SANY | SSR120C-10S | B40: SANY | C40: SSR120C-10S | E40: 12400 | F40: DONGFENG CUMMINS QSB3.9-C150-3 | G40: 2.13 | H40: 110 | I40: 1.8/0.9 | J40: 33.2 | K40: 65 | L40: China/Brasil | M40: No aplica No aplica | N40: - | O40: Tracción automática, vibración doble, telematics-ready | Q40: Controles fáciles de usar: * Palanca tipo joystick para dirección, vibración y cambio de marcha. | R40: Calidad de compactación * Fuerza centrífuga hasta 320 kN, una de las más altas del segmento. * Sistema de vibración confiable con buena transferencia de energía. * Distribución de peso balanceada para compactación uniforme. | S40: Articulación con oscilación hidráulica y gran ángulo de giro. | T40: Control y Confort * Cabina cerrada ROPS/FOPS opcional con aire acondicionado y asiento neumático. * Palanca tipo joystick para dirección, vibración y cambio de marcha. * Bajo nivel de vibración transmitida al operador. | U40: Sistema inteligente de control de vibración que ajusta la potencia según la resistencia del suelo, evitando sobrecompactación. | V40: Mantenimiento y Servicio * Capó de apertura total con acceso a 3 lados del motor. * Sistema de diagnóstico electrónico desde la pantalla de control. * Componentes hidráulicos y eléctricos dispuestos para fácil inspección. | W40: 60 | X40: 300 - 500 | Y40: 15.3 | Z40: 56392 | AA40: 1 | AB40: 2 | AC40: 3000 | AD40: 134242
A41: =B41&" | "&C41 -> SHANTUI | SR16 | B41: SHANTUI | C41: SR16 | E41: 16000 | F41: Cummins QSB6.7 | G41: 2 | H41: 168 | I41: 2.0/0.9 | J41: 0 | L41: India | M41: No aplica | N41: - | Q41: Especificaciones técnicas * Motor Cummins QSB6.7 * 168 HP * Peso operativo 16,000 kg | R41: Rendimiento de compactación * Amplitud 2.0/0.9 mm | X41: - | Y41: 0 | Z41: 0 | AA41: 1 | AB41: 2 | AC41: 3000 | AD41: 0
A42: =B42&" | "&C42 -> SHANTUI | SR22 | B42: SHANTUI | C42: SR22 | E42: 22000 | F42: Cummins QSC8.3 | G42: 2.13 | H42: 236 | I42: 2.1/1.0 | J42: 0 | L42: India | M42: No aplica | N42: - | Q42: Especificaciones técnicas * Motor Cummins QSC8.3 * 236 HP * Peso operativo 22,000 kg | R42: Rendimiento de compactación * Amplitud 2.1/1.0 mm | X42: - | Y42: 0 | Z42: 0 | AA42: 1 | AB42: 2 | AC42: 3000 | AD42: 0
A43: =B43&" | "&C43 -> JCB | 116D | B43: JCB | C43: 116D | E43: 11560 | F43: JCB DIESELMAX TCA-85 | G43: 2.1 | H43: 114 | I43: 1.8/0.8 | J43: 31.8 | K43: 55 | L43: India | M43: IntelliCompaction Proporciona un valor de compactación relativa, lo que ayuda a lograr una compactación consistente y uniforme en todo el parche. No aplica | N43: - | O43: LiveLinks Telematics, CCOMPATRONIC (compaction measurement device) | Q43: Diseño robusto, excelente acceso a mantenimiento y componentes estandarizados para máxima disponibilidad en campo. | R43: Calidad de Compactación * Buen rendimiento para suelos compactables en obras viales, rurales o plataformas. * Sistema de vibración robusto | S43: - | T43: Control y Confort Cabina abierta o cerrada con controles simples. Panel analógico, sin diagnóstico digital. Ideal para operadores con poca experiencia. | U43: - | V43: Mantenimiento y Servicio * Motor JCB DieselMax altamente confiable, sin electrónica compleja. * Capó con apertura completa para acceso rápido. * Menor necesidad de técnicos especializados. | W43: 55 | X43: 200 - 350 | Y43: 13 | Z43: 84076 | AA43: 1 | AB43: 2 | AC43: 3000 | AD43: 151576
A44: =B44&" | "&C44 -> JCB | VM115 | B44: JCB | C44: VM115 | E44: 11500 | F44: JCB DieselMAX | G44: 2.13 | H44: 125 | I44: 1.90/0.95 | J44: 0 | K44: 55 | L44: India | M44: IntelliCompaction Proporciona un valor de compactación relativa, lo que ayuda a lograr una compactación consistente y uniforme en todo el parche. No aplica | N44: - | O44: LiveLinks Telematics, CCOMPATRONIC (compaction measurement device) | Q44: Diseño robusto, excelente acceso a mantenimiento y componentes estandarizados para máxima disponibilidad en campo. | R44: Calidad de Compactación * Buen rendimiento para suelos compactables en obras viales, rurales o plataformas. * Sistema de vibración robusto | S44: - | T44: Control y Confort Cabina abierta o cerrada con controles simples. Panel analógico, sin diagnóstico digital. Ideal para operadores con poca experiencia. | U44: - | V44: Mantenimiento y Servicio * Motor JCB DieselMax altamente confiable, sin electrónica compleja. * Capó con apertura completa para acceso rápido. * Menor necesidad de técnicos especializados. | W44: 55 | X44: 200 - 350 | Y44: 13 | Z44: 84076 | AA44: 1 | AB44: 2 | AC44: 3000 | AD44: 151576
A45: =B45&" | "&C45 -> JCB | VM137 | B45: JCB | C45: VM137 | E45: 13700 | F45: JCB DieselMAX | G45: 2.13 | H45: 125 | I45: 2.00/1.00 | J45: 0 | L45: India | M45: No aplica | N45: - | Q45: Especificaciones técnicas * Motor JCB DieselMAX * 125 HP * Peso operativo 13,700 kg | R45: Rendimiento de compactación * Amplitud 2.00/1.00 mm | X45: - | Y45: 0 | Z45: 0 | AA45: 1 | AB45: 2 | AC45: 3000 | AD45: 0
A46: =B46&" | "&C46 -> NEW HOLLAND | V110 | B46: NEW HOLLAND | C46: V110 | E46: 11380 | F46: S8000 4-stroke | G46: 2.16 | H46: 110 | I46: 1.8/0.8 | J46: 31 | K46: 40 | L46: India | M46: No aplica No aplica | N46: - | O46: ReadyKit básico (en algunas versiones), cabina optimizada | Q46: Controles básicos y mecánicos: * Fáciles de usar, ideales para operadores con poca capacitación. * Palanca de avance/reversa con control de vibración independiente. | R46: Mayor tracción y maniobrabilidad Gracias a su sistema de doble tracción (Drum Drive), el rodillo compactador New Holland domina fácilmente los terrenos más empinados, mientras que su ángulo de giro de 37 grados proporciona una maniobrabilidad excepcional, simplificando el trabajo en espacios reducidos. | S46: Junta de articulación Ofrece un radio de giro 37° y seguimiento preciso del terreno. | T46: Cabina confortable Una vez dentro, el ambiente está protegido por la estructura ROPS/FOPS, incluye aire acondicionado y está diseñado para absorber y minimizar las vibraciones generadas durante la operación, asegurando una experiencia de trabajo fluida y sin estrés. | U46: Compactación eficiente Equipado con dos etapas de vibración para adaptarse a diferentes tipos de suelo, y además con un kit de pata de cabra, garantiza resultados impecables en cualquier tarea. | V46: Fácil mantenimiento Con un diseño de capó y compartimiento del motor de una sola pieza, el acceso al rodillo compactador New Holland es fácil para verificar los componentes esenciales, lo que facilita el trabajo del operador y proporciona mayor seguridad y disponibilidad operativa. | W46: 50 | X46: 200 - 300 | Y46: 10.5 | Z46: 71600 | AA46: 1 | AB46: 2 | AC46: 3000 | AD46: 127850
A47: =B47&" | "&C47 -> AMMANN | ASC110 | B47: AMMANN | C47: ASC110 | E47: 11490 | F47: Cummins QSB 4.5-C160 | G47: 2.13 | H47: 160 | I47: 1.85/0.9 | J47: 34.5 | K47: 60 | L47: Brasil | M47: AMMANN ACEforce Tecnología de ajuste activo de la vibración, que ajusta continuamente la amplitud y la frecuencia del tambor según las condiciones del terreno. Esto mejora la eficiencia y la uniformidad de la compactación. No aplica | N47: - | O47: ECOdrop, telemetría, control automático de vibración | Q47: Estación del operador El control intuitivo de la máquina facilita su uso. Las funciones avanzadas garantizan que incluso los principiantes sean productivos y de alto rendimiento. | R47: Alto rendimiento de compactación Compactación más rápida de capas más gruesas en menos pasadas. | S47: Articulación central con bloqueo hidráulico y oscilación automática | T47: Uso cómodo • El diseño sencillo del panel de instrumentos permite un control fácil y seguro • Para asegurar la máxima comodidad la plataforma del operario está montada en alojamientos de goma que amortigua las vibraciones | U47: Tecnología ACE * ACEpro ajusta continuamente la frecuencia y amplitud según los valores obtenidos: • ACEpro elimina los saltos de los tambores y por eso minimiza el riesgo de excesiva compactación o deterioro del material • ACEforce muestra el proceso de compactación mediante la función de guiado del operario | V47: Diseño de fácil mantenimiento Tiempo de inactividad minimizado gracias a procesos de mantenimiento sencillos y un diseño robusto de la máquina y sus componentes. | W47: 60 | X47: 280 - 450 | Y47: 16.3 | Z47: 89930 | AA47: 1 | AB47: 2 | AC47: 3000 | AD47: 172280
A48: =B48&" | "&C48 -> SEM | 510 | B48: SEM | C48: 510 | E48: 10000 | F48: WP4G130E22 | G48: 2.1 | H48: 130.7 | I48: 1.8/0.9 | J48: 27.6 | K48: 45 | L48: China | M48: No aplica No aplica | N48: Vision Link | O48: Vision Link | Q48: Su sistema de operación es muy sencillo: cuenta únicamente con dos palancas de control, una para el acelerador y otra para el control de avance/retroceso y freno | R48: Se utilizan ampliamente en trabajos viales, sub-bases, estacionamientos, desarrollos de obra, excavaciones para agua y alcantarillado, así como en terrenos inclinados y superficies irregulare | S48: - | T48: Control y Confort Cabina abierta o cerrada con controles simples. Panel analógico, sin diagnóstico digital. Ideal para operadores con poca experiencia. | U48: - | V48: Diseño excéntrico tipo ‘pod’. Doble amplitud y frecuencia con bomba y motor de pistón que disminuye las rutinas de mantenimiento | W48: 55 | X48: 200 - 350 | Y48: 13 | Z48: 84076 | AA48: 1 | AB48: 2 | AC48: 3000 | AD48: 151576
A49: =B49&" | "&C49 -> CASE | 1107EX | B49: CASE | C49: 1107EX | E49: 11200 | F49: S 8000 | G49: 2.1 | H49: 110 | I49: 1.8/0.8 | J49: 29 | K49: 36 | L49: India | M49: No aplica No aplica | N49: - | O49: - | Q49: Diseño robusto, excelente acceso a mantenimiento y componentes estandarizados para máxima disponibilidad en campo. | R49: El sistema opcional de accionamiento del tambor incorpora un motor de alto par en el bastidor delantero, lo que proporciona una excelente capacidad de ascenso (36%) y tracción optimizada. | S49: - | T49: Control y Confort Sistema de aire acondicionado y calefacción eficiente con 8 difusores | U49: - | V49: Mantenimiento y Servicio El mantenimiento diario y regular es posible desde el nivel del suelo gracias al capó abatible de una sola pieza. La reducción de tiempos de inactividad y de costos operativos se traduce en mayor productividad y mejor rentabilidad. | W49: 55 | X49: - | Y49: 13 | Z49: 84076 | AA49: 1 | AB49: 2 | AC49: 3000 | AD49: 151576

Sheet Datos LTR
A1: ID | B1: Marca | C1: Modelo | D1: Peso (kg) | E1: Motor | F1: Ancho de compactación (m) | G1: Potencia (HP) | H1: Amplitud (mm) | I1: Carga lineal estática (kg/cm) | J1: País de origen | K1: Asistente de compactación | L1: Tecnologías innovadoras | M1: USP | N1: Consumo de combustible (L/h) | O1: Precio CIF (USD) | P1: Mant. preventivo (USD/h) | Q1: Mant. correctivo (USD/h) | R1: Tiempo de uso (h) | S1: TCO estático app (USD) | T1: Sistema de compactación | U1: Tanque de agua (L) | V1: Junta de articulación | W1: Confort y seguridad | X1: Compactación eficiente | Y1: Tecnología ACE | Z1: Mantenimiento fácil | AA1: TCO estático (USD) | AB1: Línea de tiempo TCO (datos app)
A2: =B2&" | "&C2 -> BOMAG | BW120 AD-5 | B2: BOMAG | C2: BW120 AD-5 | D2: 2700 | E2: Kubota D1703 | F2: 1.2 | G2: 32.6 | H2: 0.5 | I2: 11.3 | J2: Germany/China | K2: Economizer - Sensor de rigidez del suelo | L2: Bajos TCO (Servicio/Matenimiento/Reparación/confiabilidad) | M2: Fácil y seguro de operar. Economizer (Opción) Incluye indicador de temperatura | N2: 2.6 | O2: 28000 | P2: 1 | Q2: 1.3 | R2: 3500 | S2: 49700 | T2: Vibratory | U2: 205 | V2: Articulación de la rueda | W2: Confort y seguridad | X2: Compactación eficiente | Y2: Tecnología ACE | Z2: Mantenimiento fácil | AA2: 49700 | AB2: 0 h: precio 28000 / TCO 49700; 1000 h: precio 32900 / TCO 49700; 1500 h: precio 35350 / TCO 49700; 2000 h: precio 37800 / TCO 49700; 2500 h: precio 40250 / TCO 49700; 3000 h: precio 42700 / TCO 49700
A3: =B3&" | "&C3 -> CATERPILLAR | CB2.7GC | B3: CATERPILLAR | C3: CB2.7GC | D3: 2698 | E3: CAT C1.7T | F3: 1.3 | G3: 24.6 | H3: 0.52 | I3: 13.7 | J3: China | K3: CMV (Compaction Meter Value) | L3: Rodillo de bajo costo operativo, ideal para flotas de alquiler o trabajos donde la simplicidad y confiabilidad mecánica son prioridad. | M3: Rodillo de bajo costo operativo, ideal para flotas de alquiler o trabajos donde la simplicidad y confiabilidad mecánica son prioridad. | N3: 2.3 | O3: 29630 | P3: 1 | Q3: 2 | R3: 3500 | S3: 52205 | T3: Vibratory | U3: 200 | V3: Articulación de la rueda | W3: Confort y seguridad | X3: Compactación eficiente | Y3: Tecnología ACE | Z3: Mantenimiento fácil | AA3: 52205 | AB3: 0 h: precio 29630 / TCO 52205; 1000 h: precio 34930 / TCO 52205; 1500 h: precio 37580 / TCO 52205; 2000 h: precio 40230 / TCO 52205; 2500 h: precio 42880 / TCO 52205; 3000 h: precio 45530 / TCO 52205
A4: =B4&" | "&C4 -> HAMM | HD12 VV | B4: HAMM | C4: HD12 VV | D4: 2695 | E4: Kubota D1503 | F4: 1.25 | G4: 30.7 | H4: 0.52 | I4: 11.2 | J4: Czech | K4: HAMM Compaction Meter: Sensor de aceleración / frecuencia | L4: Máxima maniobrabilidad con doble tambor vibratorio y opción de configuración para zonas urbanas estrechas | M4: Máxima maniobrabilidad con doble tambor vibratorio y opción de configuración para zonas urbanas estrechas | N4: 2.8 | O4: 29580 | P4: 1.5 | Q4: 1 | R4: 3500 | S4: 53030 | T4: Vibratory | U4: 180 | V4: Articulación de la rueda | W4: Confort y seguridad | X4: Compactación eficiente | Y4: Tecnología ACE | Z4: Mantenimiento fácil | AA4: 53030 | AB4: 0 h: precio 29580 / TCO 53030; 1000 h: precio 34880 / TCO 53030; 1500 h: precio 37480 / TCO 53030; 2000 h: precio 40080 / TCO 53030; 2500 h: precio 42680 / TCO 53030; 3000 h: precio 45280 / TCO 53030
A5: =B5&" | "&C5 -> DYNAPAC | CC1200 | B5: DYNAPAC | C5: CC1200 | D5: 2600 | E5: Kubota D1703-M | F5: 1.2 | G5: 35 | H5: 0.508 | I5: 10.5 | J5: Brasil | K5: DCA-A Sensor de aceleración / amplitud | L5: Chasis compacto con diseño en tándem y opción de sistema DCA para trazabilidad por zonas (en modelos superiores). | M5: Chasis compacto con diseño en tándem y opción de sistema DCA para trazabilidad por zonas (en modelos superiores). | N5: 2.7 | O5: 26783 | P5: 1 | Q5: 1.4 | R5: 3500 | S5: 49358 | T5: Vibratory | U5: 159 | V5: Articulación de la rueda | W5: Confort y seguridad | X5: Compactación eficiente | Y5: Tecnología ACE | Z5: Mantenimiento fácil | AA5: 49358 | AB5: 0 h: precio 26783 / TCO 49358; 1000 h: precio 31783 / TCO 49358; 1500 h: precio 34283 / TCO 49358; 2000 h: precio 36783 / TCO 49358; 2500 h: precio 39283 / TCO 49358; 3000 h: precio 41783 / TCO 49358
A6: =B6&" | "&C6 -> AMMANN | ARX 26 | B6: AMMANN | C6: ARX 26 | D6: 2460 | E6: Yanmar 3TNV88F | F6: 1.2 | G6: 27.3 | H6: 0.6 | I6: 10.3 | J6: Switzerland | K6: ACEforce: Sensor de rigidez dinámica | L6: Tecnología de compactación activa que ajusta automáticamente la vibración según la rigidez del suelo para optimizar el número de pasadas. | M6: Tecnología de compactación activa que ajusta automáticamente la vibración según la rigidez del suelo para optimizar el número de pasadas. | N6: 3.2 | O6: 25500 | P6: 1 | Q6: 1.3 | R6: 3500 | S6: 50350 | T6: Vibratory | U6: 110 | V6: Articulación de la rueda | W6: Confort y seguridad | X6: Compactación eficiente | Y6: Tecnología ACE | Z6: Mantenimiento fácil | AA6: 50350 | AB6: 0 h: precio 25500 / TCO 50350; 1000 h: precio 29500 / TCO 50350; 1500 h: precio 31500 / TCO 50350; 2000 h: precio 33500 / TCO 50350; 2500 h: precio 35500 / TCO 50350; 3000 h: precio 37500 / TCO 50350
A7: =B7&" | "&C7 -> JCB | CT260 | B7: JCB | C7: CT260 | D7: 2740 | E7: Kubota D1703-M | F7: 1.2 | G7: 24.4 | H7: 0.51 | I7: 10.5 | J7: India | K7: No aplica | L7: Diseño robusto, excelente acceso a mantenimiento y componentes estandarizados para máxima disponibilidad en campo. | M7: Diseño robusto, excelente acceso a mantenimiento y componentes estandarizados para máxima disponibilidad en campo. | N7: 2.7 | O7: 23500 | P7: 1.5 | Q7: 2 | R7: 3500 | S7: 49925 | T7: Vibratory | U7: 197 | V7: Articulación de la rueda | W7: Confort y seguridad | X7: Compactación eficiente | Y7: Tecnología ACE | Z7: Mantenimiento fácil | AA7: 49925 | AB7: 0 h: precio 23500 / TCO 49925; 1000 h: precio 27500 / TCO 49925; 1500 h: precio 29500 / TCO 49925; 2000 h: precio 31500 / TCO 49925; 2500 h: precio 33500 / TCO 49925; 3000 h: precio 35500 / TCO 49925
A8: =B8&" | "&C8 -> WACKER NEUSON | RD27 | B8: WACKER NEUSON | C8: RD27 | D8: 2695 | E8: Kubota D1903-M | F8: 1.2 | G8: 30.7 | H8: 0.51 | I8: 10.5 | J8: Germany | K8: No aplica | L8: Diseño robusto, excelente acceso a mantenimiento y componentes estandarizados para máxima disponibilidad en campo. | M8: Diseño robusto, excelente acceso a mantenimiento y componentes estandarizados para máxima disponibilidad en campo. | N8: 2.7 | O8: 23500 | P8: 1.5 | Q8: 2 | R8: 3500 | S8: 49925 | T8: Vibratory | U8: 197 | V8: Articulación de la rueda | W8: Confort y seguridad | X8: Compactación eficiente | Y8: Tecnología ACE | Z8: Mantenimiento fácil | AA8: 49925 | AB8: 0 h: precio 23500 / TCO 49925; 1000 h: precio 27500 / TCO 49925; 1500 h: precio 29500 / TCO 49925; 2000 h: precio 31500 / TCO 49925; 2500 h: precio 33500 / TCO 49925; 3000 h: precio 35500 / TCO 49925

Sheet Datos HTR
A1: ID | B1: Marca | C1: Modelo | D1: Peso (kg) | E1: Motor | F1: Ancho de compactación (m) | G1: Potencia (HP) | H1: Amplitud (mm) | I1: Carga lineal estática (kg/cm) | J1: Gradeabilidad (%) | K1: País de origen | L1: Asistente de compactación | M1: Asphalt Manager | N1: Telemetría | O1: Tecnologías innovadoras | P1: Sistemas de vibración / notas | Q1: Junta de articulación libre de mantenimiento | R1: Consumo de combustible (L/h) | S1: Precio CIF (USD) | T1: Mant. preventivo (USD/h) | U1: Mant. correctivo (USD/h) | V1: Tiempo de uso (h) | W1: TCO estático app (USD) | X1: USP | Y1: Profundidad de compactación máx. | Z1: Rendimiento en compactación (m³/h, ficha) | AA1: Línea de tiempo TCO (datos app)
A2: =B2&" | "&C2 -> BOMAG | BW161 AD-4 | B2: BOMAG | C2: BW161 AD-4 | D2: 9700 | E2: Deutz TCD L04 2V | F2: 1.68 | G2: 114 | H2: 0,94/0,42 | I2: 30.1 | J2: 35 | K2: Alemania | L2: BOMAG ECONOMIZER Sistema visual que permite a los operadores medir el progreso de la compactación en tiempo real. Utiliza una escala LED en la cabina para mostrar el nivel de compactación alcanzado, ayudando a evitar sobrecompacción o subcompactación. | M2: BOMAG ASPHALT MANAGER Ningún otro sistema es tan flexible como la AM: con la amplitud de salida variable, puede ser potente o sensible. Se aplica el nivel de fuerza adecuado en la dirección correcta en cualquier aplicación: Adaptación del tambor de vibración hasta oscilación. Medición del Evib en MN/m2 | N2: Telematic, BOMAP | O2: TANGO, ASPHALT MANAGER, ECONOMIZER ECOMODE, TELEMATIC | P2: 3 sistemas de vibración Solo los rodillos tándem BOMAG le ofrecen tres sistemas de vibración. Con doble vibración, TanGO y ASPHALT MANAGER, tiene tres tecnologías para elegir. | Q2: Junta de articulación libre de mantenimiento | R2: 11.8 | S2: 28000 | T2: 1 | U2: 2 | V2: 2000 | W2: 50000 | X2: TANGO, ASPHALT MANAGER, ECONOMIZER ECOMODE, TELEMATIC | Y2: 0.3 | Z2: 150-200 | AA2: 0 h: precio 28000 / TCO 28000; 1000 h: precio - / TCO 35000; 2000 h: precio - / TCO 42000
A3: =B3&" | "&C3 -> AMMANN | AV110X | B3: AMMANN | C3: AV110X | D3: 10400 | E3: Cummins QSB3.3-C99 | F3: 1.7 | G3: 99 | H3: 0,7/0,35 | I3: 30.9 | J3: 30 | K3: República Checa | L3: No aplica | M3: No aplica | N3: Dyn@Link | O3: Junta con oscilación, diagnóstico abordo | P3: Alta visibilidad, compactación potente y cómoda | Q3: No aplica | R3: 11.8 | S3: 28000 | T3: 1 | U3: 2 | V3: 2000 | W3: 50000 | X3: Junta con oscilación, diagnóstico abordo | Y3: 0.3 | Z3: 140-180 | AA3: 0 h: precio 28000 / TCO 28000; 1000 h: precio - / TCO 35000; 2000 h: precio - / TCO 42000
A4: =B4&" | "&C4 -> CATERPILLAR | CB10 | B4: CATERPILLAR | C4: CB10 | D4: 9500 | E4: CAT C4.4 | F4: 1.7 | G4: 130 | H4: 0,84/0,18 | I4: 28.5 | J4: 31 | K4: China | L4: CMV + PassCount Utiliza sensores de aceleración en el tambor vibratorio para medir la respuesta del suelo/asfalto a las vibraciones del rodillo. Proporciona una lectura relativa de la calidad de compactación. | M4: No aplica | N4: Vision Link | O4: Versa Vibe™, 360° visión, Oscilación | P4: Sistema VersaVibe™ Tecnología que permite a los compactadores tándem trabajar con cuatro configuraciones distintas de vibración, adaptándose a diferentes condiciones de asfalto y objetivos de compactación. | Q4: No aplica | R4: 11.8 | S4: 28000 | T4: 1 | U4: 2 | V4: 2000 | W4: 50000 | X4: Versa Vibe™, 360° visión, Oscilación | Y4: 0.3 | Z4: 160-210 | AA4: 0 h: precio 28000 / TCO 28000; 1000 h: precio - / TCO 35000; 2000 h: precio - / TCO 42000
A5: =B5&" | "&C5 -> DYNAPAC | CC4200 | B5: DYNAPAC | C5: CC4200 | D5: 10400 | E5: Cummins QSB4.5 | F5: 1.73 | G5: 110 | H5: 0,8/0,3 | I5: 31 | J5: 45 | K5: Brasil | L5: No aplica | M5: No aplica | N5: No | O5: Oscilación, cabina deslizante | P5: Alta fuerza centrífuga y amplitud, gran tanque de agua | Q5: Junta de articulación libre de mantenimiento | R5: 11.8 | S5: 28000 | T5: 1 | U5: 2 | V5: 2000 | W5: 50000 | X5: Oscilación, cabina deslizante | Y5: 0.3 | Z5: 150-190 | AA5: 0 h: precio 28000 / TCO 28000; 1000 h: precio - / TCO 35000; 2000 h: precio - / TCO 42000
A6: =B6&" | "&C6 -> HAMM | HD90 VV | B6: HAMM | C6: HD90 VV | D6: 9190 | E6: Deutz TCD L04 2V | F6: 1.68 | G6: 134 | H6: 0,66/0,37 | I6: 27.6 | J6: 40 | K6: Alemania | L6: HCM (HAMM Compaction) Se basa en sensores que evalúan la rigidez del material compactado en tiempo real, usando datos dinámicos del tambor vibratorio. Valores adimensionales | M6: No aplica | N6: John Deere Operations Center | O6: VIO, HAMMTRONIC, Easy Drive | P6: VIO , tecnología que permite a un solo tambor trabajar tanto con vibración vertical como con oscilación horizontal, según las condiciones del material o del entorno. | Q6: La articulación ajustable oscila para garantizar un contacto constante entre los tambores y la superficie | R6: 11.8 | S6: 28000 | T6: 1 | U6: 2 | V6: 2000 | W6: 50000 | X6: VIO, HAMMTRONIC, Easy Drive | Y6: 0.3 | Z6: 170-220 | AA6: 0 h: precio 28000 / TCO 28000; 1000 h: precio - / TCO 35000; 2000 h: precio - / TCO 42000

Sheet Datos Fresadoras
A1: ID | B1: Marca | C1: Modelo | D1: Motor | E1: Ancho de fresado | F1: Profundidad máxima | G1: Potencia del motor | H1: Diámetro del tambor | I1: Velocidad de trabajo | J1: Velocidad de desplazamiento | K1: Capacidad de transporte | L1: Ancho de banda transportadora | M1: Tanque de agua | N1: Peso operacional | O1: Radio mínimo de giro | P1: Sistema de corte | Q1: Eficiencia energética | R1: USP 1 | S1: USP 2 | T1: USP 3 | U1: USP 4 | V1: Aplicación ideal | W1: Propuesta de valor | X1: Precio CIF (USD) | Y1: Consumo de combustible (L/h) | Z1: Mant. preventivo (USD/h) | AA1: Mant. correctivo (USD/h) | AB1: Tiempo de uso (h) | AC1: TCO estático app (USD) | AD1: Capacidad de transporte (m³/h) | AE1: Velocidad de trabajo máx. (m/min) | AF1: Radio de giro (m) | AG1: Tiene BMS15L | AH1: Reducción de desgaste BMS15L (%) | AI1: Desgaste de herramientas (USD/h)
A2: =B2&" | "&C2 -> BOMAG | BM 1000/20 | B2: BOMAG | C2: BM 1000/20 | D2: 164 kW – Cummins QSB 6.7 | E2: 1.000 mm | F2: 210 mm | G2: 164 kW – Cummins QSB 6.7 | H2: 860 mm | I2: 0-40 m/min | J2: 8 km/h | K2: 92 m³/h | L2: 400 mm | M2: 700 L | N2: 11.800-13.600 kg | O2: 0,38 m | P2: BMS15L con porta-herramientas de cambio rápido (1 tornillo). Menor desgaste y mayor eficiencia energética. | Q2: Diseño optimizado que reduce desgaste hasta 20% y mejora consumo. | R2: Alta eficiencia potencia-rendimiento. Mayor capacidad de transporte. | S2: Mejor radio de giro. Ideal para entornos urbanos y espacios reducidos. | T2: Hasta 20% menor desgaste. Cambio rápido de herramientas. Mejor costo total de propiedad. | U2: Panel ergonómico. Mejor protección contra polvo y vibración. Ideal para jornadas largas. | V2: Obras urbanas, mantenimiento vial, trabajos de precisión y alta rotación operativa. | W2: Especialista en eficiencia, versatilidad y mejor TCO. | X2: 0 | Y2: 16 | Z2: 12 | AA2: 8 | AB2: 3000 | AC2: 0 | AD2: 92 | AE2: 40 | AF2: 0.38 | AG2: SÍ | AH2: 20 | AI2: 15
A3: =B3&" | "&C3 -> SANY | SCM1000C-8 | B3: SANY | C3: SCM1000C-8 | D3: 180 kW – Motor SAN | E3: 1.000 mm | F3: 280 mm | G3: 180 kW – Motor SAN | H3: 930 mm | I3: 35 m/min | J3: 8 km/h | K3: - | L3: 500 mm | M3: 800 L | N3: 15.750 kg (más pesa) | O3: 1,2 m | P3: Tambor de mayor diámetro orientado a trabajos profundos. | Q3: Mayor potencia implica mayor demanda energética. | R3: Mayor potencia y profundidad para fresado estructural pesado. | S3: Mayor estabilidad, menor agilidad. | T3: Potencia elevada puede aumentar consumo y desgaste. | U3: Cabina amplia y robusta. | V3: Proyectos estructurales, grandes profundidades y alta carga productiva. | W3: Especialista en potencia y fresado profundo. | X3: 0 | Y3: 22 | Z3: 10 | AA3: 10 | AB3: 3000 | AC3: 0 | AD3: 0 | AE3: 35 | AF3: 1.2 | AG3: NO | AI3: 20
A4: =B4&" | "&C4 -> XCMG | XM1005H | B4: XCMG | C4: XM1005H | D4: 164 kW – Cummins QSB6.7 | E4: 1.000 mm | F4: 220 mm | G4: 164 kW – Cummins QSB6.7 | H4: 860 mm | I4: 50 m/min | J4: 8,5 km/h | K4: 84 m³/h | L4: 400 mm | M4: 850 L | N4: 13.900-14.100 kg | O4: No declarado | P4: Configuración estándar con motor Cummins confiable. | Q4: Consumo competitivo dentro del segmento. | R4: Buen desempeño general con alta velocidad operativa. | S4: Maniobrabilidad intermedia. | T4: Motor Cummins facilita soporte y repuestos. | U4: Diseño funcional estándar. | V4: Empresas que buscan equilibrio costo-beneficio. | W4: Alternativa competitiva balanceada en precio y rendimiento. | X4: 0 | Y4: 18 | Z4: 10 | AA4: 8 | AB4: 3000 | AC4: 0 | AD4: 84 | AE4: 50 | AG4: NO | AI4: 17

Sheet Datos Pavimentadoras
A1: ID | B1: Marca | C1: Modelo | D1: Fabricante del motor | E1: Potencia nominal | F1: Norma de emisiones | G1: Modo de ahorro de combustible | H1: Tanque de combustible | I1: Producción máxima | J1: Velocidad de pavimentación | K1: Velocidad de desplazamiento | L1: Espesor máx. de capa | M1: Ancho mín. de trabajo | N1: Ancho base retraído | O1: Ancho base extendido | P1: Ancho máx. con extensiones | Q1: Capacidad de tolva | R1: Diámetro del sinfín | S1: Transportadores | T1: Rodillos de empuje | U1: Tipos de plancha | V1: Calentamiento de plancha | W1: Frecuencia tamper / vibración | X1: Sistema de extensión rápida | Y1: Profundidad placa alisadora | Z1: Peso operacional | AA1: Longitud de transporte | AB1: Ancho de transporte | AC1: Altura de transporte | AD1: Sistema de operación | AE1: Control de nivelación | AF1: Telemática | AG1: Extracción de humos de asfalto | AH1: Lubricación centralizada | AI1: Motor | AJ1: USP 1 | AK1: USP 2 | AL1: USP 3 | AM1: USP 4 | AN1: USP 5 | AO1: USP 6 | AP1: USP 7 | AQ1: USP 8 | AR1: USP 9 | AS1: Consumo medio de combustible | AT1: Fuente del dato de consumo | AU1: Consumo por turno 10 h (L) | AV1: CO₂ por turno 10 h | AW1: Ahorro de combustible por día | AX1: Ahorro de CO₂ por día | AY1: Tipo de calentamiento | AZ1: Tiempo de calentamiento | BA1: Vida elementos calefactores | BB1: Vida placas de desgaste | BC1: Ciclo de reemplazo | BD1: Costo reemplazo año 1 | BE1: Costo reemplazo año 2 | BF1: Costo reemplazo año 3 | BG1: Total reemplazos 3 años | BH1: Ahorro vs BOMAG 3 años | BI1: CO₂ calentamiento inicial
A2: =B2&" | "&C2 -> CATERPILLAR | AP655 | B2: CATERPILLAR | C2: AP655 | D2: Cat C4.4 (4 cil.) / opt C7.1 (6 cil.) | E2: 129 kW / 173 hp | F2: EPA Tier 4 Final / EU Stage V | G2: Eco-mode + control auto rpm | H2: 278 L | I2: 1.300 t/h | J2: Hasta 25 m/min | K2: 14,5 km/h | L2: 305 mm | M2: 2,44 m (SE47) | N2: 2,55 m (SE50) / 3,0 m (SE60) | O2: 5,0 m (SE50) / 6,0 m (SE60) | P2: 8,0 m (SE50VT) 10,0 m (SE60VT XW) | Q2: 11–12 t | R2: 406 mm (16") | S2: 2 cintas - sistema 4 bombas | T2: Ajustables (estándar) | U2: SE47FM / SE50 V,VT SE60 FM,V,VT,VT XW | V2: Eléctrica - generador 70 kW ~15 min calentamiento | W2: Variable (ajuste táctil) | X2: Manual / hidráulica (opcional) | Y2: No especificado | Z2: 19.530 kg (c/SE50VT) 21.052 kg (c/SE60VT XW) | AA2: 6.666 mm (c/SE50VT) | AB2: 2.550–2.762 mm | AC2: 3.056 mm | AD2: Pantallas táctiles dobles Pave Start Assistant | AE2: Cat Grade Control (OPCIONAL) | AF2: Product Link Elite (satélite / celular) | AG2: Sistema ventilación (desviación) | AH2: Acceso remoto puntos clave | AI2: 129 kW / 173 hp | AJ2: Eléctrico estándar - ~15 min - Vida 1.000–1.500 h - Recambio anual ~8.000 € | AK2: No publicado en ficha técnica | AL2: Eco-mode: reducción rpm motor | AM2: Manual / hidráulico convencional | AN2: Doble estación giratoria (backup) | AO2: Ajustables (estándar) | AP2: Cat Grade Control = OPCIONAL (costo adicional) | AQ2: ~24.000 € total en 3 años (recambio anual ~8.000 €) | AR2: ~366 kg CO₂ estimado (+55% vs BOMAG) | AS2: No publicado | AT2: — | AU2: N/D | AV2: ~366 kg (+55% vs BOMAG) | AW2: — | AX2: — | AY2: Eléctrico estándar | AZ2: ~60 min | BA2: 1.000 – 1.500 h | BB2: 1.000 – 2.000 h | BC2: Anual | BD2: ~8.000 € | BE2: ~8.000 € | BF2: ~8.000 € | BG2: ~24.000 € | BH2: 16.000 € | BI2: 27 kg (10,5 L)
A3: =B3&" | "&C3 -> BOMAG | BF600 C-3 | B3: BOMAG | C3: BF600 C-3 | D3: Deutz TCD 2012 L06 (6 cil.) | E3: 116 kW / 156 hp | F3: Stage IIIa / Tier 3 | G3: ECOMODE | H3: 285 L | I3: 600 t/h | J3: Hasta 25 m/min | K3: 4 km/h | L3: 300 mm | M3: 1,65 m (con reducciones) (S500) | N3: 2,5 m (S500) / 3,0 m (S600) | O3: 5,0 m (S500) / 6,0 m (S600) | P3: 8,0 m (S500) / 9,0 m (S600) [Quick Coupling] | Q3: 11 t | R3: 350 mm - 100 rpm | S3: 2 - reversibles, ctrl indep. 64 rpm | T3: Amortiguados + apoyo hidráulico | U3: S500 / S600 (tamper + vibración) | V3: MAGMALIFE - bloques aluminio 50% más rápido · 3.000–5.000 h vida | W3: Tamper 0–29 Hz / Vibr. 20–58 Hz | X3: QUICK COUPLING - sin tornillos (EXCLUSIVO BOMAG) | Y3: 400 mm - Espesor 15 mm | Z3: 21.000 kg (c/S500) 21.500 kg (c/S600) | AA3: 6.360 mm | AB3: 2.550 mm (S500) / 3.000 mm (S600) | AC3: 3.061 mm | AD3: A-PAVE pantalla gráfica Asiento SIDEVIEW giratorio/deslizable | AE3: Controlador integrado + sensor pendiente (ESTÁNDAR LATERAL) | AF3: BOMAG TELEMATIC + JOBLINK data interface | AG3: Aspiración vapores - estándar | AH3: Equipo lubric. central estándar | AI3: 116 kW / 156 hp | AJ3: 50% más rápido - 50% menos combustible en setup - Vida 3.000–5.000 h - Ahorro ~16.000 € en 3 años | AK3: 8,9 l/h promedio medido 235 kg CO₂ / jornada 10h | AL3: Regulación activa bombas hidráulicas según demanda real - Ahorro hasta 17% | AM3: Sin tornillos - sin herramientas - mín. tiempo de acople - EXCLUSIVO BOMAG | AN3: Asiento + consola deslizables al lateral - visión directa regla y borde - ESTÁNDAR | AO3: Amortiguados + apoyo hidráulico | AP3: Controlador integrado + sensor pendiente ESTÁNDAR (lateral) | AQ3: ~8.000 € total en 3 años (recambio cada 2–3 años) | AR3: 235 kg CO₂ (90,5 L diesel) | AS3: 8,9 l/h ✓ MEDIDO EN CAMPO | AT3: Medición campo 03/2019–04/2021 | AU3: 89 | AV3: 235 kg (90,5 L × 2,6) | AW3: 51 L menos que competidor 16 L menos que Dynapac | AX3: 131 kg menos que competidor 38 kg menos que Dynapac | AY3: MAGMALIFE — bloques aluminio fundido | AZ3: ~30 min (50% más rápido) | BA3: 3.000 – 5.000 h | BB3: 2.000 – 3.000 h | BC3: Cada 2–3 años | BD3: / | BE3: ~8.000 € | BF3: / | BG3: ~8.000 € ✓ | BH3: — | BI3: 9 kg (3,5 L) ✓
A4: =B4&" | "&C4 -> VÖGELE | Super 1800-3 | B4: VÖGELE | C4: Super 1800-3 | D4: Cummins QSB6.7-C170 (6 cil.) | E4: 127 kW / 170 hp | F4: EU Fase 3a / EPA Tier 3 | G4: EcoPlus | H4: 300 L | I4: 700 t/h | J4: Hasta 24 m/min | K4: 4,5 km/h | L4: 300 mm | M4: 2,55 m (AB500) | N4: 2,55 m (AB500) / 3,0 m (AB600/SB300) | O4: 5,0 m (AB500) / 6,0 m (AB600) | P4: 8,5 m (AB500) / 9,0 m (AB600) 10,0 m (SB300) | Q4: 13 t | R4: 400 mm - hasta 84 rpm | S4: 2 - hasta 33 m/min variable reversibles | T4: Oscilantes estándar PaveDock elástico (opcional) | U4: AB500/AB600 TV,TP1,TP2,TP2+ SB300 TV,TP1,TP2 | V4: Eléctrica - generador directo refrigerado por aceite | W4: Variable (SmartWheel) | X4: Mecánica + tramos hidr. (SB300) | Y4: No especificado | Z4: 19.400 kg (AB500 hasta 5m) 25.150 kg (AB500 hasta 8,5m) | AA4: 6.040 mm (AB500 TV) | AB4: 2.550 mm | AC4: 3.100 mm | AD4: ErgoPlus 3 - gran pantalla color AutoSet Plus | AE4: Niveltronic Plus (integrado std.) | AF4: PaveDock Assistant (comunicación camiones) | AG4: No especificado | AH4: Lubricación central automática | AI4: 127 kW / 170 hp | AJ4: Eléctrico generador directo - Recambio anual ~8.000 € | AK4: No publicado en ficha técnica | AL4: EcoPlus: 4 mecanismos - hasta 25% ahorro | AM4: Mecánicas estándar + tramos hidr. (SB300) | AN4: Plataforma deslizable con consola | AO4: Oscilantes std - PaveDock elástico (opcional) | AP4: Niveltronic Plus — integrado estándar | AQ4: ~24.000 € total en 3 años (recambio anual ~8.000 €) | AR4: No publicado | AS4: No publicado | AT4: — | AU4: N/D | AV4: No publicado | AW4: — | AX4: — | AY4: Eléctrico generador directo | AZ4: ~60 min | BA4: 1.000 – 1.500 h | BB4: 1.000 – 2.000 h | BC4: Anual | BD4: ~8.000 € | BE4: ~8.000 € | BF4: ~8.000 € | BG4: ~24.000 € | BH4: 16.000 € | BI4: 27 kg (10,5 L)
A5: =B5&" | "&C5 -> DYNAPAC | SD2500CS | B5: DYNAPAC | C5: SD2500CS | D5: Cummins QSB 6.7-C200 (6 cil.) | E5: 149 kW / 200 hp | F5: EU Stage V / EPA Tier 4f | G5: VarioSpeed | H5: 362 L | I5: 800 t/h | J5: Hasta 28 m/min | K5: 4 km/h | L5: 310 mm | M5: 2,05 m (con zapatas) | N5: 2,55 m (V5100) / 3,0 m (V6000/R300) | O5: 5,1 m (V5100) / 6,0 m (V6000) | P5: 8,8 m (V5100) / 9,7 m (V6000) 10,0 m (R300) | Q5: 12–15 t | R5: 380 mm | S5: 2 dual - 2×655 mm control proporcional | T5: Fijo pivotable (std.) Hidráulico amortiguado (opc.) | U5: V5100/V6000 TV,TVE,THE R300 TV,TVE / R300 HEE | V5: Eléctrica o Gas (opción única) Generador 33 kVA | W5: Variable - high compaction THE screed disponible | X5: Modular V/R-Series | Y5: No especificado | Z5: 19.000 kg (c/regla std.) | AA5: 6.150 mm | AB5: 2.550 mm | AC5: 3.100 mm | AD5: PaveManager 2.0 - digital SetAssist / TruckAssist | AE5: MOBA integrado (estándar) 3D nivelación (opcional) | AF5: Dyn@Link + MatManager + MatWiser (web reporting) | AG5: Certificado NIOSH 94% efectividad | AH5: Sistema lubric. inteligente | AI5: 149 kW / 200 hp | AJ5: Eléctrico o Gas (sin motor) - Recambio anual ~8.000 € | AK5: 10,5 l/h publicado en ficha ~273 kg CO₂ / jornada estimado | AL5: VarioSpeed: rpm adaptativo automático | AM5: Sistema modular V-Series / R-Series | AN5: Cabina deslizable 'Weather House' | AO5: Fijo pivotable std - hidráulico amort. (opcional) | AP5: MOBA integrado estándar + 3D (opcional) | AQ5: ~24.000 € total en 3 años (recambio anual ~8.000 €) | AR5: ~273 kg CO₂ estimado (10,5 l/h × 26 kg) | AS5: 10,5 l/h (en ficha oficial) | AT5: Ficha técnica oficial | AU5: 105 | AV5: ~273 kg estimado | AW5: — | AX5: — | AY5: Eléctrico o Gas (opción) | AZ5: ~30–60 min (gas: sin motor) | BA5: 1.000 – 1.500 h | BB5: 1.000 – 2.000 h | BC5: Anual | BD5: ~8.000 € | BE5: ~8.000 € | BF5: ~8.000 € | BG5: ~24.000 € | BH5: 16.000 € | BI5: 27 kg (10,5 L) — eléctr.

Sheet Análisis Compactación
A1: Análisis financiero — Compactación (SDR / LTR / HTR)
A2: Precio, consumo y mantenimiento vienen de las hojas de datos (verde). Las columnas azules son supuestos por máquina; las negras son fórmulas.
A4: ID | B4: Línea | C4: Marca | D4: Modelo | E4: Peso (kg) | F4: Precio (USD) | G4: Consumo (L/h) | H4: Mant. preventivo (USD/h) | I4: Mant. correctivo (USD/h) | J4: Valor de reventa (USD) | K4: Junta libre de mant.? | L4: Tec. BOMAG activa? | M4: Rend. base Roca (m³/h) | N4: Rend. base Grava (m³/h) | O4: Rend. base Suelo mixto (m³/h) | P4: Rend. base Arcilla (m³/h) | Q4: Rend. base suelo sel. (m³/h) | R4: Rend. efectivo (m³/h) | S4: Rend. ajustado por eficiencia (m³/h) | T4: Horas para el volumen (h) | U4: Costo operación (USD/h) | V4: Costo del trabajo (USD) | W4: Costo combustible (USD) | X4: Costo mantenimiento (USD) | Y4: Intervenciones de engrase | Z4: Costo junta articulada (USD) | AA4: TCO (USD) | AB4: Costo variable (USD/h) | AC4: TCO por hora (USD/h) | AD4: TCO (moneda sel.) | AE4: Δ TCO vs BOMAG de la línea (USD)
A5: =B5&" | "&C5&" | "&D5&" (mat. 93500000)" -> SDR | BOMAG | BW211 D-5 SL (mat. 93500000) | B5: SDR | C5: ='Datos SDR'!$B$2 -> BOMAG | D5: ='Datos SDR'!$C$2 -> BW211 D-5 SL | E5: ='Datos SDR'!$E$2 -> 10630 | F5: ='Datos SDR'!$Z$2 -> 57592.78 | G5: ='Datos SDR'!$Y$2 -> 11.8 | H5: ='Datos SDR'!$AA$2 -> 1 | I5: ='Datos SDR'!$AB$2 -> 2 | J5: 0 | K5: SÍ | L5: NO | M5: 672 | N5: 472 | O5: 417 | P5: 209 | Q5: =INDEX(M5:P5,MATCH(TipoSuelo,{"Roca","Grava","Suelo mixto","Arcilla"},0)) -> 417 | R5: =Q5*IF(AND(C5="BOMAG",L5="SÍ"),MultTecBOMAG,1) -> 417 | S5: =R5*Eficiencia -> 417 | T5: =IF(AND(S5>0,VolumenCompactacion>0),VolumenCompactacion/S5,0) -> 0 | U5: =G5*PrecioDiesel+H5+I5 -> 17.16 | V5: =T5*U5 -> 0 | W5: =G5*HorasOperacion*PrecioDiesel -> 42480 | X5: =HorasOperacion*(H5+I5) -> 9000 | Y5: =IF(AND(B5="SDR",K5="NO"),HorasOperacion/JuntaIntervalo,0) -> 0 | Z5: =Y5*JuntaHorasIntervencion*(JuntaTecnico+JuntaParada)+Y5*JuntaGrasa -> 0 | AA5: =F5+W5+X5+Z5-J5 -> 109072.78 | AB5: =U5+IF(Y5>0,(JuntaHorasIntervencion*(JuntaTecnico+JuntaParada)+JuntaGrasa)/JuntaIntervalo,0) -> 17.16 | AC5: =IF(HorasOperacion>0,AA5/HorasOperacion,0) -> 36.357593 | AD5: =AA5*TasaMoneda -> 109072.78 | AE5: =IFERROR(AA5-INDEX($AA$5:$AA$64,MATCH(1,INDEX((B$5:B$64=B5)*(C$5:C$64="BOMAG"),0),0)),0) -> 0
A6: =B6&" | "&C6&" | "&D6&" (mat. 93500004)" -> SDR | BOMAG | BW211 D-5 SL (mat. 93500004) | B6: SDR | C6: ='Datos SDR'!$B$3 -> BOMAG | D6: ='Datos SDR'!$C$3 -> BW211 D-5 SL | E6: ='Datos SDR'!$E$3 -> 10630 | F6: ='Datos SDR'!$Z$3 -> 59374 | G6: ='Datos SDR'!$Y$3 -> 11.8 | H6: ='Datos SDR'!$AA$3 -> 1 | I6: ='Datos SDR'!$AB$3 -> 2 | J6: 0 | K6: SÍ | L6: NO | M6: 672 | N6: 472 | O6: 417 | P6: 209 | Q6: =INDEX(M6:P6,MATCH(TipoSuelo,{"Roca","Grava","Suelo mixto","Arcilla"},0)) -> 417 | R6: =Q6*IF(AND(C6="BOMAG",L6="SÍ"),MultTecBOMAG,1) -> 417 | S6: =R6*Eficiencia -> 417 | T6: =IF(AND(S6>0,VolumenCompactacion>0),VolumenCompactacion/S6,0) -> 0 | U6: =G6*PrecioDiesel+H6+I6 -> 17.16 | V6: =T6*U6 -> 0 | W6: =G6*HorasOperacion*PrecioDiesel -> 42480 | X6: =HorasOperacion*(H6+I6) -> 9000 | Y6: =IF(AND(B6="SDR",K6="NO"),HorasOperacion/JuntaIntervalo,0) -> 0 | Z6: =Y6*JuntaHorasIntervencion*(JuntaTecnico+JuntaParada)+Y6*JuntaGrasa -> 0 | AA6: =F6+W6+X6+Z6-J6 -> 110854 | AB6: =U6+IF(Y6>0,(JuntaHorasIntervencion*(JuntaTecnico+JuntaParada)+JuntaGrasa)/JuntaIntervalo,0) -> 17.16 | AC6: =IF(HorasOperacion>0,AA6/HorasOperacion,0) -> 36.951333 | AD6: =AA6*TasaMoneda -> 110854 | AE6: =IFERROR(AA6-INDEX($AA$5:$AA$64,MATCH(1,INDEX((B$5:B$64=B6)*(C$5:C$64="BOMAG"),0),0)),0) -> 1781.22
A7: =B7&" | "&C7&" | "&D7&" (mat. 58400031)" -> SDR | BOMAG | BW211 D-5 SL (mat. 58400031) | B7: SDR | C7: ='Datos SDR'!$B$4 -> BOMAG | D7: ='Datos SDR'!$C$4 -> BW211 D-5 SL | E7: ='Datos SDR'!$E$4 -> 10630 | F7: ='Datos SDR'!$Z$4 -> 63530.18 | G7: ='Datos SDR'!$Y$4 -> 12.4 | H7: ='Datos SDR'!$AA$4 -> 1 | I7: ='Datos SDR'!$AB$4 -> 2 | J7: 0 | K7: SÍ | L7: NO | M7: 672 | N7: 472 | O7: 417 | P7: 209 | Q7: =INDEX(M7:P7,MATCH(TipoSuelo,{"Roca","Grava","Suelo mixto","Arcilla"},0)) -> 417 | R7: =Q7*IF(AND(C7="BOMAG",L7="SÍ"),MultTecBOMAG,1) -> 417 | S7: =R7*Eficiencia -> 417 | T7: =IF(AND(S7>0,VolumenCompactacion>0),VolumenCompactacion/S7,0) -> 0 | U7: =G7*PrecioDiesel+H7+I7 -> 17.88 | V7: =T7*U7 -> 0 | W7: =G7*HorasOperacion*PrecioDiesel -> 44640 | X7: =HorasOperacion*(H7+I7) -> 9000 | Y7: =IF(AND(B7="SDR",K7="NO"),HorasOperacion/JuntaIntervalo,0) -> 0 | Z7: =Y7*JuntaHorasIntervencion*(JuntaTecnico+JuntaParada)+Y7*JuntaGrasa -> 0 | AA7: =F7+W7+X7+Z7-J7 -> 117170.18 | AB7: =U7+IF(Y7>0,(JuntaHorasIntervencion*(JuntaTecnico+JuntaParada)+JuntaGrasa)/JuntaIntervalo,0) -> 17.88 | AC7: =IF(HorasOperacion>0,AA7/HorasOperacion,0) -> 39.056727 | AD7: =AA7*TasaMoneda -> 117170.18 | AE7: =IFERROR(AA7-INDEX($AA$5:$AA$64,MATCH(1,INDEX((B$5:B$64=B7)*(C$5:C$64="BOMAG"),0),0)),0) -> 8097.4
A8: =B8&" | "&C8&" | "&D8&" (mat. 58400033)" -> SDR | BOMAG | BW211 D-5 SL (mat. 58400033) | B8: SDR | C8: ='Datos SDR'!$B$5 -> BOMAG | D8: ='Datos SDR'!$C$5 -> BW211 D-5 SL | E8: ='Datos SDR'!$E$5 -> 10630 | F8: ='Datos SDR'!$Z$5 -> 66500 | G8: ='Datos SDR'!$Y$5 -> 12.4 | H8: ='Datos SDR'!$AA$5 -> 1 | I8: ='Datos SDR'!$AB$5 -> 2 | J8: 0 | K8: SÍ | L8: NO | M8: 672 | N8: 472 | O8: 417 | P8: 209 | Q8: =INDEX(M8:P8,MATCH(TipoSuelo,{"Roca","Grava","Suelo mixto","Arcilla"},0)) -> 417 | R8: =Q8*IF(AND(C8="BOMAG",L8="SÍ"),MultTecBOMAG,1) -> 417 | S8: =R8*Eficiencia -> 417 | T8: =IF(AND(S8>0,VolumenCompactacion>0),VolumenCompactacion/S8,0) -> 0 | U8: =G8*PrecioDiesel+H8+I8 -> 17.88 | V8: =T8*U8 -> 0 | W8: =G8*HorasOperacion*PrecioDiesel -> 44640 | X8: =HorasOperacion*(H8+I8) -> 9000 | Y8: =IF(AND(B8="SDR",K8="NO"),HorasOperacion/JuntaIntervalo,0) -> 0 | Z8: =Y8*JuntaHorasIntervencion*(JuntaTecnico+JuntaParada)+Y8*JuntaGrasa -> 0 | AA8: =F8+W8+X8+Z8-J8 -> 120140 | AB8: =U8+IF(Y8>0,(JuntaHorasIntervencion*(JuntaTecnico+JuntaParada)+JuntaGrasa)/JuntaIntervalo,0) -> 17.88 | AC8: =IF(HorasOperacion>0,AA8/HorasOperacion,0) -> 40.046667 | AD8: =AA8*TasaMoneda -> 120140 | AE8: =IFERROR(AA8-INDEX($AA$5:$AA$64,MATCH(1,INDEX((B$5:B$64=B8)*(C$5:C$64="BOMAG"),0),0)),0) -> 11067.22
A9: =B9&" | "&C9&" | "&D9 -> SDR | BOMAG | BW212 D-5 SL | B9: SDR | C9: ='Datos SDR'!$B$6 -> BOMAG | D9: ='Datos SDR'!$C$6 -> BW212 D-5 SL | E9: ='Datos SDR'!$E$6 -> 11490 | F9: ='Datos SDR'!$Z$6 -> 68684 | G9: ='Datos SDR'!$Y$6 -> 12.4 | H9: ='Datos SDR'!$AA$6 -> 1 | I9: ='Datos SDR'!$AB$6 -> 2 | J9: 0 | K9: SÍ | L9: NO | M9: 815 | N9: 615 | O9: 532 | P9: 266 | Q9: =INDEX(M9:P9,MATCH(TipoSuelo,{"Roca","Grava","Suelo mixto","Arcilla"},0)) -> 532 | R9: =Q9*IF(AND(C9="BOMAG",L9="SÍ"),MultTecBOMAG,1) -> 532 | S9: =R9*Eficiencia -> 532 | T9: =IF(AND(S9>0,VolumenCompactacion>0),VolumenCompactacion/S9,0) -> 0 | U9: =G9*PrecioDiesel+H9+I9 -> 17.88 | V9: =T9*U9 -> 0 | W9: =G9*HorasOperacion*PrecioDiesel -> 44640 | X9: =HorasOperacion*(H9+I9) -> 9000 | Y9: =IF(AND(B9="SDR",K9="NO"),HorasOperacion/JuntaIntervalo,0) -> 0 | Z9: =Y9*JuntaHorasIntervencion*(JuntaTecnico+JuntaParada)+Y9*JuntaGrasa -> 0 | AA9: =F9+W9+X9+Z9-J9 -> 122324 | AB9: =U9+IF(Y9>0,(JuntaHorasIntervencion*(JuntaTecnico+JuntaParada)+JuntaGrasa)/JuntaIntervalo,0) -> 17.88 | AC9: =IF(HorasOperacion>0,AA9/HorasOperacion,0) -> 40.774667 | AD9: =AA9*TasaMoneda -> 122324 | AE9: =IFERROR(AA9-INDEX($AA$5:$AA$64,MATCH(1,INDEX((B$5:B$64=B9)*(C$5:C$64="BOMAG"),0),0)),0) -> 13251.22
A10: =B10&" | "&C10&" | "&D10 -> SDR | BOMAG | BW213 D-5 SL | B10: SDR | C10: ='Datos SDR'!$B$7 -> BOMAG | D10: ='Datos SDR'!$C$7 -> BW213 D-5 SL | E10: ='Datos SDR'!$E$7 -> 12320 | F10: ='Datos SDR'!$Z$7 -> 72948 | G10: ='Datos SDR'!$Y$7 -> 12.4 | H10: ='Datos SDR'!$AA$7 -> 1 | I10: ='Datos SDR'!$AB$7 -> 2 | J10: 0 | K10: SÍ | L10: NO | M10: 772 | N10: 588 | O10: 504 | P10: 252 | Q10: =INDEX(M10:P10,MATCH(TipoSuelo,{"Roca","Grava","Suelo mixto","Arcilla"},0)) -> 504 | R10: =Q10*IF(AND(C10="BOMAG",L10="SÍ"),MultTecBOMAG,1) -> 504 | S10: =R10*Eficiencia -> 504 | T10: =IF(AND(S10>0,VolumenCompactacion>0),VolumenCompactacion/S10,0) -> 0 | U10: =G10*PrecioDiesel+H10+I10 -> 17.88 | V10: =T10*U10 -> 0 | W10: =G10*HorasOperacion*PrecioDiesel -> 44640 | X10: =HorasOperacion*(H10+I10) -> 9000 | Y10: =IF(AND(B10="SDR",K10="NO"),HorasOperacion/JuntaIntervalo,0) -> 0 | Z10: =Y10*JuntaHorasIntervencion*(JuntaTecnico+JuntaParada)+Y10*JuntaGrasa -> 0 | AA10: =F10+W10+X10+Z10-J10 -> 126588 | AB10: =U10+IF(Y10>0,(JuntaHorasIntervencion*(JuntaTecnico+JuntaParada)+JuntaGrasa)/JuntaIntervalo,0) -> 17.88 | AC10: =IF(HorasOperacion>0,AA10/HorasOperacion,0) -> 42.196 | AD10: =AA10*TasaMoneda -> 126588 | AE10: =IFERROR(AA10-INDEX($AA$5:$AA$64,MATCH(1,INDEX((B$5:B$64=B10)*(C$5:C$64="BOMAG"),0),0)),0) -> 17515.22
A11: =B11&" | "&C11&" | "&D11 -> SDR | BOMAG | BW213 D-5 SL TCD | B11: SDR | C11: ='Datos SDR'!$B$8 -> BOMAG | D11: ='Datos SDR'!$C$8 -> BW213 D-5 SL TCD | E11: ='Datos SDR'!$E$8 -> 11960 | F11: ='Datos SDR'!$Z$8 -> 72948 | G11: ='Datos SDR'!$Y$8 -> 12.4 | H11: ='Datos SDR'!$AA$8 -> 1 | I11: ='Datos SDR'!$AB$8 -> 2 | J11: 0 | K11: SÍ | L11: NO | M11: 893 | N11: 693 | O11: 595 | P11: 297 | Q11: =INDEX(M11:P11,MATCH(TipoSuelo,{"Roca","Grava","Suelo mixto","Arcilla"},0)) -> 595 | R11: =Q11*IF(AND(C11="BOMAG",L11="SÍ"),MultTecBOMAG,1) -> 595 | S11: =R11*Eficiencia -> 595 | T11: =IF(AND(S11>0,VolumenCompactacion>0),VolumenCompactacion/S11,0) -> 0 | U11: =G11*PrecioDiesel+H11+I11 -> 17.88 | V11: =T11*U11 -> 0 | W11: =G11*HorasOperacion*PrecioDiesel -> 44640 | X11: =HorasOperacion*(H11+I11) -> 9000 | Y11: =IF(AND(B11="SDR",K11="NO"),HorasOperacion/JuntaIntervalo,0) -> 0 | Z11: =Y11*JuntaHorasIntervencion*(JuntaTecnico+JuntaParada)+Y11*JuntaGrasa -> 0 | AA11: =F11+W11+X11+Z11-J11 -> 126588 | AB11: =U11+IF(Y11>0,(JuntaHorasIntervencion*(JuntaTecnico+JuntaParada)+JuntaGrasa)/JuntaIntervalo,0) -> 17.88 | AC11: =IF(HorasOperacion>0,AA11/HorasOperacion,0) -> 42.196 | AD11: =AA11*TasaMoneda -> 126588 | AE11: =IFERROR(AA11-INDEX($AA$5:$AA$64,MATCH(1,INDEX((B$5:B$64=B11)*(C$5:C$64="BOMAG"),0),0)),0) -> 17515.22
A12: =B12&" | "&C12&" | "&D12 -> SDR | BOMAG | BW216 D-5 SL | B12: SDR | C12: ='Datos SDR'!$B$9 -> BOMAG | D12: ='Datos SDR'!$C$9 -> BW216 D-5 SL | E12: ='Datos SDR'!$E$9 -> 14850 | F12: ='Datos SDR'!$Z$9 -> 0 | G12: ='Datos SDR'!$Y$9 -> 0 | H12: ='Datos SDR'!$AA$9 -> 1 | I12: ='Datos SDR'!$AB$9 -> 2 | J12: 0 | K12: SÍ | L12: NO | M12: 1055 | N12: 751 | O12: 608 | P12: 304 | Q12: =INDEX(M12:P12,MATCH(TipoSuelo,{"Roca","Grava","Suelo mixto","Arcilla"},0)) -> 608 | R12: =Q12*IF(AND(C12="BOMAG",L12="SÍ"),MultTecBOMAG,1) -> 608 | S12: =R12*Eficiencia -> 608 | T12: =IF(AND(S12>0,VolumenCompactacion>0),VolumenCompactacion/S12,0) -> 0 | U12: =G12*PrecioDiesel+H12+I12 -> 3 | V12: =T12*U12 -> 0 | W12: =G12*HorasOperacion*PrecioDiesel -> 0 | X12: =HorasOperacion*(H12+I12) -> 9000 | Y12: =IF(AND(B12="SDR",K12="NO"),HorasOperacion/JuntaIntervalo,0) -> 0 | Z12: =Y12*JuntaHorasIntervencion*(JuntaTecnico+JuntaParada)+Y12*JuntaGrasa -> 0 | AA12: =F12+W12+X12+Z12-J12 -> 9000 | AB12: =U12+IF(Y12>0,(JuntaHorasIntervencion*(JuntaTecnico+JuntaParada)+JuntaGrasa)/JuntaIntervalo,0) -> 3 | AC12: =IF(HorasOperacion>0,AA12/HorasOperacion,0) -> 3 | AD12: =AA12*TasaMoneda -> 9000 | AE12: =IFERROR(AA12-INDEX($AA$5:$AA$64,MATCH(1,INDEX((B$5:B$64=B12)*(C$5:C$64="BOMAG"),0),0)),0) -> -100072.78
A13: =B13&" | "&C13&" | "&D13 -> SDR | BOMAG | BW219 D-5 PL | B13: SDR | C13: ='Datos SDR'!$B$10 -> BOMAG | D13: ='Datos SDR'!$C$10 -> BW219 D-5 PL | E13: ='Datos SDR'!$E$10 -> 19400 | F13: ='Datos SDR'!$Z$10 -> 0 | G13: ='Datos SDR'!$Y$10 -> 0 | H13: ='Datos SDR'!$AA$10 -> 1 | I13: ='Datos SDR'!$AB$10 -> 2 | J13: 0 | K13: SÍ | L13: NO | M13: 987 | N13: 573 | O13: 547 | P13: 313 | Q13: =INDEX(M13:P13,MATCH(TipoSuelo,{"Roca","Grava","Suelo mixto","Arcilla"},0)) -> 547 | R13: =Q13*IF(AND(C13="BOMAG",L13="SÍ"),MultTecBOMAG,1) -> 547 | S13: =R13*Eficiencia -> 547 | T13: =IF(AND(S13>0,VolumenCompactacion>0),VolumenCompactacion/S13,0) -> 0 | U13: =G13*PrecioDiesel+H13+I13 -> 3 | V13: =T13*U13 -> 0 | W13: =G13*HorasOperacion*PrecioDiesel -> 0 | X13: =HorasOperacion*(H13+I13) -> 9000 | Y13: =IF(AND(B13="SDR",K13="NO"),HorasOperacion/JuntaIntervalo,0) -> 0 | Z13: =Y13*JuntaHorasIntervencion*(JuntaTecnico+JuntaParada)+Y13*JuntaGrasa -> 0 | AA13: =F13+W13+X13+Z13-J13 -> 9000 | AB13: =U13+IF(Y13>0,(JuntaHorasIntervencion*(JuntaTecnico+JuntaParada)+JuntaGrasa)/JuntaIntervalo,0) -> 3 | AC13: =IF(HorasOperacion>0,AA13/HorasOperacion,0) -> 3 | AD13: =AA13*TasaMoneda -> 9000 | AE13: =IFERROR(AA13-INDEX($AA$5:$AA$64,MATCH(1,INDEX((B$5:B$64=B13)*(C$5:C$64="BOMAG"),0),0)),0) -> -100072.78
A14: =B14&" | "&C14&" | "&D14 -> SDR | BOMAG | BW220 D-5 PL | B14: SDR | C14: ='Datos SDR'!$B$11 -> BOMAG | D14: ='Datos SDR'!$C$11 -> BW220 D-5 PL | E14: ='Datos SDR'!$E$11 -> 20100 | F14: ='Datos SDR'!$Z$11 -> 0 | G14: ='Datos SDR'!$Y$11 -> 0 | H14: ='Datos SDR'!$AA$11 -> 1 | I14: ='Datos SDR'!$AB$11 -> 2 | J14: 0 | K14: SÍ | L14: NO | M14: 1138 | N14: 702 | O14: 628 | P14: 337 | Q14: =INDEX(M14:P14,MATCH(TipoSuelo,{"Roca","Grava","Suelo mixto","Arcilla"},0)) -> 628 | R14: =Q14*IF(AND(C14="BOMAG",L14="SÍ"),MultTecBOMAG,1) -> 628 | S14: =R14*Eficiencia -> 628 | T14: =IF(AND(S14>0,VolumenCompactacion>0),VolumenCompactacion/S14,0) -> 0 | U14: =G14*PrecioDiesel+H14+I14 -> 3 | V14: =T14*U14 -> 0 | W14: =G14*HorasOperacion*PrecioDiesel -> 0 | X14: =HorasOperacion*(H14+I14) -> 9000 | Y14: =IF(AND(B14="SDR",K14="NO"),HorasOperacion/JuntaIntervalo,0) -> 0 | Z14: =Y14*JuntaHorasIntervencion*(JuntaTecnico+JuntaParada)+Y14*JuntaGrasa -> 0 | AA14: =F14+W14+X14+Z14-J14 -> 9000 | AB14: =U14+IF(Y14>0,(JuntaHorasIntervencion*(JuntaTecnico+JuntaParada)+JuntaGrasa)/JuntaIntervalo,0) -> 3 | AC14: =IF(HorasOperacion>0,AA14/HorasOperacion,0) -> 3 | AD14: =AA14*TasaMoneda -> 9000 | AE14: =IFERROR(AA14-INDEX($AA$5:$AA$64,MATCH(1,INDEX((B$5:B$64=B14)*(C$5:C$64="BOMAG"),0),0)),0) -> -100072.78
A15: =B15&" | "&C15&" | "&D15 -> SDR | SAKAI | SV521D | B15: SDR | C15: ='Datos SDR'!$B$12 -> SAKAI | D15: ='Datos SDR'!$C$12 -> SV521D | E15: ='Datos SDR'!$E$12 -> 10720 | F15: ='Datos SDR'!$Z$12 -> 0 | G15: ='Datos SDR'!$Y$12 -> 0 | H15: ='Datos SDR'!$AA$12 -> 1 | I15: ='Datos SDR'!$AB$12 -> 2 | J15: 0 | K15: NO | L15: N/A | M15: 687 | N15: 487 | O15: 429 | P15: 215 | Q15: =INDEX(M15:P15,MATCH(TipoSuelo,{"Roca","Grava","Suelo mixto","Arcilla"},0)) -> 429 | R15: =Q15*IF(AND(C15="BOMAG",L15="SÍ"),MultTecBOMAG,1) -> 429 | S15: =R15*Eficiencia -> 429 | T15: =IF(AND(S15>0,VolumenCompactacion>0),VolumenCompactacion/S15,0) -> 0 | U15: =G15*PrecioDiesel+H15+I15 -> 3 | V15: =T15*U15 -> 0 | W15: =G15*HorasOperacion*PrecioDiesel -> 0 | X15: =HorasOperacion*(H15+I15) -> 9000 | Y15: =IF(AND(B15="SDR",K15="NO"),HorasOperacion/JuntaIntervalo,0) -> 60 | Z15: =Y15*JuntaHorasIntervencion*(JuntaTecnico+JuntaParada)+Y15*JuntaGrasa -> 5550 | AA15: =F15+W15+X15+Z15-J15 -> 14550 | AB15: =U15+IF(Y15>0,(JuntaHorasIntervencion*(JuntaTecnico+JuntaParada)+JuntaGrasa)/JuntaIntervalo,0) -> 4.85 | AC15: =IF(HorasOperacion>0,AA15/HorasOperacion,0) -> 4.85 | AD15: =AA15*TasaMoneda -> 14550 | AE15: =IFERROR(AA15-INDEX($AA$5:$AA$64,MATCH(1,INDEX((B$5:B$64=B15)*(C$5:C$64="BOMAG"),0),0)),0) -> -94522.78
A16: =B16&" | "&C16&" | "&D16 -> SDR | SAKAI | SV621D | B16: SDR | C16: ='Datos SDR'!$B$13 -> SAKAI | D16: ='Datos SDR'!$C$13 -> SV621D | E16: ='Datos SDR'!$E$13 -> 13020 | F16: ='Datos SDR'!$Z$13 -> 0 | G16: ='Datos SDR'!$Y$13 -> 0 | H16: ='Datos SDR'!$AA$13 -> 1 | I16: ='Datos SDR'!$AB$13 -> 2 | J16: 0 | K16: NO | L16: N/A | M16: 506 | N16: 354 | O16: 303 | P16: 152 | Q16: =INDEX(M16:P16,MATCH(TipoSuelo,{"Roca","Grava","Suelo mixto","Arcilla"},0)) -> 303 | R16: =Q16*IF(AND(C16="BOMAG",L16="SÍ"),MultTecBOMAG,1) -> 303 | S16: =R16*Eficiencia -> 303 | T16: =IF(AND(S16>0,VolumenCompactacion>0),VolumenCompactacion/S16,0) -> 0 | U16: =G16*PrecioDiesel+H16+I16 -> 3 | V16: =T16*U16 -> 0 | W16: =G16*HorasOperacion*PrecioDiesel -> 0 | X16: =HorasOperacion*(H16+I16) -> 9000 | Y16: =IF(AND(B16="SDR",K16="NO"),HorasOperacion/JuntaIntervalo,0) -> 60 | Z16: =Y16*JuntaHorasIntervencion*(JuntaTecnico+JuntaParada)+Y16*JuntaGrasa -> 5550 | AA16: =F16+W16+X16+Z16-J16 -> 14550 | AB16: =U16+IF(Y16>0,(JuntaHorasIntervencion*(JuntaTecnico+JuntaParada)+JuntaGrasa)/JuntaIntervalo,0) -> 4.85 | AC16: =IF(HorasOperacion>0,AA16/HorasOperacion,0) -> 4.85 | AD16: =AA16*TasaMoneda -> 14550 | AE16: =IFERROR(AA16-INDEX($AA$5:$AA$64,MATCH(1,INDEX((B$5:B$64=B16)*(C$5:C$64="BOMAG"),0),0)),0) -> -94522.78
A17: =B17&" | "&C17&" | "&D17 -> SDR | SAKAI | SV700D | B17: SDR | C17: ='Datos SDR'!$B$14 -> SAKAI | D17: ='Datos SDR'!$C$14 -> SV700D | E17: ='Datos SDR'!$E$14 -> 14950 | F17: ='Datos SDR'!$Z$14 -> 0 | G17: ='Datos SDR'!$Y$14 -> 0 | H17: ='Datos SDR'!$AA$14 -> 1 | I17: ='Datos SDR'!$AB$14 -> 2 | J17: 0 | K17: NO | L17: N/A | M17: 1085 | N17: 772 | O17: 625 | P17: 312 | Q17: =INDEX(M17:P17,MATCH(TipoSuelo,{"Roca","Grava","Suelo mixto","Arcilla"},0)) -> 625 | R17: =Q17*IF(AND(C17="BOMAG",L17="SÍ"),MultTecBOMAG,1) -> 625 | S17: =R17*Eficiencia -> 625 | T17: =IF(AND(S17>0,VolumenCompactacion>0),VolumenCompactacion/S17,0) -> 0 | U17: =G17*PrecioDiesel+H17+I17 -> 3 | V17: =T17*U17 -> 0 | W17: =G17*HorasOperacion*PrecioDiesel -> 0 | X17: =HorasOperacion*(H17+I17) -> 9000 | Y17: =IF(AND(B17="SDR",K17="NO"),HorasOperacion/JuntaIntervalo,0) -> 60 | Z17: =Y17*JuntaHorasIntervencion*(JuntaTecnico+JuntaParada)+Y17*JuntaGrasa -> 5550 | AA17: =F17+W17+X17+Z17-J17 -> 14550 | AB17: =U17+IF(Y17>0,(JuntaHorasIntervencion*(JuntaTecnico+JuntaParada)+JuntaGrasa)/JuntaIntervalo,0) -> 4.85 | AC17: =IF(HorasOperacion>0,AA17/HorasOperacion,0) -> 4.85 | AD17: =AA17*TasaMoneda -> 14550 | AE17: =IFERROR(AA17-INDEX($AA$5:$AA$64,MATCH(1,INDEX((B$5:B$64=B17)*(C$5:C$64="BOMAG"),0),0)),0) -> -94522.78
A18: =B18&" | "&C18&" | "&D18 -> SDR | SAKAI | SV900-1 | B18: SDR | C18: ='Datos SDR'!$B$15 -> SAKAI | D18: ='Datos SDR'!$C$15 -> SV900-1 | E18: ='Datos SDR'!$E$15 -> 19350 | F18: ='Datos SDR'!$Z$15 -> 0 | G18: ='Datos SDR'!$Y$15 -> 0 | H18: ='Datos SDR'!$AA$15 -> 1 | I18: ='Datos SDR'!$AB$15 -> 2 | J18: 0 | K18: NO | L18: N/A | M18: 976 | N18: 564 | O18: 541 | P18: 312 | Q18: =INDEX(M18:P18,MATCH(TipoSuelo,{"Roca","Grava","Suelo mixto","Arcilla"},0)) -> 541 | R18: =Q18*IF(AND(C18="BOMAG",L18="SÍ"),MultTecBOMAG,1) -> 541 | S18: =R18*Eficiencia -> 541 | T18: =IF(AND(S18>0,VolumenCompactacion>0),VolumenCompactacion/S18,0) -> 0 | U18: =G18*PrecioDiesel+H18+I18 -> 3 | V18: =T18*U18 -> 0 | W18: =G18*HorasOperacion*PrecioDiesel -> 0 | X18: =HorasOperacion*(H18+I18) -> 9000 | Y18: =IF(AND(B18="SDR",K18="NO"),HorasOperacion/JuntaIntervalo,0) -> 60 | Z18: =Y18*JuntaHorasIntervencion*(JuntaTecnico+JuntaParada)+Y18*JuntaGrasa -> 5550 | AA18: =F18+W18+X18+Z18-J18 -> 14550 | AB18: =U18+IF(Y18>0,(JuntaHorasIntervencion*(JuntaTecnico+JuntaParada)+JuntaGrasa)/JuntaIntervalo,0) -> 4.85 | AC18: =IF(HorasOperacion>0,AA18/HorasOperacion,0) -> 4.85 | AD18: =AA18*TasaMoneda -> 14550 | AE18: =IFERROR(AA18-INDEX($AA$5:$AA$64,MATCH(1,INDEX((B$5:B$64=B18)*(C$5:C$64="BOMAG"),0),0)),0) -> -94522.78
A19: =B19&" | "&C19&" | "&D19 -> SDR | DYNAPAC | CA25 D-Rhino | B19: SDR | C19: ='Datos SDR'!$B$16 -> DYNAPAC | D19: ='Datos SDR'!$C$16 -> CA25 D-Rhino | E19: ='Datos SDR'!$E$16 -> 10400 | F19: ='Datos SDR'!$Z$16 -> 90000 | G19: ='Datos SDR'!$Y$16 -> 13.6 | H19: ='Datos SDR'!$AA$16 -> 1 | I19: ='Datos SDR'!$AB$16 -> 2 | J19: 0 | K19: NO | L19: N/A | M19: 633 | N19: 433 | O19: 387 | P19: 193 | Q19: =INDEX(M19:P19,MATCH(TipoSuelo,{"Roca","Grava","Suelo mixto","Arcilla"},0)) -> 387 | R19: =Q19*IF(AND(C19="BOMAG",L19="SÍ"),MultTecBOMAG,1) -> 387 | S19: =R19*Eficiencia -> 387 | T19: =IF(AND(S19>0,VolumenCompactacion>0),VolumenCompactacion/S19,0) -> 0 | U19: =G19*PrecioDiesel+H19+I19 -> 19.32 | V19: =T19*U19 -> 0 | W19: =G19*HorasOperacion*PrecioDiesel -> 48960 | X19: =HorasOperacion*(H19+I19) -> 9000 | Y19: =IF(AND(B19="SDR",K19="NO"),HorasOperacion/JuntaIntervalo,0) -> 60 | Z19: =Y19*JuntaHorasIntervencion*(JuntaTecnico+JuntaParada)+Y19*JuntaGrasa -> 5550 | AA19: =F19+W19+X19+Z19-J19 -> 153510 | AB19: =U19+IF(Y19>0,(JuntaHorasIntervencion*(JuntaTecnico+JuntaParada)+JuntaGrasa)/JuntaIntervalo,0) -> 21.17 | AC19: =IF(HorasOperacion>0,AA19/HorasOperacion,0) -> 51.17 | AD19: =AA19*TasaMoneda -> 153510 | AE19: =IFERROR(AA19-INDEX($AA$5:$AA$64,MATCH(1,INDEX((B$5:B$64=B19)*(C$5:C$64="BOMAG"),0),0)),0) -> 44437.22
A20: =B20&" | "&C20&" | "&D20 -> SDR | DYNAPAC | CA35 D-Rhino | B20: SDR | C20: ='Datos SDR'!$B$17 -> DYNAPAC | D20: ='Datos SDR'!$C$17 -> CA35 D-Rhino | E20: ='Datos SDR'!$E$17 -> 12200 | F20: ='Datos SDR'!$Z$17 -> 90000 | G20: ='Datos SDR'!$Y$17 -> 13.6 | H20: ='Datos SDR'!$AA$17 -> 1 | I20: ='Datos SDR'!$AB$17 -> 2 | J20: 0 | K20: NO | L20: N/A | M20: 820 | N20: 630 | O20: 540 | P20: 270 | Q20: =INDEX(M20:P20,MATCH(TipoSuelo,{"Roca","Grava","Suelo mixto","Arcilla"},0)) -> 540 | R20: =Q20*IF(AND(C20="BOMAG",L20="SÍ"),MultTecBOMAG,1) -> 540 | S20: =R20*Eficiencia -> 540 | T20: =IF(AND(S20>0,VolumenCompactacion>0),VolumenCompactacion/S20,0) -> 0 | U20: =G20*PrecioDiesel+H20+I20 -> 19.32 | V20: =T20*U20 -> 0 | W20: =G20*HorasOperacion*PrecioDiesel -> 48960 | X20: =HorasOperacion*(H20+I20) -> 9000 | Y20: =IF(AND(B20="SDR",K20="NO"),HorasOperacion/JuntaIntervalo,0) -> 60 | Z20: =Y20*JuntaHorasIntervencion*(JuntaTecnico+JuntaParada)+Y20*JuntaGrasa -> 5550 | AA20: =F20+W20+X20+Z20-J20 -> 153510 | AB20: =U20+IF(Y20>0,(JuntaHorasIntervencion*(JuntaTecnico+JuntaParada)+JuntaGrasa)/JuntaIntervalo,0) -> 21.17 | AC20: =IF(HorasOperacion>0,AA20/HorasOperacion,0) -> 51.17 | AD20: =AA20*TasaMoneda -> 153510 | AE20: =IFERROR(AA20-INDEX($AA$5:$AA$64,MATCH(1,INDEX((B$5:B$64=B20)*(C$5:C$64="BOMAG"),0),0)),0) -> 44437.22
A21: =B21&" | "&C21&" | "&D21 -> SDR | DYNAPAC | CA2500D | B21: SDR | C21: ='Datos SDR'!$B$18 -> DYNAPAC | D21: ='Datos SDR'!$C$18 -> CA2500D | E21: ='Datos SDR'!$E$18 -> 10000 | F21: ='Datos SDR'!$Z$18 -> 0 | G21: ='Datos SDR'!$Y$18 -> 0 | H21: ='Datos SDR'!$AA$18 -> 1 | I21: ='Datos SDR'!$AB$18 -> 2 | J21: 0 | K21: NO | L21: N/A | M21: 567 | N21: 367 | O21: 333 | P21: 167 | Q21: =INDEX(M21:P21,MATCH(TipoSuelo,{"Roca","Grava","Suelo mixto","Arcilla"},0)) -> 333 | R21: =Q21*IF(AND(C21="BOMAG",L21="SÍ"),MultTecBOMAG,1) -> 333 | S21: =R21*Eficiencia -> 333 | T21: =IF(AND(S21>0,VolumenCompactacion>0),VolumenCompactacion/S21,0) -> 0 | U21: =G21*PrecioDiesel+H21+I21 -> 3 | V21: =T21*U21 -> 0 | W21: =G21*HorasOperacion*PrecioDiesel -> 0 | X21: =HorasOperacion*(H21+I21) -> 9000 | Y21: =IF(AND(B21="SDR",K21="NO"),HorasOperacion/JuntaIntervalo,0) -> 60 | Z21: =Y21*JuntaHorasIntervencion*(JuntaTecnico+JuntaParada)+Y21*JuntaGrasa -> 5550 | AA21: =F21+W21+X21+Z21-J21 -> 14550 | AB21: =U21+IF(Y21>0,(JuntaHorasIntervencion*(JuntaTecnico+JuntaParada)+JuntaGrasa)/JuntaIntervalo,0) -> 4.85 | AC21: =IF(HorasOperacion>0,AA21/HorasOperacion,0) -> 4.85 | AD21: =AA21*TasaMoneda -> 14550 | AE21: =IFERROR(AA21-INDEX($AA$5:$AA$64,MATCH(1,INDEX((B$5:B$64=B21)*(C$5:C$64="BOMAG"),0),0)),0) -> -94522.78
A22: =B22&" | "&C22&" | "&D22 -> SDR | DYNAPAC | CA3500D | B22: SDR | C22: ='Datos SDR'!$B$19 -> DYNAPAC | D22: ='Datos SDR'!$C$19 -> CA3500D | E22: ='Datos SDR'!$E$19 -> 16000 | F22: ='Datos SDR'!$Z$19 -> 90000 | G22: ='Datos SDR'!$Y$19 -> 13.6 | H22: ='Datos SDR'!$AA$19 -> 1 | I22: ='Datos SDR'!$AB$19 -> 2 | J22: 0 | K22: NO | L22: N/A | M22: 1400 | N22: 1000 | O22: 800 | P22: 400 | Q22: =INDEX(M22:P22,MATCH(TipoSuelo,{"Roca","Grava","Suelo mixto","Arcilla"},0)) -> 800 | R22: =Q22*IF(AND(C22="BOMAG",L22="SÍ"),MultTecBOMAG,1) -> 800 | S22: =R22*Eficiencia -> 800 | T22: =IF(AND(S22>0,VolumenCompactacion>0),VolumenCompactacion/S22,0) -> 0 | U22: =G22*PrecioDiesel+H22+I22 -> 19.32 | V22: =T22*U22 -> 0 | W22: =G22*HorasOperacion*PrecioDiesel -> 48960 | X22: =HorasOperacion*(H22+I22) -> 9000 | Y22: =IF(AND(B22="SDR",K22="NO"),HorasOperacion/JuntaIntervalo,0) -> 60 | Z22: =Y22*JuntaHorasIntervencion*(JuntaTecnico+JuntaParada)+Y22*JuntaGrasa -> 5550 | AA22: =F22+W22+X22+Z22-J22 -> 153510 | AB22: =U22+IF(Y22>0,(JuntaHorasIntervencion*(JuntaTecnico+JuntaParada)+JuntaGrasa)/JuntaIntervalo,0) -> 21.17 | AC22: =IF(HorasOperacion>0,AA22/HorasOperacion,0) -> 51.17 | AD22: =AA22*TasaMoneda -> 153510 | AE22: =IFERROR(AA22-INDEX($AA$5:$AA$64,MATCH(1,INDEX((B$5:B$64=B22)*(C$5:C$64="BOMAG"),0),0)),0) -> 44437.22
A23: =B23&" | "&C23&" | "&D23 -> SDR | DYNAPAC | CA4500D | B23: SDR | C23: ='Datos SDR'!$B$20 -> DYNAPAC | D23: ='Datos SDR'!$C$20 -> CA4500D | E23: ='Datos SDR'!$E$20 -> 21000 | F23: ='Datos SDR'!$Z$20 -> 0 | G23: ='Datos SDR'!$Y$20 -> 0 | H23: ='Datos SDR'!$AA$20 -> 1 | I23: ='Datos SDR'!$AB$20 -> 2 | J23: 0 | K23: NO | L23: N/A | M23: 1333 | N23: 867 | O23: 733 | P23: 367 | Q23: =INDEX(M23:P23,MATCH(TipoSuelo,{"Roca","Grava","Suelo mixto","Arcilla"},0)) -> 733 | R23: =Q23*IF(AND(C23="BOMAG",L23="SÍ"),MultTecBOMAG,1) -> 733 | S23: =R23*Eficiencia -> 733 | T23: =IF(AND(S23>0,VolumenCompactacion>0),VolumenCompactacion/S23,0) -> 0 | U23: =G23*PrecioDiesel+H23+I23 -> 3 | V23: =T23*U23 -> 0 | W23: =G23*HorasOperacion*PrecioDiesel -> 0 | X23: =HorasOperacion*(H23+I23) -> 9000 | Y23: =IF(AND(B23="SDR",K23="NO"),HorasOperacion/JuntaIntervalo,0) -> 60 | Z23: =Y23*JuntaHorasIntervencion*(JuntaTecnico+JuntaParada)+Y23*JuntaGrasa -> 5550 | AA23: =F23+W23+X23+Z23-J23 -> 14550 | AB23: =U23+IF(Y23>0,(JuntaHorasIntervencion*(JuntaTecnico+JuntaParada)+JuntaGrasa)/JuntaIntervalo,0) -> 4.85 | AC23: =IF(HorasOperacion>0,AA23/HorasOperacion,0) -> 4.85 | AD23: =AA23*TasaMoneda -> 14550 | AE23: =IFERROR(AA23-INDEX($AA$5:$AA$64,MATCH(1,INDEX((B$5:B$64=B23)*(C$5:C$64="BOMAG"),0),0)),0) -> -94522.78
A24: =B24&" | "&C24&" | "&D24 -> SDR | DYNAPAC REDLINE | DRS120D | B24: SDR | C24: ='Datos SDR'!$B$21 -> DYNAPAC REDLINE | D24: ='Datos SDR'!$C$21 -> DRS120D | E24: ='Datos SDR'!$E$21 -> 11400 | F24: ='Datos SDR'!$Z$21 -> 0 | G24: ='Datos SDR'!$Y$21 -> 0 | H24: ='Datos SDR'!$AA$21 -> 1 | I24: ='Datos SDR'!$AB$21 -> 2 | J24: 0 | K24: NO | L24: N/A | M24: 800 | N24: 600 | O24: 520 | P24: 260 | Q24: =INDEX(M24:P24,MATCH(TipoSuelo,{"Roca","Grava","Suelo mixto","Arcilla"},0)) -> 520 | R24: =Q24*IF(AND(C24="BOMAG",L24="SÍ"),MultTecBOMAG,1) -> 520 | S24: =R24*Eficiencia -> 520 | T24: =IF(AND(S24>0,VolumenCompactacion>0),VolumenCompactacion/S24,0) -> 0 | U24: =G24*PrecioDiesel+H24+I24 -> 3 | V24: =T24*U24 -> 0 | W24: =G24*HorasOperacion*PrecioDiesel -> 0 | X24: =HorasOperacion*(H24+I24) -> 9000 | Y24: =IF(AND(B24="SDR",K24="NO"),HorasOperacion/JuntaIntervalo,0) -> 60 | Z24: =Y24*JuntaHorasIntervencion*(JuntaTecnico+JuntaParada)+Y24*JuntaGrasa -> 5550 | AA24: =F24+W24+X24+Z24-J24 -> 14550 | AB24: =U24+IF(Y24>0,(JuntaHorasIntervencion*(JuntaTecnico+JuntaParada)+JuntaGrasa)/JuntaIntervalo,0) -> 4.85 | AC24: =IF(HorasOperacion>0,AA24/HorasOperacion,0) -> 4.85 | AD24: =AA24*TasaMoneda -> 14550 | AE24: =IFERROR(AA24-INDEX($AA$5:$AA$64,MATCH(1,INDEX((B$5:B$64=B24)*(C$5:C$64="BOMAG"),0),0)),0) -> -94522.78
A25: =B25&" | "&C25&" | "&D25 -> SDR | HAMM | HC110 | B25: SDR | C25: ='Datos SDR'!$B$22 -> HAMM | D25: ='Datos SDR'!$C$22 -> HC110 | E25: ='Datos SDR'!$E$22 -> 11765 | F25: ='Datos SDR'!$Z$22 -> 91845.1 | G25: ='Datos SDR'!$Y$22 -> 13.6 | H25: ='Datos SDR'!$AA$22 -> 1 | I25: ='Datos SDR'!$AB$22 -> 2 | J25: 0 | K25: NO | L25: N/A | M25: 861 | N25: 661 | O25: 569 | P25: 284 | Q25: =INDEX(M25:P25,MATCH(TipoSuelo,{"Roca","Grava","Suelo mixto","Arcilla"},0)) -> 569 | R25: =Q25*IF(AND(C25="BOMAG",L25="SÍ"),MultTecBOMAG,1) -> 569 | S25: =R25*Eficiencia -> 569 | T25: =IF(AND(S25>0,VolumenCompactacion>0),VolumenCompactacion/S25,0) -> 0 | U25: =G25*PrecioDiesel+H25+I25 -> 19.32 | V25: =T25*U25 -> 0 | W25: =G25*HorasOperacion*PrecioDiesel -> 48960 | X25: =HorasOperacion*(H25+I25) -> 9000 | Y25: =IF(AND(B25="SDR",K25="NO"),HorasOperacion/JuntaIntervalo,0) -> 60 | Z25: =Y25*JuntaHorasIntervencion*(JuntaTecnico+JuntaParada)+Y25*JuntaGrasa -> 5550 | AA25: =F25+W25+X25+Z25-J25 -> 155355.1 | AB25: =U25+IF(Y25>0,(JuntaHorasIntervencion*(JuntaTecnico+JuntaParada)+JuntaGrasa)/JuntaIntervalo,0) -> 21.17 | AC25: =IF(HorasOperacion>0,AA25/HorasOperacion,0) -> 51.785033 | AD25: =AA25*TasaMoneda -> 155355.1 | AE25: =IFERROR(AA25-INDEX($AA$5:$AA$64,MATCH(1,INDEX((B$5:B$64=B25)*(C$5:C$64="BOMAG"),0),0)),0) -> 46282.32
A26: =B26&" | "&C26&" | "&D26 -> SDR | HAMM | HC119 | B26: SDR | C26: ='Datos SDR'!$B$23 -> HAMM | D26: ='Datos SDR'!$C$23 -> HC119 | E26: ='Datos SDR'!$E$23 -> 11745 | F26: ='Datos SDR'!$Z$23 -> 91845.1 | G26: ='Datos SDR'!$Y$23 -> 13.6 | H26: ='Datos SDR'!$AA$23 -> 1 | I26: ='Datos SDR'!$AB$23 -> 2 | J26: 0 | K26: NO | L26: N/A | M26: 857 | N26: 657 | O26: 566 | P26: 283 | Q26: =INDEX(M26:P26,MATCH(TipoSuelo,{"Roca","Grava","Suelo mixto","Arcilla"},0)) -> 566 | R26: =Q26*IF(AND(C26="BOMAG",L26="SÍ"),MultTecBOMAG,1) -> 566 | S26: =R26*Eficiencia -> 566 | T26: =IF(AND(S26>0,VolumenCompactacion>0),VolumenCompactacion/S26,0) -> 0 | U26: =G26*PrecioDiesel+H26+I26 -> 19.32 | V26: =T26*U26 -> 0 | W26: =G26*HorasOperacion*PrecioDiesel -> 48960 | X26: =HorasOperacion*(H26+I26) -> 9000 | Y26: =IF(AND(B26="SDR",K26="NO"),HorasOperacion/JuntaIntervalo,0) -> 60 | Z26: =Y26*JuntaHorasIntervencion*(JuntaTecnico+JuntaParada)+Y26*JuntaGrasa -> 5550 | AA26: =F26+W26+X26+Z26-J26 -> 155355.1 | AB26: =U26+IF(Y26>0,(JuntaHorasIntervencion*(JuntaTecnico+JuntaParada)+JuntaGrasa)/JuntaIntervalo,0) -> 21.17 | AC26: =IF(HorasOperacion>0,AA26/HorasOperacion,0) -> 51.785033 | AD26: =AA26*TasaMoneda -> 155355.1 | AE26: =IFERROR(AA26-INDEX($AA$5:$AA$64,MATCH(1,INDEX((B$5:B$64=B26)*(C$5:C$64="BOMAG"),0),0)),0) -> 46282.32
A27: =B27&" | "&C27&" | "&D27 -> SDR | HAMM | H13i | B27: SDR | C27: ='Datos SDR'!$B$24 -> HAMM | D27: ='Datos SDR'!$C$24 -> H13i | E27: ='Datos SDR'!$E$24 -> 12600 | F27: ='Datos SDR'!$Z$24 -> 0 | G27: ='Datos SDR'!$Y$24 -> 0 | H27: ='Datos SDR'!$AA$24 -> 1 | I27: ='Datos SDR'!$AB$24 -> 2 | J27: 0 | K27: NO | L27: N/A | M27: 660 | N27: 490 | O27: 420 | P27: 210 | Q27: =INDEX(M27:P27,MATCH(TipoSuelo,{"Roca","Grava","Suelo mixto","Arcilla"},0)) -> 420 | R27: =Q27*IF(AND(C27="BOMAG",L27="SÍ"),MultTecBOMAG,1) -> 420 | S27: =R27*Eficiencia -> 420 | T27: =IF(AND(S27>0,VolumenCompactacion>0),VolumenCompactacion/S27,0) -> 0 | U27: =G27*PrecioDiesel+H27+I27 -> 3 | V27: =T27*U27 -> 0 | W27: =G27*HorasOperacion*PrecioDiesel -> 0 | X27: =HorasOperacion*(H27+I27) -> 9000 | Y27: =IF(AND(B27="SDR",K27="NO"),HorasOperacion/JuntaIntervalo,0) -> 60 | Z27: =Y27*JuntaHorasIntervencion*(JuntaTecnico+JuntaParada)+Y27*JuntaGrasa -> 5550 | AA27: =F27+W27+X27+Z27-J27 -> 14550 | AB27: =U27+IF(Y27>0,(JuntaHorasIntervencion*(JuntaTecnico+JuntaParada)+JuntaGrasa)/JuntaIntervalo,0) -> 4.85 | AC27: =IF(HorasOperacion>0,AA27/HorasOperacion,0) -> 4.85 | AD27: =AA27*TasaMoneda -> 14550 | AE27: =IFERROR(AA27-INDEX($AA$5:$AA$64,MATCH(1,INDEX((B$5:B$64=B27)*(C$5:C$64="BOMAG"),0),0)),0) -> -94522.78
A28: =B28&" | "&C28&" | "&D28 -> SDR | HAMM | H16i | B28: SDR | C28: ='Datos SDR'!$B$25 -> HAMM | D28: ='Datos SDR'!$C$25 -> H16i | E28: ='Datos SDR'!$E$25 -> 16430 | F28: ='Datos SDR'!$Z$25 -> 0 | G28: ='Datos SDR'!$Y$25 -> 0 | H28: ='Datos SDR'!$AA$25 -> 1 | I28: ='Datos SDR'!$AB$25 -> 2 | J28: 0 | K28: NO | L28: N/A | M28: 1328 | N28: 928 | O28: 757 | P28: 386 | Q28: =INDEX(M28:P28,MATCH(TipoSuelo,{"Roca","Grava","Suelo mixto","Arcilla"},0)) -> 757 | R28: =Q28*IF(AND(C28="BOMAG",L28="SÍ"),MultTecBOMAG,1) -> 757 | S28: =R28*Eficiencia -> 757 | T28: =IF(AND(S28>0,VolumenCompactacion>0),VolumenCompactacion/S28,0) -> 0 | U28: =G28*PrecioDiesel+H28+I28 -> 3 | V28: =T28*U28 -> 0 | W28: =G28*HorasOperacion*PrecioDiesel -> 0 | X28: =HorasOperacion*(H28+I28) -> 9000 | Y28: =IF(AND(B28="SDR",K28="NO"),HorasOperacion/JuntaIntervalo,0) -> 60 | Z28: =Y28*JuntaHorasIntervencion*(JuntaTecnico+JuntaParada)+Y28*JuntaGrasa -> 5550 | AA28: =F28+W28+X28+Z28-J28 -> 14550 | AB28: =U28+IF(Y28>0,(JuntaHorasIntervencion*(JuntaTecnico+JuntaParada)+JuntaGrasa)/JuntaIntervalo,0) -> 4.85 | AC28: =IF(HorasOperacion>0,AA28/HorasOperacion,0) -> 4.85 | AD28: =AA28*TasaMoneda -> 14550 | AE28: =IFERROR(AA28-INDEX($AA$5:$AA$64,MATCH(1,INDEX((B$5:B$64=B28)*(C$5:C$64="BOMAG"),0),0)),0) -> -94522.78
A29: =B29&" | "&C29&" | "&D29 -> SDR | HAMM | H18i | B29: SDR | C29: ='Datos SDR'!$B$26 -> HAMM | D29: ='Datos SDR'!$C$26 -> H18i | E29: ='Datos SDR'!$E$26 -> 18000 | F29: ='Datos SDR'!$Z$26 -> 0 | G29: ='Datos SDR'!$Y$26 -> 0 | H29: ='Datos SDR'!$AA$26 -> 1 | I29: ='Datos SDR'!$AB$26 -> 2 | J29: 0 | K29: NO | L29: N/A | M29: 1067 | N29: 667 | O29: 600 | P29: 333 | Q29: =INDEX(M29:P29,MATCH(TipoSuelo,{"Roca","Grava","Suelo mixto","Arcilla"},0)) -> 600 | R29: =Q29*IF(AND(C29="BOMAG",L29="SÍ"),MultTecBOMAG,1) -> 600 | S29: =R29*Eficiencia -> 600 | T29: =IF(AND(S29>0,VolumenCompactacion>0),VolumenCompactacion/S29,0) -> 0 | U29: =G29*PrecioDiesel+H29+I29 -> 3 | V29: =T29*U29 -> 0 | W29: =G29*HorasOperacion*PrecioDiesel -> 0 | X29: =HorasOperacion*(H29+I29) -> 9000 | Y29: =IF(AND(B29="SDR",K29="NO"),HorasOperacion/JuntaIntervalo,0) -> 60 | Z29: =Y29*JuntaHorasIntervencion*(JuntaTecnico+JuntaParada)+Y29*JuntaGrasa -> 5550 | AA29: =F29+W29+X29+Z29-J29 -> 14550 | AB29: =U29+IF(Y29>0,(JuntaHorasIntervencion*(JuntaTecnico+JuntaParada)+JuntaGrasa)/JuntaIntervalo,0) -> 4.85 | AC29: =IF(HorasOperacion>0,AA29/HorasOperacion,0) -> 4.85 | AD29: =AA29*TasaMoneda -> 14550 | AE29: =IFERROR(AA29-INDEX($AA$5:$AA$64,MATCH(1,INDEX((B$5:B$64=B29)*(C$5:C$64="BOMAG"),0),0)),0) -> -94522.78
A30: =B30&" | "&C30&" | "&D30 -> SDR | HAMM | H25i | B30: SDR | C30: ='Datos SDR'!$B$27 -> HAMM | D30: ='Datos SDR'!$C$27 -> H25i | E30: ='Datos SDR'!$E$27 -> 24925 | F30: ='Datos SDR'!$Z$27 -> 0 | G30: ='Datos SDR'!$Y$27 -> 0 | H30: ='Datos SDR'!$AA$27 -> 1 | I30: ='Datos SDR'!$AB$27 -> 2 | J30: 0 | K30: NO | L30: N/A | M30: 2184 | N30: 1586 | O30: 1191 | P30: 498 | Q30: =INDEX(M30:P30,MATCH(TipoSuelo,{"Roca","Grava","Suelo mixto","Arcilla"},0)) -> 1191 | R30: =Q30*IF(AND(C30="BOMAG",L30="SÍ"),MultTecBOMAG,1) -> 1191 | S30: =R30*Eficiencia -> 1191 | T30: =IF(AND(S30>0,VolumenCompactacion>0),VolumenCompactacion/S30,0) -> 0 | U30: =G30*PrecioDiesel+H30+I30 -> 3 | V30: =T30*U30 -> 0 | W30: =G30*HorasOperacion*PrecioDiesel -> 0 | X30: =HorasOperacion*(H30+I30) -> 9000 | Y30: =IF(AND(B30="SDR",K30="NO"),HorasOperacion/JuntaIntervalo,0) -> 60 | Z30: =Y30*JuntaHorasIntervencion*(JuntaTecnico+JuntaParada)+Y30*JuntaGrasa -> 5550 | AA30: =F30+W30+X30+Z30-J30 -> 14550 | AB30: =U30+IF(Y30>0,(JuntaHorasIntervencion*(JuntaTecnico+JuntaParada)+JuntaGrasa)/JuntaIntervalo,0) -> 4.85 | AC30: =IF(HorasOperacion>0,AA30/HorasOperacion,0) -> 4.85 | AD30: =AA30*TasaMoneda -> 14550 | AE30: =IFERROR(AA30-INDEX($AA$5:$AA$64,MATCH(1,INDEX((B$5:B$64=B30)*(C$5:C$64="BOMAG"),0),0)),0) -> -94522.78
A31: =B31&" | "&C31&" | "&D31 -> SDR | CATERPILLAR | CS10GC | B31: SDR | C31: ='Datos SDR'!$B$28 -> CATERPILLAR | D31: ='Datos SDR'!$C$28 -> CS10GC | E31: ='Datos SDR'!$E$28 -> 10492 | F31: ='Datos SDR'!$Z$28 -> 105298.85 | G31: ='Datos SDR'!$Y$28 -> 14.5 | H31: ='Datos SDR'!$AA$28 -> 1 | I31: ='Datos SDR'!$AB$28 -> 2 | J31: 0 | K31: NO | L31: N/A | M31: 649 | N31: 449 | O31: 399 | P31: 199 | Q31: =INDEX(M31:P31,MATCH(TipoSuelo,{"Roca","Grava","Suelo mixto","Arcilla"},0)) -> 399 | R31: =Q31*IF(AND(C31="BOMAG",L31="SÍ"),MultTecBOMAG,1) -> 399 | S31: =R31*Eficiencia -> 399 | T31: =IF(AND(S31>0,VolumenCompactacion>0),VolumenCompactacion/S31,0) -> 0 | U31: =G31*PrecioDiesel+H31+I31 -> 20.4 | V31: =T31*U31 -> 0 | W31: =G31*HorasOperacion*PrecioDiesel -> 52200 | X31: =HorasOperacion*(H31+I31) -> 9000 | Y31: =IF(AND(B31="SDR",K31="NO"),HorasOperacion/JuntaIntervalo,0) -> 60 | Z31: =Y31*JuntaHorasIntervencion*(JuntaTecnico+JuntaParada)+Y31*JuntaGrasa -> 5550 | AA31: =F31+W31+X31+Z31-J31 -> 172048.85 | AB31: =U31+IF(Y31>0,(JuntaHorasIntervencion*(JuntaTecnico+JuntaParada)+JuntaGrasa)/JuntaIntervalo,0) -> 22.25 | AC31: =IF(HorasOperacion>0,AA31/HorasOperacion,0) -> 57.349617 | AD31: =AA31*TasaMoneda -> 172048.85 | AE31: =IFERROR(AA31-INDEX($AA$5:$AA$64,MATCH(1,INDEX((B$5:B$64=B31)*(C$5:C$64="BOMAG"),0),0)),0) -> 62976.07
A32: =B32&" | "&C32&" | "&D32 -> SDR | CATERPILLAR | CS11GC | B32: SDR | C32: ='Datos SDR'!$B$29 -> CATERPILLAR | D32: ='Datos SDR'!$C$29 -> CS11GC | E32: ='Datos SDR'!$E$29 -> 10900 | F32: ='Datos SDR'!$Z$29 -> 105298.85 | G32: ='Datos SDR'!$Y$29 -> 14.5 | H32: ='Datos SDR'!$AA$29 -> 1 | I32: ='Datos SDR'!$AB$29 -> 2 | J32: 0 | K32: NO | L32: N/A | M32: 717 | N32: 517 | O32: 453 | P32: 227 | Q32: =INDEX(M32:P32,MATCH(TipoSuelo,{"Roca","Grava","Suelo mixto","Arcilla"},0)) -> 453 | R32: =Q32*IF(AND(C32="BOMAG",L32="SÍ"),MultTecBOMAG,1) -> 453 | S32: =R32*Eficiencia -> 453 | T32: =IF(AND(S32>0,VolumenCompactacion>0),VolumenCompactacion/S32,0) -> 0 | U32: =G32*PrecioDiesel+H32+I32 -> 20.4 | V32: =T32*U32 -> 0 | W32: =G32*HorasOperacion*PrecioDiesel -> 52200 | X32: =HorasOperacion*(H32+I32) -> 9000 | Y32: =IF(AND(B32="SDR",K32="NO"),HorasOperacion/JuntaIntervalo,0) -> 60 | Z32: =Y32*JuntaHorasIntervencion*(JuntaTecnico+JuntaParada)+Y32*JuntaGrasa -> 5550 | AA32: =F32+W32+X32+Z32-J32 -> 172048.85 | AB32: =U32+IF(Y32>0,(JuntaHorasIntervencion*(JuntaTecnico+JuntaParada)+JuntaGrasa)/JuntaIntervalo,0) -> 22.25 | AC32: =IF(HorasOperacion>0,AA32/HorasOperacion,0) -> 57.349617 | AD32: =AA32*TasaMoneda -> 172048.85 | AE32: =IFERROR(AA32-INDEX($AA$5:$AA$64,MATCH(1,INDEX((B$5:B$64=B32)*(C$5:C$64="BOMAG"),0),0)),0) -> 62976.07
A33: =B33&" | "&C33&" | "&D33 -> SDR | CATERPILLAR | CS12 | B33: SDR | C33: ='Datos SDR'!$B$30 -> CATERPILLAR | D33: ='Datos SDR'!$C$30 -> CS12 | E33: ='Datos SDR'!$E$30 -> 11743 | F33: ='Datos SDR'!$Z$30 -> 105298.85 | G33: ='Datos SDR'!$Y$30 -> 14.5 | H33: ='Datos SDR'!$AA$30 -> 1 | I33: ='Datos SDR'!$AB$30 -> 2 | J33: 0 | K33: NO | L33: N/A | M33: 857 | N33: 657 | O33: 566 | P33: 283 | Q33: =INDEX(M33:P33,MATCH(TipoSuelo,{"Roca","Grava","Suelo mixto","Arcilla"},0)) -> 566 | R33: =Q33*IF(AND(C33="BOMAG",L33="SÍ"),MultTecBOMAG,1) -> 566 | S33: =R33*Eficiencia -> 566 | T33: =IF(AND(S33>0,VolumenCompactacion>0),VolumenCompactacion/S33,0) -> 0 | U33: =G33*PrecioDiesel+H33+I33 -> 20.4 | V33: =T33*U33 -> 0 | W33: =G33*HorasOperacion*PrecioDiesel -> 52200 | X33: =HorasOperacion*(H33+I33) -> 9000 | Y33: =IF(AND(B33="SDR",K33="NO"),HorasOperacion/JuntaIntervalo,0) -> 60 | Z33: =Y33*JuntaHorasIntervencion*(JuntaTecnico+JuntaParada)+Y33*JuntaGrasa -> 5550 | AA33: =F33+W33+X33+Z33-J33 -> 172048.85 | AB33: =U33+IF(Y33>0,(JuntaHorasIntervencion*(JuntaTecnico+JuntaParada)+JuntaGrasa)/JuntaIntervalo,0) -> 22.25 | AC33: =IF(HorasOperacion>0,AA33/HorasOperacion,0) -> 57.349617 | AD33: =AA33*TasaMoneda -> 172048.85 | AE33: =IFERROR(AA33-INDEX($AA$5:$AA$64,MATCH(1,INDEX((B$5:B$64=B33)*(C$5:C$64="BOMAG"),0),0)),0) -> 62976.07
A34: =B34&" | "&C34&" | "&D34 -> SDR | CATERPILLAR | CS13GC | B34: SDR | C34: ='Datos SDR'!$B$31 -> CATERPILLAR | D34: ='Datos SDR'!$C$31 -> CS13GC | E34: ='Datos SDR'!$E$31 -> 12700 | F34: ='Datos SDR'!$Z$31 -> 0 | G34: ='Datos SDR'!$Y$31 -> 0 | H34: ='Datos SDR'!$AA$31 -> 1 | I34: ='Datos SDR'!$AB$31 -> 2 | J34: 0 | K34: NO | L34: N/A | M34: 620 | N34: 455 | O34: 390 | P34: 195 | Q34: =INDEX(M34:P34,MATCH(TipoSuelo,{"Roca","Grava","Suelo mixto","Arcilla"},0)) -> 390 | R34: =Q34*IF(AND(C34="BOMAG",L34="SÍ"),MultTecBOMAG,1) -> 390 | S34: =R34*Eficiencia -> 390 | T34: =IF(AND(S34>0,VolumenCompactacion>0),VolumenCompactacion/S34,0) -> 0 | U34: =G34*PrecioDiesel+H34+I34 -> 3 | V34: =T34*U34 -> 0 | W34: =G34*HorasOperacion*PrecioDiesel -> 0 | X34: =HorasOperacion*(H34+I34) -> 9000 | Y34: =IF(AND(B34="SDR",K34="NO"),HorasOperacion/JuntaIntervalo,0) -> 60 | Z34: =Y34*JuntaHorasIntervencion*(JuntaTecnico+JuntaParada)+Y34*JuntaGrasa -> 5550 | AA34: =F34+W34+X34+Z34-J34 -> 14550 | AB34: =U34+IF(Y34>0,(JuntaHorasIntervencion*(JuntaTecnico+JuntaParada)+JuntaGrasa)/JuntaIntervalo,0) -> 4.85 | AC34: =IF(HorasOperacion>0,AA34/HorasOperacion,0) -> 4.85 | AD34: =AA34*TasaMoneda -> 14550 | AE34: =IFERROR(AA34-INDEX($AA$5:$AA$64,MATCH(1,INDEX((B$5:B$64=B34)*(C$5:C$64="BOMAG"),0),0)),0) -> -94522.78
A35: =B35&" | "&C35&" | "&D35 -> SDR | XCMG | XS113E | B35: SDR | C35: ='Datos SDR'!$B$32 -> XCMG | D35: ='Datos SDR'!$C$32 -> XS113E | E35: ='Datos SDR'!$E$32 -> 10400 | F35: ='Datos SDR'!$Z$32 -> 54786 | G35: ='Datos SDR'!$Y$32 -> 13.6 | H35: ='Datos SDR'!$AA$32 -> 1 | I35: ='Datos SDR'!$AB$32 -> 2 | J35: 0 | K35: NO | L35: N/A | M35: 633 | N35: 433 | O35: 387 | P35: 193 | Q35: =INDEX(M35:P35,MATCH(TipoSuelo,{"Roca","Grava","Suelo mixto","Arcilla"},0)) -> 387 | R35: =Q35*IF(AND(C35="BOMAG",L35="SÍ"),MultTecBOMAG,1) -> 387 | S35: =R35*Eficiencia -> 387 | T35: =IF(AND(S35>0,VolumenCompactacion>0),VolumenCompactacion/S35,0) -> 0 | U35: =G35*PrecioDiesel+H35+I35 -> 19.32 | V35: =T35*U35 -> 0 | W35: =G35*HorasOperacion*PrecioDiesel -> 48960 | X35: =HorasOperacion*(H35+I35) -> 9000 | Y35: =IF(AND(B35="SDR",K35="NO"),HorasOperacion/JuntaIntervalo,0) -> 60 | Z35: =Y35*JuntaHorasIntervencion*(JuntaTecnico+JuntaParada)+Y35*JuntaGrasa -> 5550 | AA35: =F35+W35+X35+Z35-J35 -> 118296 | AB35: =U35+IF(Y35>0,(JuntaHorasIntervencion*(JuntaTecnico+JuntaParada)+JuntaGrasa)/JuntaIntervalo,0) -> 21.17 | AC35: =IF(HorasOperacion>0,AA35/HorasOperacion,0) -> 39.432 | AD35: =AA35*TasaMoneda -> 118296 | AE35: =IFERROR(AA35-INDEX($AA$5:$AA$64,MATCH(1,INDEX((B$5:B$64=B35)*(C$5:C$64="BOMAG"),0),0)),0) -> 9223.22
A36: =B36&" | "&C36&" | "&D36 -> SDR | XCMG | XS123 | B36: SDR | C36: ='Datos SDR'!$B$33 -> XCMG | D36: ='Datos SDR'!$C$33 -> XS123 | E36: ='Datos SDR'!$E$33 -> 12000 | F36: ='Datos SDR'!$Z$33 -> 54786 | G36: ='Datos SDR'!$Y$33 -> 13.6 | H36: ='Datos SDR'!$AA$33 -> 1 | I36: ='Datos SDR'!$AB$33 -> 2 | J36: 0 | K36: NO | L36: N/A | M36: 900 | N36: 700 | O36: 600 | P36: 300 | Q36: =INDEX(M36:P36,MATCH(TipoSuelo,{"Roca","Grava","Suelo mixto","Arcilla"},0)) -> 600 | R36: =Q36*IF(AND(C36="BOMAG",L36="SÍ"),MultTecBOMAG,1) -> 600 | S36: =R36*Eficiencia -> 600 | T36: =IF(AND(S36>0,VolumenCompactacion>0),VolumenCompactacion/S36,0) -> 0 | U36: =G36*PrecioDiesel+H36+I36 -> 19.32 | V36: =T36*U36 -> 0 | W36: =G36*HorasOperacion*PrecioDiesel -> 48960 | X36: =HorasOperacion*(H36+I36) -> 9000 | Y36: =IF(AND(B36="SDR",K36="NO"),HorasOperacion/JuntaIntervalo,0) -> 60 | Z36: =Y36*JuntaHorasIntervencion*(JuntaTecnico+JuntaParada)+Y36*JuntaGrasa -> 5550 | AA36: =F36+W36+X36+Z36-J36 -> 118296 | AB36: =U36+IF(Y36>0,(JuntaHorasIntervencion*(JuntaTecnico+JuntaParada)+JuntaGrasa)/JuntaIntervalo,0) -> 21.17 | AC36: =IF(HorasOperacion>0,AA36/HorasOperacion,0) -> 39.432 | AD36: =AA36*TasaMoneda -> 118296 | AE36: =IFERROR(AA36-INDEX($AA$5:$AA$64,MATCH(1,INDEX((B$5:B$64=B36)*(C$5:C$64="BOMAG"),0),0)),0) -> 9223.22
A37: =B37&" | "&C37&" | "&D37 -> SDR | XCMG | XS143J | B37: SDR | C37: ='Datos SDR'!$B$34 -> XCMG | D37: ='Datos SDR'!$C$34 -> XS143J | E37: ='Datos SDR'!$E$34 -> 14000 | F37: ='Datos SDR'!$Z$34 -> 0 | G37: ='Datos SDR'!$Y$34 -> 0 | H37: ='Datos SDR'!$AA$34 -> 1 | I37: ='Datos SDR'!$AB$34 -> 2 | J37: 0 | K37: NO | L37: N/A | M37: 800 | N37: 567 | O37: 467 | P37: 233 | Q37: =INDEX(M37:P37,MATCH(TipoSuelo,{"Roca","Grava","Suelo mixto","Arcilla"},0)) -> 467 | R37: =Q37*IF(AND(C37="BOMAG",L37="SÍ"),MultTecBOMAG,1) -> 467 | S37: =R37*Eficiencia -> 467 | T37: =IF(AND(S37>0,VolumenCompactacion>0),VolumenCompactacion/S37,0) -> 0 | U37: =G37*PrecioDiesel+H37+I37 -> 3 | V37: =T37*U37 -> 0 | W37: =G37*HorasOperacion*PrecioDiesel -> 0 | X37: =HorasOperacion*(H37+I37) -> 9000 | Y37: =IF(AND(B37="SDR",K37="NO"),HorasOperacion/JuntaIntervalo,0) -> 60 | Z37: =Y37*JuntaHorasIntervencion*(JuntaTecnico+JuntaParada)+Y37*JuntaGrasa -> 5550 | AA37: =F37+W37+X37+Z37-J37 -> 14550 | AB37: =U37+IF(Y37>0,(JuntaHorasIntervencion*(JuntaTecnico+JuntaParada)+JuntaGrasa)/JuntaIntervalo,0) -> 4.85 | AC37: =IF(HorasOperacion>0,AA37/HorasOperacion,0) -> 4.85 | AD37: =AA37*TasaMoneda -> 14550 | AE37: =IFERROR(AA37-INDEX($AA$5:$AA$64,MATCH(1,INDEX((B$5:B$64=B37)*(C$5:C$64="BOMAG"),0),0)),0) -> -94522.78
A38: =B38&" | "&C38&" | "&D38 -> SDR | XCMG | XS162J | B38: SDR | C38: ='Datos SDR'!$B$35 -> XCMG | D38: ='Datos SDR'!$C$35 -> XS162J | E38: ='Datos SDR'!$E$35 -> 16000 | F38: ='Datos SDR'!$Z$35 -> 0 | G38: ='Datos SDR'!$Y$35 -> 0 | H38: ='Datos SDR'!$AA$35 -> 1 | I38: ='Datos SDR'!$AB$35 -> 2 | J38: 0 | K38: NO | L38: N/A | M38: 1400 | N38: 1000 | O38: 800 | P38: 400 | Q38: =INDEX(M38:P38,MATCH(TipoSuelo,{"Roca","Grava","Suelo mixto","Arcilla"},0)) -> 800 | R38: =Q38*IF(AND(C38="BOMAG",L38="SÍ"),MultTecBOMAG,1) -> 800 | S38: =R38*Eficiencia -> 800 | T38: =IF(AND(S38>0,VolumenCompactacion>0),VolumenCompactacion/S38,0) -> 0 | U38: =G38*PrecioDiesel+H38+I38 -> 3 | V38: =T38*U38 -> 0 | W38: =G38*HorasOperacion*PrecioDiesel -> 0 | X38: =HorasOperacion*(H38+I38) -> 9000 | Y38: =IF(AND(B38="SDR",K38="NO"),HorasOperacion/JuntaIntervalo,0) -> 60 | Z38: =Y38*JuntaHorasIntervencion*(JuntaTecnico+JuntaParada)+Y38*JuntaGrasa -> 5550 | AA38: =F38+W38+X38+Z38-J38 -> 14550 | AB38: =U38+IF(Y38>0,(JuntaHorasIntervencion*(JuntaTecnico+JuntaParada)+JuntaGrasa)/JuntaIntervalo,0) -> 4.85 | AC38: =IF(HorasOperacion>0,AA38/HorasOperacion,0) -> 4.85 | AD38: =AA38*TasaMoneda -> 14550 | AE38: =IFERROR(AA38-INDEX($AA$5:$AA$64,MATCH(1,INDEX((B$5:B$64=B38)*(C$5:C$64="BOMAG"),0),0)),0) -> -94522.78
A39: =B39&" | "&C39&" | "&D39 -> SDR | XCMG | XS182 | B39: SDR | C39: ='Datos SDR'!$B$36 -> XCMG | D39: ='Datos SDR'!$C$36 -> XS182 | E39: ='Datos SDR'!$E$36 -> 18000 | F39: ='Datos SDR'!$Z$36 -> 0 | G39: ='Datos SDR'!$Y$36 -> 0 | H39: ='Datos SDR'!$AA$36 -> 1 | I39: ='Datos SDR'!$AB$36 -> 2 | J39: 0 | K39: NO | L39: N/A | M39: 1067 | N39: 667 | O39: 600 | P39: 333 | Q39: =INDEX(M39:P39,MATCH(TipoSuelo,{"Roca","Grava","Suelo mixto","Arcilla"},0)) -> 600 | R39: =Q39*IF(AND(C39="BOMAG",L39="SÍ"),MultTecBOMAG,1) -> 600 | S39: =R39*Eficiencia -> 600 | T39: =IF(AND(S39>0,VolumenCompactacion>0),VolumenCompactacion/S39,0) -> 0 | U39: =G39*PrecioDiesel+H39+I39 -> 3 | V39: =T39*U39 -> 0 | W39: =G39*HorasOperacion*PrecioDiesel -> 0 | X39: =HorasOperacion*(H39+I39) -> 9000 | Y39: =IF(AND(B39="SDR",K39="NO"),HorasOperacion/JuntaIntervalo,0) -> 60 | Z39: =Y39*JuntaHorasIntervencion*(JuntaTecnico+JuntaParada)+Y39*JuntaGrasa -> 5550 | AA39: =F39+W39+X39+Z39-J39 -> 14550 | AB39: =U39+IF(Y39>0,(JuntaHorasIntervencion*(JuntaTecnico+JuntaParada)+JuntaGrasa)/JuntaIntervalo,0) -> 4.85 | AC39: =IF(HorasOperacion>0,AA39/HorasOperacion,0) -> 4.85 | AD39: =AA39*TasaMoneda -> 14550 | AE39: =IFERROR(AA39-INDEX($AA$5:$AA$64,MATCH(1,INDEX((B$5:B$64=B39)*(C$5:C$64="BOMAG"),0),0)),0) -> -94522.78
A40: =B40&" | "&C40&" | "&D40 -> SDR | XCMG | XS203J | B40: SDR | C40: ='Datos SDR'!$B$37 -> XCMG | D40: ='Datos SDR'!$C$37 -> XS203J | E40: ='Datos SDR'!$E$37 -> 20000 | F40: ='Datos SDR'!$Z$37 -> 0 | G40: ='Datos SDR'!$Y$37 -> 0 | H40: ='Datos SDR'!$AA$37 -> 1 | I40: ='Datos SDR'!$AB$37 -> 2 | J40: 0 | K40: NO | L40: N/A | M40: 1117 | N40: 683 | O40: 617 | P40: 333 | Q40: =INDEX(M40:P40,MATCH(TipoSuelo,{"Roca","Grava","Suelo mixto","Arcilla"},0)) -> 617 | R40: =Q40*IF(AND(C40="BOMAG",L40="SÍ"),MultTecBOMAG,1) -> 617 | S40: =R40*Eficiencia -> 617 | T40: =IF(AND(S40>0,VolumenCompactacion>0),VolumenCompactacion/S40,0) -> 0 | U40: =G40*PrecioDiesel+H40+I40 -> 3 | V40: =T40*U40 -> 0 | W40: =G40*HorasOperacion*PrecioDiesel -> 0 | X40: =HorasOperacion*(H40+I40) -> 9000 | Y40: =IF(AND(B40="SDR",K40="NO"),HorasOperacion/JuntaIntervalo,0) -> 60 | Z40: =Y40*JuntaHorasIntervencion*(JuntaTecnico+JuntaParada)+Y40*JuntaGrasa -> 5550 | AA40: =F40+W40+X40+Z40-J40 -> 14550 | AB40: =U40+IF(Y40>0,(JuntaHorasIntervencion*(JuntaTecnico+JuntaParada)+JuntaGrasa)/JuntaIntervalo,0) -> 4.85 | AC40: =IF(HorasOperacion>0,AA40/HorasOperacion,0) -> 4.85 | AD40: =AA40*TasaMoneda -> 14550 | AE40: =IFERROR(AA40-INDEX($AA$5:$AA$64,MATCH(1,INDEX((B$5:B$64=B40)*(C$5:C$64="BOMAG"),0),0)),0) -> -94522.78
A41: =B41&" | "&C41&" | "&D41 -> SDR | SANY | SSR120C-8 | B41: SDR | C41: ='Datos SDR'!$B$38 -> SANY | D41: ='Datos SDR'!$C$38 -> SSR120C-8 | E41: ='Datos SDR'!$E$38 -> 11580 | F41: ='Datos SDR'!$Z$38 -> 0 | G41: ='Datos SDR'!$Y$38 -> 0 | H41: ='Datos SDR'!$AA$38 -> 1 | I41: ='Datos SDR'!$AB$38 -> 2 | J41: 0 | K41: NO | L41: N/A | M41: 830 | N41: 630 | O41: 544 | P41: 272 | Q41: =INDEX(M41:P41,MATCH(TipoSuelo,{"Roca","Grava","Suelo mixto","Arcilla"},0)) -> 544 | R41: =Q41*IF(AND(C41="BOMAG",L41="SÍ"),MultTecBOMAG,1) -> 544 | S41: =R41*Eficiencia -> 544 | T41: =IF(AND(S41>0,VolumenCompactacion>0),VolumenCompactacion/S41,0) -> 0 | U41: =G41*PrecioDiesel+H41+I41 -> 3 | V41: =T41*U41 -> 0 | W41: =G41*HorasOperacion*PrecioDiesel -> 0 | X41: =HorasOperacion*(H41+I41) -> 9000 | Y41: =IF(AND(B41="SDR",K41="NO"),HorasOperacion/JuntaIntervalo,0) -> 60 | Z41: =Y41*JuntaHorasIntervencion*(JuntaTecnico+JuntaParada)+Y41*JuntaGrasa -> 5550 | AA41: =F41+W41+X41+Z41-J41 -> 14550 | AB41: =U41+IF(Y41>0,(JuntaHorasIntervencion*(JuntaTecnico+JuntaParada)+JuntaGrasa)/JuntaIntervalo,0) -> 4.85 | AC41: =IF(HorasOperacion>0,AA41/HorasOperacion,0) -> 4.85 | AD41: =AA41*TasaMoneda -> 14550 | AE41: =IFERROR(AA41-INDEX($AA$5:$AA$64,MATCH(1,INDEX((B$5:B$64=B41)*(C$5:C$64="BOMAG"),0),0)),0) -> -94522.78
A42: =B42&" | "&C42&" | "&D42 -> SDR | SANY | SSR120C-10 | B42: SDR | C42: ='Datos SDR'!$B$39 -> SANY | D42: ='Datos SDR'!$C$39 -> SSR120C-10 | E42: ='Datos SDR'!$E$39 -> 12000 | F42: ='Datos SDR'!$Z$39 -> 0 | G42: ='Datos SDR'!$Y$39 -> 0 | H42: ='Datos SDR'!$AA$39 -> 1 | I42: ='Datos SDR'!$AB$39 -> 2 | J42: 0 | K42: NO | L42: N/A | M42: 900 | N42: 700 | O42: 600 | P42: 300 | Q42: =INDEX(M42:P42,MATCH(TipoSuelo,{"Roca","Grava","Suelo mixto","Arcilla"},0)) -> 600 | R42: =Q42*IF(AND(C42="BOMAG",L42="SÍ"),MultTecBOMAG,1) -> 600 | S42: =R42*Eficiencia -> 600 | T42: =IF(AND(S42>0,VolumenCompactacion>0),VolumenCompactacion/S42,0) -> 0 | U42: =G42*PrecioDiesel+H42+I42 -> 3 | V42: =T42*U42 -> 0 | W42: =G42*HorasOperacion*PrecioDiesel -> 0 | X42: =HorasOperacion*(H42+I42) -> 9000 | Y42: =IF(AND(B42="SDR",K42="NO"),HorasOperacion/JuntaIntervalo,0) -> 60 | Z42: =Y42*JuntaHorasIntervencion*(JuntaTecnico+JuntaParada)+Y42*JuntaGrasa -> 5550 | AA42: =F42+W42+X42+Z42-J42 -> 14550 | AB42: =U42+IF(Y42>0,(JuntaHorasIntervencion*(JuntaTecnico+JuntaParada)+JuntaGrasa)/JuntaIntervalo,0) -> 4.85 | AC42: =IF(HorasOperacion>0,AA42/HorasOperacion,0) -> 4.85 | AD42: =AA42*TasaMoneda -> 14550 | AE42: =IFERROR(AA42-INDEX($AA$5:$AA$64,MATCH(1,INDEX((B$5:B$64=B42)*(C$5:C$64="BOMAG"),0),0)),0) -> -94522.78
A43: =B43&" | "&C43&" | "&D43 -> SDR | SANY | SSR120C-10S | B43: SDR | C43: ='Datos SDR'!$B$40 -> SANY | D43: ='Datos SDR'!$C$40 -> SSR120C-10S | E43: ='Datos SDR'!$E$40 -> 12400 | F43: ='Datos SDR'!$Z$40 -> 56392 | G43: ='Datos SDR'!$Y$40 -> 15.3 | H43: ='Datos SDR'!$AA$40 -> 1 | I43: ='Datos SDR'!$AB$40 -> 2 | J43: 0 | K43: NO | L43: N/A | M43: 740 | N43: 560 | O43: 480 | P43: 240 | Q43: =INDEX(M43:P43,MATCH(TipoSuelo,{"Roca","Grava","Suelo mixto","Arcilla"},0)) -> 480 | R43: =Q43*IF(AND(C43="BOMAG",L43="SÍ"),MultTecBOMAG,1) -> 480 | S43: =R43*Eficiencia -> 480 | T43: =IF(AND(S43>0,VolumenCompactacion>0),VolumenCompactacion/S43,0) -> 0 | U43: =G43*PrecioDiesel+H43+I43 -> 21.36 | V43: =T43*U43 -> 0 | W43: =G43*HorasOperacion*PrecioDiesel -> 55080 | X43: =HorasOperacion*(H43+I43) -> 9000 | Y43: =IF(AND(B43="SDR",K43="NO"),HorasOperacion/JuntaIntervalo,0) -> 60 | Z43: =Y43*JuntaHorasIntervencion*(JuntaTecnico+JuntaParada)+Y43*JuntaGrasa -> 5550 | AA43: =F43+W43+X43+Z43-J43 -> 126022 | AB43: =U43+IF(Y43>0,(JuntaHorasIntervencion*(JuntaTecnico+JuntaParada)+JuntaGrasa)/JuntaIntervalo,0) -> 23.21 | AC43: =IF(HorasOperacion>0,AA43/HorasOperacion,0) -> 42.007333 | AD43: =AA43*TasaMoneda -> 126022 | AE43: =IFERROR(AA43-INDEX($AA$5:$AA$64,MATCH(1,INDEX((B$5:B$64=B43)*(C$5:C$64="BOMAG"),0),0)),0) -> 16949.22
A44: =B44&" | "&C44&" | "&D44 -> SDR | SHANTUI | SR16 | B44: SDR | C44: ='Datos SDR'!$B$41 -> SHANTUI | D44: ='Datos SDR'!$C$41 -> SR16 | E44: ='Datos SDR'!$E$41 -> 16000 | F44: ='Datos SDR'!$Z$41 -> 0 | G44: ='Datos SDR'!$Y$41 -> 0 | H44: ='Datos SDR'!$AA$41 -> 1 | I44: ='Datos SDR'!$AB$41 -> 2 | J44: 0 | K44: NO | L44: N/A | M44: 1400 | N44: 1000 | O44: 800 | P44: 400 | Q44: =INDEX(M44:P44,MATCH(TipoSuelo,{"Roca","Grava","Suelo mixto","Arcilla"},0)) -> 800 | R44: =Q44*IF(AND(C44="BOMAG",L44="SÍ"),MultTecBOMAG,1) -> 800 | S44: =R44*Eficiencia -> 800 | T44: =IF(AND(S44>0,VolumenCompactacion>0),VolumenCompactacion/S44,0) -> 0 | U44: =G44*PrecioDiesel+H44+I44 -> 3 | V44: =T44*U44 -> 0 | W44: =G44*HorasOperacion*PrecioDiesel -> 0 | X44: =HorasOperacion*(H44+I44) -> 9000 | Y44: =IF(AND(B44="SDR",K44="NO"),HorasOperacion/JuntaIntervalo,0) -> 60 | Z44: =Y44*JuntaHorasIntervencion*(JuntaTecnico+JuntaParada)+Y44*JuntaGrasa -> 5550 | AA44: =F44+W44+X44+Z44-J44 -> 14550 | AB44: =U44+IF(Y44>0,(JuntaHorasIntervencion*(JuntaTecnico+JuntaParada)+JuntaGrasa)/JuntaIntervalo,0) -> 4.85 | AC44: =IF(HorasOperacion>0,AA44/HorasOperacion,0) -> 4.85 | AD44: =AA44*TasaMoneda -> 14550 | AE44: =IFERROR(AA44-INDEX($AA$5:$AA$64,MATCH(1,INDEX((B$5:B$64=B44)*(C$5:C$64="BOMAG"),0),0)),0) -> -94522.78
A45: =B45&" | "&C45&" | "&D45 -> SDR | SHANTUI | SR22 | B45: SDR | C45: ='Datos SDR'!$B$42 -> SHANTUI | D45: ='Datos SDR'!$C$42 -> SR22 | E45: ='Datos SDR'!$E$42 -> 22000 | F45: ='Datos SDR'!$Z$42 -> 0 | G45: ='Datos SDR'!$Y$42 -> 0 | H45: ='Datos SDR'!$AA$42 -> 1 | I45: ='Datos SDR'!$AB$42 -> 2 | J45: 0 | K45: NO | L45: N/A | M45: 1550 | N45: 1050 | O45: 850 | P45: 400 | Q45: =INDEX(M45:P45,MATCH(TipoSuelo,{"Roca","Grava","Suelo mixto","Arcilla"},0)) -> 850 | R45: =Q45*IF(AND(C45="BOMAG",L45="SÍ"),MultTecBOMAG,1) -> 850 | S45: =R45*Eficiencia -> 850 | T45: =IF(AND(S45>0,VolumenCompactacion>0),VolumenCompactacion/S45,0) -> 0 | U45: =G45*PrecioDiesel+H45+I45 -> 3 | V45: =T45*U45 -> 0 | W45: =G45*HorasOperacion*PrecioDiesel -> 0 | X45: =HorasOperacion*(H45+I45) -> 9000 | Y45: =IF(AND(B45="SDR",K45="NO"),HorasOperacion/JuntaIntervalo,0) -> 60 | Z45: =Y45*JuntaHorasIntervencion*(JuntaTecnico+JuntaParada)+Y45*JuntaGrasa -> 5550 | AA45: =F45+W45+X45+Z45-J45 -> 14550 | AB45: =U45+IF(Y45>0,(JuntaHorasIntervencion*(JuntaTecnico+JuntaParada)+JuntaGrasa)/JuntaIntervalo,0) -> 4.85 | AC45: =IF(HorasOperacion>0,AA45/HorasOperacion,0) -> 4.85 | AD45: =AA45*TasaMoneda -> 14550 | AE45: =IFERROR(AA45-INDEX($AA$5:$AA$64,MATCH(1,INDEX((B$5:B$64=B45)*(C$5:C$64="BOMAG"),0),0)),0) -> -94522.78
A46: =B46&" | "&C46&" | "&D46 -> SDR | JCB | 116D | B46: SDR | C46: ='Datos SDR'!$B$43 -> JCB | D46: ='Datos SDR'!$C$43 -> 116D | E46: ='Datos SDR'!$E$43 -> 11560 | F46: ='Datos SDR'!$Z$43 -> 84076 | G46: ='Datos SDR'!$Y$43 -> 13 | H46: ='Datos SDR'!$AA$43 -> 1 | I46: ='Datos SDR'!$AB$43 -> 2 | J46: 0 | K46: NO | L46: N/A | M46: 827 | N46: 627 | O46: 541 | P46: 271 | Q46: =INDEX(M46:P46,MATCH(TipoSuelo,{"Roca","Grava","Suelo mixto","Arcilla"},0)) -> 541 | R46: =Q46*IF(AND(C46="BOMAG",L46="SÍ"),MultTecBOMAG,1) -> 541 | S46: =R46*Eficiencia -> 541 | T46: =IF(AND(S46>0,VolumenCompactacion>0),VolumenCompactacion/S46,0) -> 0 | U46: =G46*PrecioDiesel+H46+I46 -> 18.6 | V46: =T46*U46 -> 0 | W46: =G46*HorasOperacion*PrecioDiesel -> 46800 | X46: =HorasOperacion*(H46+I46) -> 9000 | Y46: =IF(AND(B46="SDR",K46="NO"),HorasOperacion/JuntaIntervalo,0) -> 60 | Z46: =Y46*JuntaHorasIntervencion*(JuntaTecnico+JuntaParada)+Y46*JuntaGrasa -> 5550 | AA46: =F46+W46+X46+Z46-J46 -> 145426 | AB46: =U46+IF(Y46>0,(JuntaHorasIntervencion*(JuntaTecnico+JuntaParada)+JuntaGrasa)/JuntaIntervalo,0) -> 20.45 | AC46: =IF(HorasOperacion>0,AA46/HorasOperacion,0) -> 48.475333 | AD46: =AA46*TasaMoneda -> 145426 | AE46: =IFERROR(AA46-INDEX($AA$5:$AA$64,MATCH(1,INDEX((B$5:B$64=B46)*(C$5:C$64="BOMAG"),0),0)),0) -> 36353.22
A47: =B47&" | "&C47&" | "&D47 -> SDR | JCB | VM115 | B47: SDR | C47: ='Datos SDR'!$B$44 -> JCB | D47: ='Datos SDR'!$C$44 -> VM115 | E47: ='Datos SDR'!$E$44 -> 11500 | F47: ='Datos SDR'!$Z$44 -> 84076 | G47: ='Datos SDR'!$Y$44 -> 13 | H47: ='Datos SDR'!$AA$44 -> 1 | I47: ='Datos SDR'!$AB$44 -> 2 | J47: 0 | K47: NO | L47: N/A | M47: 817 | N47: 617 | O47: 533 | P47: 267 | Q47: =INDEX(M47:P47,MATCH(TipoSuelo,{"Roca","Grava","Suelo mixto","Arcilla"},0)) -> 533 | R47: =Q47*IF(AND(C47="BOMAG",L47="SÍ"),MultTecBOMAG,1) -> 533 | S47: =R47*Eficiencia -> 533 | T47: =IF(AND(S47>0,VolumenCompactacion>0),VolumenCompactacion/S47,0) -> 0 | U47: =G47*PrecioDiesel+H47+I47 -> 18.6 | V47: =T47*U47 -> 0 | W47: =G47*HorasOperacion*PrecioDiesel -> 46800 | X47: =HorasOperacion*(H47+I47) -> 9000 | Y47: =IF(AND(B47="SDR",K47="NO"),HorasOperacion/JuntaIntervalo,0) -> 60 | Z47: =Y47*JuntaHorasIntervencion*(JuntaTecnico+JuntaParada)+Y47*JuntaGrasa -> 5550 | AA47: =F47+W47+X47+Z47-J47 -> 145426 | AB47: =U47+IF(Y47>0,(JuntaHorasIntervencion*(JuntaTecnico+JuntaParada)+JuntaGrasa)/JuntaIntervalo,0) -> 20.45 | AC47: =IF(HorasOperacion>0,AA47/HorasOperacion,0) -> 48.475333 | AD47: =AA47*TasaMoneda -> 145426 | AE47: =IFERROR(AA47-INDEX($AA$5:$AA$64,MATCH(1,INDEX((B$5:B$64=B47)*(C$5:C$64="BOMAG"),0),0)),0) -> 36353.22
A48: =B48&" | "&C48&" | "&D48 -> SDR | JCB | VM137 | B48: SDR | C48: ='Datos SDR'!$B$45 -> JCB | D48: ='Datos SDR'!$C$45 -> VM137 | E48: ='Datos SDR'!$E$45 -> 13700 | F48: ='Datos SDR'!$Z$45 -> 0 | G48: ='Datos SDR'!$Y$45 -> 0 | H48: ='Datos SDR'!$AA$45 -> 1 | I48: ='Datos SDR'!$AB$45 -> 2 | J48: 0 | K48: NO | L48: N/A | M48: 710 | N48: 502 | O48: 417 | P48: 208 | Q48: =INDEX(M48:P48,MATCH(TipoSuelo,{"Roca","Grava","Suelo mixto","Arcilla"},0)) -> 417 | R48: =Q48*IF(AND(C48="BOMAG",L48="SÍ"),MultTecBOMAG,1) -> 417 | S48: =R48*Eficiencia -> 417 | T48: =IF(AND(S48>0,VolumenCompactacion>0),VolumenCompactacion/S48,0) -> 0 | U48: =G48*PrecioDiesel+H48+I48 -> 3 | V48: =T48*U48 -> 0 | W48: =G48*HorasOperacion*PrecioDiesel -> 0 | X48: =HorasOperacion*(H48+I48) -> 9000 | Y48: =IF(AND(B48="SDR",K48="NO"),HorasOperacion/JuntaIntervalo,0) -> 60 | Z48: =Y48*JuntaHorasIntervencion*(JuntaTecnico+JuntaParada)+Y48*JuntaGrasa -> 5550 | AA48: =F48+W48+X48+Z48-J48 -> 14550 | AB48: =U48+IF(Y48>0,(JuntaHorasIntervencion*(JuntaTecnico+JuntaParada)+JuntaGrasa)/JuntaIntervalo,0) -> 4.85 | AC48: =IF(HorasOperacion>0,AA48/HorasOperacion,0) -> 4.85 | AD48: =AA48*TasaMoneda -> 14550 | AE48: =IFERROR(AA48-INDEX($AA$5:$AA$64,MATCH(1,INDEX((B$5:B$64=B48)*(C$5:C$64="BOMAG"),0),0)),0) -> -94522.78
A49: =B49&" | "&C49&" | "&D49 -> SDR | NEW HOLLAND | V110 | B49: SDR | C49: ='Datos SDR'!$B$46 -> NEW HOLLAND | D49: ='Datos SDR'!$C$46 -> V110 | E49: ='Datos SDR'!$E$46 -> 11380 | F49: ='Datos SDR'!$Z$46 -> 71600 | G49: ='Datos SDR'!$Y$46 -> 10.5 | H49: ='Datos SDR'!$AA$46 -> 1 | I49: ='Datos SDR'!$AB$46 -> 2 | J49: 0 | K49: NO | L49: N/A | M49: 797 | N49: 597 | O49: 517 | P49: 259 | Q49: =INDEX(M49:P49,MATCH(TipoSuelo,{"Roca","Grava","Suelo mixto","Arcilla"},0)) -> 517 | R49: =Q49*IF(AND(C49="BOMAG",L49="SÍ"),MultTecBOMAG,1) -> 517 | S49: =R49*Eficiencia -> 517 | T49: =IF(AND(S49>0,VolumenCompactacion>0),VolumenCompactacion/S49,0) -> 0 | U49: =G49*PrecioDiesel+H49+I49 -> 15.6 | V49: =T49*U49 -> 0 | W49: =G49*HorasOperacion*PrecioDiesel -> 37800 | X49: =HorasOperacion*(H49+I49) -> 9000 | Y49: =IF(AND(B49="SDR",K49="NO"),HorasOperacion/JuntaIntervalo,0) -> 60 | Z49: =Y49*JuntaHorasIntervencion*(JuntaTecnico+JuntaParada)+Y49*JuntaGrasa -> 5550 | AA49: =F49+W49+X49+Z49-J49 -> 123950 | AB49: =U49+IF(Y49>0,(JuntaHorasIntervencion*(JuntaTecnico+JuntaParada)+JuntaGrasa)/JuntaIntervalo,0) -> 17.45 | AC49: =IF(HorasOperacion>0,AA49/HorasOperacion,0) -> 41.316667 | AD49: =AA49*TasaMoneda -> 123950 | AE49: =IFERROR(AA49-INDEX($AA$5:$AA$64,MATCH(1,INDEX((B$5:B$64=B49)*(C$5:C$64="BOMAG"),0),0)),0) -> 14877.22
A50: =B50&" | "&C50&" | "&D50 -> SDR | AMMANN | ASC110 | B50: SDR | C50: ='Datos SDR'!$B$47 -> AMMANN | D50: ='Datos SDR'!$C$47 -> ASC110 | E50: ='Datos SDR'!$E$47 -> 11490 | F50: ='Datos SDR'!$Z$47 -> 89930 | G50: ='Datos SDR'!$Y$47 -> 16.3 | H50: ='Datos SDR'!$AA$47 -> 1 | I50: ='Datos SDR'!$AB$47 -> 2 | J50: 0 | K50: NO | L50: N/A | M50: 815 | N50: 615 | O50: 532 | P50: 266 | Q50: =INDEX(M50:P50,MATCH(TipoSuelo,{"Roca","Grava","Suelo mixto","Arcilla"},0)) -> 532 | R50: =Q50*IF(AND(C50="BOMAG",L50="SÍ"),MultTecBOMAG,1) -> 532 | S50: =R50*Eficiencia -> 532 | T50: =IF(AND(S50>0,VolumenCompactacion>0),VolumenCompactacion/S50,0) -> 0 | U50: =G50*PrecioDiesel+H50+I50 -> 22.56 | V50: =T50*U50 -> 0 | W50: =G50*HorasOperacion*PrecioDiesel -> 58680 | X50: =HorasOperacion*(H50+I50) -> 9000 | Y50: =IF(AND(B50="SDR",K50="NO"),HorasOperacion/JuntaIntervalo,0) -> 60 | Z50: =Y50*JuntaHorasIntervencion*(JuntaTecnico+JuntaParada)+Y50*JuntaGrasa -> 5550 | AA50: =F50+W50+X50+Z50-J50 -> 163160 | AB50: =U50+IF(Y50>0,(JuntaHorasIntervencion*(JuntaTecnico+JuntaParada)+JuntaGrasa)/JuntaIntervalo,0) -> 24.41 | AC50: =IF(HorasOperacion>0,AA50/HorasOperacion,0) -> 54.386667 | AD50: =AA50*TasaMoneda -> 163160 | AE50: =IFERROR(AA50-INDEX($AA$5:$AA$64,MATCH(1,INDEX((B$5:B$64=B50)*(C$5:C$64="BOMAG"),0),0)),0) -> 54087.22
A51: =B51&" | "&C51&" | "&D51 -> SDR | SEM | 510 | B51: SDR | C51: ='Datos SDR'!$B$48 -> SEM | D51: ='Datos SDR'!$C$48 -> 510 | E51: ='Datos SDR'!$E$48 -> 10000 | F51: ='Datos SDR'!$Z$48 -> 84076 | G51: ='Datos SDR'!$Y$48 -> 13 | H51: ='Datos SDR'!$AA$48 -> 1 | I51: ='Datos SDR'!$AB$48 -> 2 | J51: 0 | K51: NO | L51: N/A | M51: 567 | N51: 367 | O51: 333 | P51: 167 | Q51: =INDEX(M51:P51,MATCH(TipoSuelo,{"Roca","Grava","Suelo mixto","Arcilla"},0)) -> 333 | R51: =Q51*IF(AND(C51="BOMAG",L51="SÍ"),MultTecBOMAG,1) -> 333 | S51: =R51*Eficiencia -> 333 | T51: =IF(AND(S51>0,VolumenCompactacion>0),VolumenCompactacion/S51,0) -> 0 | U51: =G51*PrecioDiesel+H51+I51 -> 18.6 | V51: =T51*U51 -> 0 | W51: =G51*HorasOperacion*PrecioDiesel -> 46800 | X51: =HorasOperacion*(H51+I51) -> 9000 | Y51: =IF(AND(B51="SDR",K51="NO"),HorasOperacion/JuntaIntervalo,0) -> 60 | Z51: =Y51*JuntaHorasIntervencion*(JuntaTecnico+JuntaParada)+Y51*JuntaGrasa -> 5550 | AA51: =F51+W51+X51+Z51-J51 -> 145426 | AB51: =U51+IF(Y51>0,(JuntaHorasIntervencion*(JuntaTecnico+JuntaParada)+JuntaGrasa)/JuntaIntervalo,0) -> 20.45 | AC51: =IF(HorasOperacion>0,AA51/HorasOperacion,0) -> 48.475333 | AD51: =AA51*TasaMoneda -> 145426 | AE51: =IFERROR(AA51-INDEX($AA$5:$AA$64,MATCH(1,INDEX((B$5:B$64=B51)*(C$5:C$64="BOMAG"),0),0)),0) -> 36353.22
A52: =B52&" | "&C52&" | "&D52 -> SDR | CASE | 1107EX | B52: SDR | C52: ='Datos SDR'!$B$49 -> CASE | D52: ='Datos SDR'!$C$49 -> 1107EX | E52: ='Datos SDR'!$E$49 -> 11200 | F52: ='Datos SDR'!$Z$49 -> 84076 | G52: ='Datos SDR'!$Y$49 -> 13 | H52: ='Datos SDR'!$AA$49 -> 1 | I52: ='Datos SDR'!$AB$49 -> 2 | J52: 0 | K52: NO | L52: N/A | M52: 767 | N52: 567 | O52: 493 | P52: 247 | Q52: =INDEX(M52:P52,MATCH(TipoSuelo,{"Roca","Grava","Suelo mixto","Arcilla"},0)) -> 493 | R52: =Q52*IF(AND(C52="BOMAG",L52="SÍ"),MultTecBOMAG,1) -> 493 | S52: =R52*Eficiencia -> 493 | T52: =IF(AND(S52>0,VolumenCompactacion>0),VolumenCompactacion/S52,0) -> 0 | U52: =G52*PrecioDiesel+H52+I52 -> 18.6 | V52: =T52*U52 -> 0 | W52: =G52*HorasOperacion*PrecioDiesel -> 46800 | X52: =HorasOperacion*(H52+I52) -> 9000 | Y52: =IF(AND(B52="SDR",K52="NO"),HorasOperacion/JuntaIntervalo,0) -> 60 | Z52: =Y52*JuntaHorasIntervencion*(JuntaTecnico+JuntaParada)+Y52*JuntaGrasa -> 5550 | AA52: =F52+W52+X52+Z52-J52 -> 145426 | AB52: =U52+IF(Y52>0,(JuntaHorasIntervencion*(JuntaTecnico+JuntaParada)+JuntaGrasa)/JuntaIntervalo,0) -> 20.45 | AC52: =IF(HorasOperacion>0,AA52/HorasOperacion,0) -> 48.475333 | AD52: =AA52*TasaMoneda -> 145426 | AE52: =IFERROR(AA52-INDEX($AA$5:$AA$64,MATCH(1,INDEX((B$5:B$64=B52)*(C$5:C$64="BOMAG"),0),0)),0) -> 36353.22
A53: =B53&" | "&C53&" | "&D53 -> LTR | BOMAG | BW120 AD-5 | B53: LTR | C53: ='Datos LTR'!$B$2 -> BOMAG | D53: ='Datos LTR'!$C$2 -> BW120 AD-5 | E53: ='Datos LTR'!$D$2 -> 2700 | F53: ='Datos LTR'!$O$2 -> 28000 | G53: ='Datos LTR'!$N$2 -> 2.6 | H53: ='Datos LTR'!$P$2 -> 1 | I53: ='Datos LTR'!$Q$2 -> 1.3 | J53: 0 | K53: N/A | L53: NO | M53: 169 | N53: 144 | O53: 144 | P53: 82 | Q53: =INDEX(M53:P53,MATCH(TipoSuelo,{"Roca","Grava","Suelo mixto","Arcilla"},0)) -> 144 | R53: =Q53*IF(AND(C53="BOMAG",L53="SÍ"),MultTecBOMAG,1) -> 144 | S53: =R53*Eficiencia -> 144 | T53: =IF(AND(S53>0,VolumenCompactacion>0),VolumenCompactacion/S53,0) -> 0 | U53: =G53*PrecioDiesel+H53+I53 -> 5.42 | V53: =T53*U53 -> 0 | W53: =G53*HorasOperacion*PrecioDiesel -> 9360 | X53: =HorasOperacion*(H53+I53) -> 6900 | Y53: =IF(AND(B53="SDR",K53="NO"),HorasOperacion/JuntaIntervalo,0) -> 0 | Z53: =Y53*JuntaHorasIntervencion*(JuntaTecnico+JuntaParada)+Y53*JuntaGrasa -> 0 | AA53: =F53+W53+X53+Z53-J53 -> 44260 | AB53: =U53+IF(Y53>0,(JuntaHorasIntervencion*(JuntaTecnico+JuntaParada)+JuntaGrasa)/JuntaIntervalo,0) -> 5.42 | AC53: =IF(HorasOperacion>0,AA53/HorasOperacion,0) -> 14.753333 | AD53: =AA53*TasaMoneda -> 44260 | AE53: =IFERROR(AA53-INDEX($AA$5:$AA$64,MATCH(1,INDEX((B$5:B$64=B53)*(C$5:C$64="BOMAG"),0),0)),0) -> 0
A54: =B54&" | "&C54&" | "&D54 -> LTR | CATERPILLAR | CB2.7GC | B54: LTR | C54: ='Datos LTR'!$B$3 -> CATERPILLAR | D54: ='Datos LTR'!$C$3 -> CB2.7GC | E54: ='Datos LTR'!$D$3 -> 2698 | F54: ='Datos LTR'!$O$3 -> 29630 | G54: ='Datos LTR'!$N$3 -> 2.3 | H54: ='Datos LTR'!$P$3 -> 1 | I54: ='Datos LTR'!$Q$3 -> 2 | J54: 0 | K54: N/A | L54: N/A | M54: 169 | N54: 144 | O54: 144 | P54: 82 | Q54: =INDEX(M54:P54,MATCH(TipoSuelo,{"Roca","Grava","Suelo mixto","Arcilla"},0)) -> 144 | R54: =Q54*IF(AND(C54="BOMAG",L54="SÍ"),MultTecBOMAG,1) -> 144 | S54: =R54*Eficiencia -> 144 | T54: =IF(AND(S54>0,VolumenCompactacion>0),VolumenCompactacion/S54,0) -> 0 | U54: =G54*PrecioDiesel+H54+I54 -> 5.76 | V54: =T54*U54 -> 0 | W54: =G54*HorasOperacion*PrecioDiesel -> 8280 | X54: =HorasOperacion*(H54+I54) -> 9000 | Y54: =IF(AND(B54="SDR",K54="NO"),HorasOperacion/JuntaIntervalo,0) -> 0 | Z54: =Y54*JuntaHorasIntervencion*(JuntaTecnico+JuntaParada)+Y54*JuntaGrasa -> 0 | AA54: =F54+W54+X54+Z54-J54 -> 46910 | AB54: =U54+IF(Y54>0,(JuntaHorasIntervencion*(JuntaTecnico+JuntaParada)+JuntaGrasa)/JuntaIntervalo,0) -> 5.76 | AC54: =IF(HorasOperacion>0,AA54/HorasOperacion,0) -> 15.636667 | AD54: =AA54*TasaMoneda -> 46910 | AE54: =IFERROR(AA54-INDEX($AA$5:$AA$64,MATCH(1,INDEX((B$5:B$64=B54)*(C$5:C$64="BOMAG"),0),0)),0) -> 2650
A55: =B55&" | "&C55&" | "&D55 -> LTR | HAMM | HD12 VV | B55: LTR | C55: ='Datos LTR'!$B$4 -> HAMM | D55: ='Datos LTR'!$C$4 -> HD12 VV | E55: ='Datos LTR'!$D$4 -> 2695 | F55: ='Datos LTR'!$O$4 -> 29580 | G55: ='Datos LTR'!$N$4 -> 2.8 | H55: ='Datos LTR'!$P$4 -> 1.5 | I55: ='Datos LTR'!$Q$4 -> 1 | J55: 0 | K55: N/A | L55: N/A | M55: 169 | N55: 143 | O55: 143 | P55: 82 | Q55: =INDEX(M55:P55,MATCH(TipoSuelo,{"Roca","Grava","Suelo mixto","Arcilla"},0)) -> 143 | R55: =Q55*IF(AND(C55="BOMAG",L55="SÍ"),MultTecBOMAG,1) -> 143 | S55: =R55*Eficiencia -> 143 | T55: =IF(AND(S55>0,VolumenCompactacion>0),VolumenCompactacion/S55,0) -> 0 | U55: =G55*PrecioDiesel+H55+I55 -> 5.86 | V55: =T55*U55 -> 0 | W55: =G55*HorasOperacion*PrecioDiesel -> 10080 | X55: =HorasOperacion*(H55+I55) -> 7500 | Y55: =IF(AND(B55="SDR",K55="NO"),HorasOperacion/JuntaIntervalo,0) -> 0 | Z55: =Y55*JuntaHorasIntervencion*(JuntaTecnico+JuntaParada)+Y55*JuntaGrasa -> 0 | AA55: =F55+W55+X55+Z55-J55 -> 47160 | AB55: =U55+IF(Y55>0,(JuntaHorasIntervencion*(JuntaTecnico+JuntaParada)+JuntaGrasa)/JuntaIntervalo,0) -> 5.86 | AC55: =IF(HorasOperacion>0,AA55/HorasOperacion,0) -> 15.72 | AD55: =AA55*TasaMoneda -> 47160 | AE55: =IFERROR(AA55-INDEX($AA$5:$AA$64,MATCH(1,INDEX((B$5:B$64=B55)*(C$5:C$64="BOMAG"),0),0)),0) -> 2900
A56: =B56&" | "&C56&" | "&D56 -> LTR | DYNAPAC | CC1200 | B56: LTR | C56: ='Datos LTR'!$B$5 -> DYNAPAC | D56: ='Datos LTR'!$C$5 -> CC1200 | E56: ='Datos LTR'!$D$5 -> 2600 | F56: ='Datos LTR'!$O$5 -> 26783 | G56: ='Datos LTR'!$N$5 -> 2.7 | H56: ='Datos LTR'!$P$5 -> 1 | I56: ='Datos LTR'!$Q$5 -> 1.4 | J56: 0 | K56: N/A | L56: N/A | M56: 155 | N56: 132 | O56: 132 | P56: 76 | Q56: =INDEX(M56:P56,MATCH(TipoSuelo,{"Roca","Grava","Suelo mixto","Arcilla"},0)) -> 132 | R56: =Q56*IF(AND(C56="BOMAG",L56="SÍ"),MultTecBOMAG,1) -> 132 | S56: =R56*Eficiencia -> 132 | T56: =IF(AND(S56>0,VolumenCompactacion>0),VolumenCompactacion/S56,0) -> 0 | U56: =G56*PrecioDiesel+H56+I56 -> 5.64 | V56: =T56*U56 -> 0 | W56: =G56*HorasOperacion*PrecioDiesel -> 9720 | X56: =HorasOperacion*(H56+I56) -> 7200 | Y56: =IF(AND(B56="SDR",K56="NO"),HorasOperacion/JuntaIntervalo,0) -> 0 | Z56: =Y56*JuntaHorasIntervencion*(JuntaTecnico+JuntaParada)+Y56*JuntaGrasa -> 0 | AA56: =F56+W56+X56+Z56-J56 -> 43703 | AB56: =U56+IF(Y56>0,(JuntaHorasIntervencion*(JuntaTecnico+JuntaParada)+JuntaGrasa)/JuntaIntervalo,0) -> 5.64 | AC56: =IF(HorasOperacion>0,AA56/HorasOperacion,0) -> 14.567667 | AD56: =AA56*TasaMoneda -> 43703 | AE56: =IFERROR(AA56-INDEX($AA$5:$AA$64,MATCH(1,INDEX((B$5:B$64=B56)*(C$5:C$64="BOMAG"),0),0)),0) -> -557
A57: =B57&" | "&C57&" | "&D57 -> LTR | AMMANN | ARX 26 | B57: LTR | C57: ='Datos LTR'!$B$6 -> AMMANN | D57: ='Datos LTR'!$C$6 -> ARX 26 | E57: ='Datos LTR'!$D$6 -> 2460 | F57: ='Datos LTR'!$O$6 -> 25500 | G57: ='Datos LTR'!$N$6 -> 3.2 | H57: ='Datos LTR'!$P$6 -> 1 | I57: ='Datos LTR'!$Q$6 -> 1.3 | J57: 0 | K57: N/A | L57: N/A | M57: 136 | N57: 115 | O57: 115 | P57: 68 | Q57: =INDEX(M57:P57,MATCH(TipoSuelo,{"Roca","Grava","Suelo mixto","Arcilla"},0)) -> 115 | R57: =Q57*IF(AND(C57="BOMAG",L57="SÍ"),MultTecBOMAG,1) -> 115 | S57: =R57*Eficiencia -> 115 | T57: =IF(AND(S57>0,VolumenCompactacion>0),VolumenCompactacion/S57,0) -> 0 | U57: =G57*PrecioDiesel+H57+I57 -> 6.14 | V57: =T57*U57 -> 0 | W57: =G57*HorasOperacion*PrecioDiesel -> 11520 | X57: =HorasOperacion*(H57+I57) -> 6900 | Y57: =IF(AND(B57="SDR",K57="NO"),HorasOperacion/JuntaIntervalo,0) -> 0 | Z57: =Y57*JuntaHorasIntervencion*(JuntaTecnico+JuntaParada)+Y57*JuntaGrasa -> 0 | AA57: =F57+W57+X57+Z57-J57 -> 43920 | AB57: =U57+IF(Y57>0,(JuntaHorasIntervencion*(JuntaTecnico+JuntaParada)+JuntaGrasa)/JuntaIntervalo,0) -> 6.14 | AC57: =IF(HorasOperacion>0,AA57/HorasOperacion,0) -> 14.64 | AD57: =AA57*TasaMoneda -> 43920 | AE57: =IFERROR(AA57-INDEX($AA$5:$AA$64,MATCH(1,INDEX((B$5:B$64=B57)*(C$5:C$64="BOMAG"),0),0)),0) -> -340
A58: =B58&" | "&C58&" | "&D58 -> LTR | JCB | CT260 | B58: LTR | C58: ='Datos LTR'!$B$7 -> JCB | D58: ='Datos LTR'!$C$7 -> CT260 | E58: ='Datos LTR'!$D$7 -> 2740 | F58: ='Datos LTR'!$O$7 -> 23500 | G58: ='Datos LTR'!$N$7 -> 2.7 | H58: ='Datos LTR'!$P$7 -> 1.5 | I58: ='Datos LTR'!$Q$7 -> 2 | J58: 0 | K58: N/A | L58: N/A | M58: 175 | N58: 149 | O58: 149 | P58: 84 | Q58: =INDEX(M58:P58,MATCH(TipoSuelo,{"Roca","Grava","Suelo mixto","Arcilla"},0)) -> 149 | R58: =Q58*IF(AND(C58="BOMAG",L58="SÍ"),MultTecBOMAG,1) -> 149 | S58: =R58*Eficiencia -> 149 | T58: =IF(AND(S58>0,VolumenCompactacion>0),VolumenCompactacion/S58,0) -> 0 | U58: =G58*PrecioDiesel+H58+I58 -> 6.74 | V58: =T58*U58 -> 0 | W58: =G58*HorasOperacion*PrecioDiesel -> 9720 | X58: =HorasOperacion*(H58+I58) -> 10500 | Y58: =IF(AND(B58="SDR",K58="NO"),HorasOperacion/JuntaIntervalo,0) -> 0 | Z58: =Y58*JuntaHorasIntervencion*(JuntaTecnico+JuntaParada)+Y58*JuntaGrasa -> 0 | AA58: =F58+W58+X58+Z58-J58 -> 43720 | AB58: =U58+IF(Y58>0,(JuntaHorasIntervencion*(JuntaTecnico+JuntaParada)+JuntaGrasa)/JuntaIntervalo,0) -> 6.74 | AC58: =IF(HorasOperacion>0,AA58/HorasOperacion,0) -> 14.573333 | AD58: =AA58*TasaMoneda -> 43720 | AE58: =IFERROR(AA58-INDEX($AA$5:$AA$64,MATCH(1,INDEX((B$5:B$64=B58)*(C$5:C$64="BOMAG"),0),0)),0) -> -540
A59: =B59&" | "&C59&" | "&D59 -> LTR | WACKER NEUSON | RD27 | B59: LTR | C59: ='Datos LTR'!$B$8 -> WACKER NEUSON | D59: ='Datos LTR'!$C$8 -> RD27 | E59: ='Datos LTR'!$D$8 -> 2695 | F59: ='Datos LTR'!$O$8 -> 23500 | G59: ='Datos LTR'!$N$8 -> 2.7 | H59: ='Datos LTR'!$P$8 -> 1.5 | I59: ='Datos LTR'!$Q$8 -> 2 | J59: 0 | K59: N/A | L59: N/A | M59: 169 | N59: 143 | O59: 143 | P59: 82 | Q59: =INDEX(M59:P59,MATCH(TipoSuelo,{"Roca","Grava","Suelo mixto","Arcilla"},0)) -> 143 | R59: =Q59*IF(AND(C59="BOMAG",L59="SÍ"),MultTecBOMAG,1) -> 143 | S59: =R59*Eficiencia -> 143 | T59: =IF(AND(S59>0,VolumenCompactacion>0),VolumenCompactacion/S59,0) -> 0 | U59: =G59*PrecioDiesel+H59+I59 -> 6.74 | V59: =T59*U59 -> 0 | W59: =G59*HorasOperacion*PrecioDiesel -> 9720 | X59: =HorasOperacion*(H59+I59) -> 10500 | Y59: =IF(AND(B59="SDR",K59="NO"),HorasOperacion/JuntaIntervalo,0) -> 0 | Z59: =Y59*JuntaHorasIntervencion*(JuntaTecnico+JuntaParada)+Y59*JuntaGrasa -> 0 | AA59: =F59+W59+X59+Z59-J59 -> 43720 | AB59: =U59+IF(Y59>0,(JuntaHorasIntervencion*(JuntaTecnico+JuntaParada)+JuntaGrasa)/JuntaIntervalo,0) -> 6.74 | AC59: =IF(HorasOperacion>0,AA59/HorasOperacion,0) -> 14.573333 | AD59: =AA59*TasaMoneda -> 43720 | AE59: =IFERROR(AA59-INDEX($AA$5:$AA$64,MATCH(1,INDEX((B$5:B$64=B59)*(C$5:C$64="BOMAG"),0),0)),0) -> -540
A60: =B60&" | "&C60&" | "&D60 -> HTR | BOMAG | BW161 AD-4 | B60: HTR | C60: ='Datos HTR'!$B$2 -> BOMAG | D60: ='Datos HTR'!$C$2 -> BW161 AD-4 | E60: ='Datos HTR'!$D$2 -> 9700 | F60: ='Datos HTR'!$S$2 -> 28000 | G60: ='Datos HTR'!$R$2 -> 11.8 | H60: ='Datos HTR'!$T$2 -> 1 | I60: ='Datos HTR'!$U$2 -> 2 | J60: 0 | K60: N/A | L60: NO | M60: 517 | N60: 317 | O60: 293 | P60: 147 | Q60: =INDEX(M60:P60,MATCH(TipoSuelo,{"Roca","Grava","Suelo mixto","Arcilla"},0)) -> 293 | R60: =Q60*IF(AND(C60="BOMAG",L60="SÍ"),MultTecBOMAG,1) -> 293 | S60: =R60*Eficiencia -> 293 | T60: =IF(AND(S60>0,VolumenCompactacion>0),VolumenCompactacion/S60,0) -> 0 | U60: =G60*PrecioDiesel+H60+I60 -> 17.16 | V60: =T60*U60 -> 0 | W60: =G60*HorasOperacion*PrecioDiesel -> 42480 | X60: =HorasOperacion*(H60+I60) -> 9000 | Y60: =IF(AND(B60="SDR",K60="NO"),HorasOperacion/JuntaIntervalo,0) -> 0 | Z60: =Y60*JuntaHorasIntervencion*(JuntaTecnico+JuntaParada)+Y60*JuntaGrasa -> 0 | AA60: =F60+W60+X60+Z60-J60 -> 79480 | AB60: =U60+IF(Y60>0,(JuntaHorasIntervencion*(JuntaTecnico+JuntaParada)+JuntaGrasa)/JuntaIntervalo,0) -> 17.16 | AC60: =IF(HorasOperacion>0,AA60/HorasOperacion,0) -> 26.493333 | AD60: =AA60*TasaMoneda -> 79480 | AE60: =IFERROR(AA60-INDEX($AA$5:$AA$64,MATCH(1,INDEX((B$5:B$64=B60)*(C$5:C$64="BOMAG"),0),0)),0) -> 0
A61: =B61&" | "&C61&" | "&D61 -> HTR | AMMANN | AV110X | B61: HTR | C61: ='Datos HTR'!$B$3 -> AMMANN | D61: ='Datos HTR'!$C$3 -> AV110X | E61: ='Datos HTR'!$D$3 -> 10400 | F61: ='Datos HTR'!$S$3 -> 28000 | G61: ='Datos HTR'!$R$3 -> 11.8 | H61: ='Datos HTR'!$T$3 -> 1 | I61: ='Datos HTR'!$U$3 -> 2 | J61: 0 | K61: N/A | L61: N/A | M61: 633 | N61: 433 | O61: 387 | P61: 193 | Q61: =INDEX(M61:P61,MATCH(TipoSuelo,{"Roca","Grava","Suelo mixto","Arcilla"},0)) -> 387 | R61: =Q61*IF(AND(C61="BOMAG",L61="SÍ"),MultTecBOMAG,1) -> 387 | S61: =R61*Eficiencia -> 387 | T61: =IF(AND(S61>0,VolumenCompactacion>0),VolumenCompactacion/S61,0) -> 0 | U61: =G61*PrecioDiesel+H61+I61 -> 17.16 | V61: =T61*U61 -> 0 | W61: =G61*HorasOperacion*PrecioDiesel -> 42480 | X61: =HorasOperacion*(H61+I61) -> 9000 | Y61: =IF(AND(B61="SDR",K61="NO"),HorasOperacion/JuntaIntervalo,0) -> 0 | Z61: =Y61*JuntaHorasIntervencion*(JuntaTecnico+JuntaParada)+Y61*JuntaGrasa -> 0 | AA61: =F61+W61+X61+Z61-J61 -> 79480 | AB61: =U61+IF(Y61>0,(JuntaHorasIntervencion*(JuntaTecnico+JuntaParada)+JuntaGrasa)/JuntaIntervalo,0) -> 17.16 | AC61: =IF(HorasOperacion>0,AA61/HorasOperacion,0) -> 26.493333 | AD61: =AA61*TasaMoneda -> 79480 | AE61: =IFERROR(AA61-INDEX($AA$5:$AA$64,MATCH(1,INDEX((B$5:B$64=B61)*(C$5:C$64="BOMAG"),0),0)),0) -> 0
A62: =B62&" | "&C62&" | "&D62 -> HTR | CATERPILLAR | CB10 | B62: HTR | C62: ='Datos HTR'!$B$4 -> CATERPILLAR | D62: ='Datos HTR'!$C$4 -> CB10 | E62: ='Datos HTR'!$D$4 -> 9500 | F62: ='Datos HTR'!$S$4 -> 28000 | G62: ='Datos HTR'!$R$4 -> 11.8 | H62: ='Datos HTR'!$T$4 -> 1 | I62: ='Datos HTR'!$U$4 -> 2 | J62: 0 | K62: N/A | L62: N/A | M62: 483 | N62: 283 | O62: 267 | P62: 133 | Q62: =INDEX(M62:P62,MATCH(TipoSuelo,{"Roca","Grava","Suelo mixto","Arcilla"},0)) -> 267 | R62: =Q62*IF(AND(C62="BOMAG",L62="SÍ"),MultTecBOMAG,1) -> 267 | S62: =R62*Eficiencia -> 267 | T62: =IF(AND(S62>0,VolumenCompactacion>0),VolumenCompactacion/S62,0) -> 0 | U62: =G62*PrecioDiesel+H62+I62 -> 17.16 | V62: =T62*U62 -> 0 | W62: =G62*HorasOperacion*PrecioDiesel -> 42480 | X62: =HorasOperacion*(H62+I62) -> 9000 | Y62: =IF(AND(B62="SDR",K62="NO"),HorasOperacion/JuntaIntervalo,0) -> 0 | Z62: =Y62*JuntaHorasIntervencion*(JuntaTecnico+JuntaParada)+Y62*JuntaGrasa -> 0 | AA62: =F62+W62+X62+Z62-J62 -> 79480 | AB62: =U62+IF(Y62>0,(JuntaHorasIntervencion*(JuntaTecnico+JuntaParada)+JuntaGrasa)/JuntaIntervalo,0) -> 17.16 | AC62: =IF(HorasOperacion>0,AA62/HorasOperacion,0) -> 26.493333 | AD62: =AA62*TasaMoneda -> 79480 | AE62: =IFERROR(AA62-INDEX($AA$5:$AA$64,MATCH(1,INDEX((B$5:B$64=B62)*(C$5:C$64="BOMAG"),0),0)),0) -> 0
A63: =B63&" | "&C63&" | "&D63 -> HTR | DYNAPAC | CC4200 | B63: HTR | C63: ='Datos HTR'!$B$5 -> DYNAPAC | D63: ='Datos HTR'!$C$5 -> CC4200 | E63: ='Datos HTR'!$D$5 -> 10400 | F63: ='Datos HTR'!$S$5 -> 28000 | G63: ='Datos HTR'!$R$5 -> 11.8 | H63: ='Datos HTR'!$T$5 -> 1 | I63: ='Datos HTR'!$U$5 -> 2 | J63: 0 | K63: N/A | L63: N/A | M63: 633 | N63: 433 | O63: 387 | P63: 193 | Q63: =INDEX(M63:P63,MATCH(TipoSuelo,{"Roca","Grava","Suelo mixto","Arcilla"},0)) -> 387 | R63: =Q63*IF(AND(C63="BOMAG",L63="SÍ"),MultTecBOMAG,1) -> 387 | S63: =R63*Eficiencia -> 387 | T63: =IF(AND(S63>0,VolumenCompactacion>0),VolumenCompactacion/S63,0) -> 0 | U63: =G63*PrecioDiesel+H63+I63 -> 17.16 | V63: =T63*U63 -> 0 | W63: =G63*HorasOperacion*PrecioDiesel -> 42480 | X63: =HorasOperacion*(H63+I63) -> 9000 | Y63: =IF(AND(B63="SDR",K63="NO"),HorasOperacion/JuntaIntervalo,0) -> 0 | Z63: =Y63*JuntaHorasIntervencion*(JuntaTecnico+JuntaParada)+Y63*JuntaGrasa -> 0 | AA63: =F63+W63+X63+Z63-J63 -> 79480 | AB63: =U63+IF(Y63>0,(JuntaHorasIntervencion*(JuntaTecnico+JuntaParada)+JuntaGrasa)/JuntaIntervalo,0) -> 17.16 | AC63: =IF(HorasOperacion>0,AA63/HorasOperacion,0) -> 26.493333 | AD63: =AA63*TasaMoneda -> 79480 | AE63: =IFERROR(AA63-INDEX($AA$5:$AA$64,MATCH(1,INDEX((B$5:B$64=B63)*(C$5:C$64="BOMAG"),0),0)),0) -> 0
A64: =B64&" | "&C64&" | "&D64 -> HTR | HAMM | HD90 VV | B64: HTR | C64: ='Datos HTR'!$B$6 -> HAMM | D64: ='Datos HTR'!$C$6 -> HD90 VV | E64: ='Datos HTR'!$D$6 -> 9190 | F64: ='Datos HTR'!$S$6 -> 28000 | G64: ='Datos HTR'!$R$6 -> 11.8 | H64: ='Datos HTR'!$T$6 -> 1 | I64: ='Datos HTR'!$U$6 -> 2 | J64: 0 | K64: N/A | L64: N/A | M64: 432 | N64: 232 | O64: 225 | P64: 113 | Q64: =INDEX(M64:P64,MATCH(TipoSuelo,{"Roca","Grava","Suelo mixto","Arcilla"},0)) -> 225 | R64: =Q64*IF(AND(C64="BOMAG",L64="SÍ"),MultTecBOMAG,1) -> 225 | S64: =R64*Eficiencia -> 225 | T64: =IF(AND(S64>0,VolumenCompactacion>0),VolumenCompactacion/S64,0) -> 0 | U64: =G64*PrecioDiesel+H64+I64 -> 17.16 | V64: =T64*U64 -> 0 | W64: =G64*HorasOperacion*PrecioDiesel -> 42480 | X64: =HorasOperacion*(H64+I64) -> 9000 | Y64: =IF(AND(B64="SDR",K64="NO"),HorasOperacion/JuntaIntervalo,0) -> 0 | Z64: =Y64*JuntaHorasIntervencion*(JuntaTecnico+JuntaParada)+Y64*JuntaGrasa -> 0 | AA64: =F64+W64+X64+Z64-J64 -> 79480 | AB64: =U64+IF(Y64>0,(JuntaHorasIntervencion*(JuntaTecnico+JuntaParada)+JuntaGrasa)/JuntaIntervalo,0) -> 17.16 | AC64: =IF(HorasOperacion>0,AA64/HorasOperacion,0) -> 26.493333 | AD64: =AA64*TasaMoneda -> 79480 | AE64: =IFERROR(AA64-INDEX($AA$5:$AA$64,MATCH(1,INDEX((B$5:B$64=B64)*(C$5:C$64="BOMAG"),0),0)),0) -> 0

Sheet Análisis Fresadoras
A1: Análisis financiero — Fresadoras en frío
A3: ID | B3: Marca | C3: Modelo | D3: Precio (USD) | E3: Consumo (L/h) | F3: Mant. preventivo base (USD/h) | G3: Mant. correctivo base (USD/h) | H3: Tiene BMS15L? | I3: BMS15L activado? | J3: Reducción de desgaste (%) | K3: Multiplicador de desgaste | L3: Mant. preventivo efectivo (USD/h) | M3: Mant. correctivo efectivo (USD/h) | N3: Desgaste herramientas base (USD/h) | O3: Desgaste herramientas efectivo (USD/h) | P3: Capacidad de transporte (m³/h) | Q3: Velocidad de trabajo (m/min) | R3: Radio de giro (m) | S3: Horas para el volumen (h) | T3: Costo combustible (USD) | U3: Costo mantenimiento (USD) | V3: Costo desgaste herramientas (USD) | W3: Valor de reventa (USD) | X3: TCO (USD) | Y3: Costo variable (USD/h) | Z3: TCO por hora (USD/h) | AA3: TCO (moneda sel.) | AB3: Δ TCO vs BOMAG (USD)
A4: =B4&" | "&C4 -> BOMAG | BM 1000/20 | B4: ='Datos Fresadoras'!$B$2 -> BOMAG | C4: ='Datos Fresadoras'!$C$2 -> BM 1000/20 | D4: ='Datos Fresadoras'!$X$2 -> 0 | E4: ='Datos Fresadoras'!$Y$2 -> 16 | F4: ='Datos Fresadoras'!$Z$2 -> 12 | G4: ='Datos Fresadoras'!$AA$2 -> 8 | H4: SÍ | I4: SÍ | J4: 0.2 | K4: =IF(AND(H4="SÍ",I4="SÍ"),1-J4,1) -> 0.8 | L4: =F4*K4 -> 9.6 | M4: =G4*K4 -> 6.4 | N4: ='Datos Fresadoras'!$AI$2 -> 15 | O4: =N4*K4 -> 12 | P4: 92 | Q4: 40 | R4: 0.38 | S4: =IF(AND(VolumenFresado>0,P4>0),VolumenFresado/P4,0) -> 0 | T4: =E4*HorasOperacion*PrecioDiesel -> 57600 | U4: =HorasOperacion*(L4+M4) -> 48000 | V4: =O4*HorasOperacion -> 36000 | W4: 0 | X4: =D4+T4+U4+V4-W4 -> 141600 | Y4: =E4*PrecioDiesel+L4+M4+O4 -> 47.2 | Z4: =IF(HorasOperacion>0,X4/HorasOperacion,0) -> 47.2 | AA4: =X4*TasaMoneda -> 141600 | AB4: =IFERROR(X4-INDEX($X$4:$X$6,MATCH("BOMAG",$B$4:$B$6,0)),0) -> 0
A5: =B5&" | "&C5 -> SANY | SCM1000C-8 | B5: ='Datos Fresadoras'!$B$3 -> SANY | C5: ='Datos Fresadoras'!$C$3 -> SCM1000C-8 | D5: ='Datos Fresadoras'!$X$3 -> 0 | E5: ='Datos Fresadoras'!$Y$3 -> 22 | F5: ='Datos Fresadoras'!$Z$3 -> 10 | G5: ='Datos Fresadoras'!$AA$3 -> 10 | H5: NO | I5: SÍ | J5: =ReduccionBMS15L -> 0.2 | K5: =IF(AND(H5="SÍ",I5="SÍ"),1-J5,1) -> 1 | L5: =F5*K5 -> 10 | M5: =G5*K5 -> 10 | N5: ='Datos Fresadoras'!$AI$3 -> 20 | O5: =N5*K5 -> 20 | P5: 0 | Q5: 35 | R5: 1.2 | S5: =IF(AND(VolumenFresado>0,P5>0),VolumenFresado/P5,0) -> 0 | T5: =E5*HorasOperacion*PrecioDiesel -> 79200 | U5: =HorasOperacion*(L5+M5) -> 60000 | V5: =O5*HorasOperacion -> 60000 | W5: 0 | X5: =D5+T5+U5+V5-W5 -> 199200 | Y5: =E5*PrecioDiesel+L5+M5+O5 -> 66.4 | Z5: =IF(HorasOperacion>0,X5/HorasOperacion,0) -> 66.4 | AA5: =X5*TasaMoneda -> 199200 | AB5: =IFERROR(X5-INDEX($X$4:$X$6,MATCH("BOMAG",$B$4:$B$6,0)),0) -> 57600
A6: =B6&" | "&C6 -> XCMG | XM1005H | B6: ='Datos Fresadoras'!$B$4 -> XCMG | C6: ='Datos Fresadoras'!$C$4 -> XM1005H | D6: ='Datos Fresadoras'!$X$4 -> 0 | E6: ='Datos Fresadoras'!$Y$4 -> 18 | F6: ='Datos Fresadoras'!$Z$4 -> 10 | G6: ='Datos Fresadoras'!$AA$4 -> 8 | H6: NO | I6: SÍ | J6: =ReduccionBMS15L -> 0.2 | K6: =IF(AND(H6="SÍ",I6="SÍ"),1-J6,1) -> 1 | L6: =F6*K6 -> 10 | M6: =G6*K6 -> 8 | N6: ='Datos Fresadoras'!$AI$4 -> 17 | O6: =N6*K6 -> 17 | P6: 84 | Q6: 50 | R6: No declarado | S6: =IF(AND(VolumenFresado>0,P6>0),VolumenFresado/P6,0) -> 0 | T6: =E6*HorasOperacion*PrecioDiesel -> 64800 | U6: =HorasOperacion*(L6+M6) -> 54000 | V6: =O6*HorasOperacion -> 51000 | W6: 0 | X6: =D6+T6+U6+V6-W6 -> 169800 | Y6: =E6*PrecioDiesel+L6+M6+O6 -> 56.6 | Z6: =IF(HorasOperacion>0,X6/HorasOperacion,0) -> 56.6 | AA6: =X6*TasaMoneda -> 169800 | AB6: =IFERROR(X6-INDEX($X$4:$X$6,MATCH("BOMAG",$B$4:$B$6,0)),0) -> 28200

Sheet Análisis Pavimentadoras
A1: Análisis financiero — Pavimentadoras
A2: Consumo base y mantenimiento son los valores que la app deriva del bloque financiero (ver notas en cada encabezado). Precio en 0 en la app: ingréselo.
A4: ID | B4: Marca | C4: Modelo | D4: Precio (USD) | E4: Consumo base (L/h) | F4: Modo de ahorro | G4: Tiene ECOMODE? | H4: Modo de ahorro activado? | I4: Factor de consumo | J4: Consumo efectivo (L/h) | K4: Mant. preventivo (USD/h) | L4: Mant. correctivo (USD/h) | M4: Tiene MAGMALIFE? | N4: MAGMALIFE activado? | O4: Combustible calentamiento ficha (L/turno) | P4: Combustible calentamiento efectivo (L/turno) | Q4: Tiempo calentamiento ficha (min) | R4: Tiempo calentamiento efectivo (min) | S4: Reemplazos plancha 3 años (EUR) | T4: Desgaste plancha propio (USD/h) | U4: Desgaste plancha competidor (USD/h) | V4: Desgaste plancha efectivo (USD/h) | W4: Costo combustible (USD) | X4: Costo mantenimiento (USD) | Y4: Costo combustible calentamiento (USD) | Z4: Costo desgaste plancha (USD) | AA4: Valor de reventa (USD) | AB4: TCO (USD) | AC4: Costo variable (USD/h) | AD4: TCO por hora (USD/h) | AE4: TCO (moneda sel.) | AF4: Δ TCO vs BOMAG (USD)
A5: =B5&" | "&C5 -> CATERPILLAR | AP655 | B5: ='Datos Pavimentadoras'!$B$2 -> CATERPILLAR | C5: ='Datos Pavimentadoras'!$C$2 -> AP655 | D5: 0 | E5: 14.0769 | F5: ='Datos Pavimentadoras'!$G$2 -> Eco-mode + control auto rpm | G5: NO | H5: NO | I5: =IF(H5="NO",1,IF(G5="SÍ",1-AhorroECOMODE,IF(ISNUMBER(SEARCH("ecoplus",F5)),FactorEcoPlus,IF(ISNUMBER(SEARCH("variospeed",F5)),FactorVarioSpeed,IF(ISNUMBER(SEARCH("eco-mode",F5)),FactorEcoMode,IF(ISNUMBER(SEARCH("eco mode",F5)),FactorEcoMode,1)))))) -> 1 | J5: =E5*I5 -> 14.0769 | K5: 10 | L5: 6 | M5: NO | N5: SÍ | O5: 10.5 | P5: =IF(AND(M5="SÍ",N5="SÍ"),IF(O5>0,O5,SetupMagmaL),IF(M5="SÍ",SetupCompetidorL,IF(O5>0,O5,SetupCompetidorL))) -> 10.5 | Q5: 60 | R5: =IF(AND(M5="SÍ",N5="NO"),HorasCalentamientoComp,IF(Q5>0,Q5,HorasCalentamientoComp)) -> 60 | S5: 24000 | T5: =S5*EURUSD/(3*HorasAnioPaver) -> 8.64 | U5: =Desgaste3aCompEUR*EURUSD/(3*HorasAnioPaver) -> 8.64 | V5: =IF(AND(M5="SÍ",N5="SÍ"),T5,IF(M5="SÍ",U5,IF(T5>0,T5,U5))) -> 8.64 | W5: =J5*HorasOperacion*PrecioDiesel -> 50676.84 | X5: =HorasOperacion*(K5+L5) -> 48000 | Y5: =HorasOperacion/HorasTurno*P5*PrecioDiesel -> 3780 | Z5: =V5*HorasOperacion -> 25920 | AA5: 0 | AB5: =D5+W5+X5+Y5+Z5-AA5 -> 128376.84 | AC5: =J5*PrecioDiesel+K5+L5+P5/HorasTurno*PrecioDiesel+V5 -> 42.79228 | AD5: =IF(HorasOperacion>0,AB5/HorasOperacion,0) -> 42.79228 | AE5: =AB5*TasaMoneda -> 128376.84 | AF5: =IFERROR(AB5-INDEX($AB$5:$AB$8,MATCH("BOMAG",$B$5:$B$8,0)),0) -> 55883.64
A6: =B6&" | "&C6 -> BOMAG | BF600 C-3 | B6: ='Datos Pavimentadoras'!$B$3 -> BOMAG | C6: ='Datos Pavimentadoras'!$C$3 -> BF600 C-3 | D6: 0 | E6: 8.9 | F6: ='Datos Pavimentadoras'!$G$3 -> ECOMODE | G6: SÍ | H6: SÍ | I6: =IF(H6="NO",1,IF(G6="SÍ",1-AhorroECOMODE,IF(ISNUMBER(SEARCH("ecoplus",F6)),FactorEcoPlus,IF(ISNUMBER(SEARCH("variospeed",F6)),FactorVarioSpeed,IF(ISNUMBER(SEARCH("eco-mode",F6)),FactorEcoMode,IF(ISNUMBER(SEARCH("eco mode",F6)),FactorEcoMode,1)))))) -> 0.83 | J6: =E6*I6 -> 7.387 | K6: 8 | L6: 4 | M6: SÍ | N6: SÍ | O6: 3.5 | P6: =IF(AND(M6="SÍ",N6="SÍ"),IF(O6>0,O6,SetupMagmaL),IF(M6="SÍ",SetupCompetidorL,IF(O6>0,O6,SetupCompetidorL))) -> 3.5 | Q6: 30 | R6: =IF(AND(M6="SÍ",N6="NO"),HorasCalentamientoComp,IF(Q6>0,Q6,HorasCalentamientoComp)) -> 30 | S6: 8000 | T6: =S6*EURUSD/(3*HorasAnioPaver) -> 2.88 | U6: =Desgaste3aCompEUR*EURUSD/(3*HorasAnioPaver) -> 8.64 | V6: =IF(AND(M6="SÍ",N6="SÍ"),T6,IF(M6="SÍ",U6,IF(T6>0,T6,U6))) -> 2.88 | W6: =J6*HorasOperacion*PrecioDiesel -> 26593.2 | X6: =HorasOperacion*(K6+L6) -> 36000 | Y6: =HorasOperacion/HorasTurno*P6*PrecioDiesel -> 1260 | Z6: =V6*HorasOperacion -> 8640 | AA6: 0 | AB6: =D6+W6+X6+Y6+Z6-AA6 -> 72493.2 | AC6: =J6*PrecioDiesel+K6+L6+P6/HorasTurno*PrecioDiesel+V6 -> 24.1644 | AD6: =IF(HorasOperacion>0,AB6/HorasOperacion,0) -> 24.1644 | AE6: =AB6*TasaMoneda -> 72493.2 | AF6: =IFERROR(AB6-INDEX($AB$5:$AB$8,MATCH("BOMAG",$B$5:$B$8,0)),0) -> 0
A7: =B7&" | "&C7 -> VÖGELE | Super 1800-3 | B7: ='Datos Pavimentadoras'!$B$4 -> VÖGELE | C7: ='Datos Pavimentadoras'!$C$4 -> Super 1800-3 | D7: 0 | E7: 0 | F7: ='Datos Pavimentadoras'!$G$4 -> EcoPlus | G7: NO | H7: NO | I7: =IF(H7="NO",1,IF(G7="SÍ",1-AhorroECOMODE,IF(ISNUMBER(SEARCH("ecoplus",F7)),FactorEcoPlus,IF(ISNUMBER(SEARCH("variospeed",F7)),FactorVarioSpeed,IF(ISNUMBER(SEARCH("eco-mode",F7)),FactorEcoMode,IF(ISNUMBER(SEARCH("eco mode",F7)),FactorEcoMode,1)))))) -> 1 | J7: =E7*I7 -> 0 | K7: 10 | L7: 6 | M7: NO | N7: SÍ | O7: 10.5 | P7: =IF(AND(M7="SÍ",N7="SÍ"),IF(O7>0,O7,SetupMagmaL),IF(M7="SÍ",SetupCompetidorL,IF(O7>0,O7,SetupCompetidorL))) -> 10.5 | Q7: 60 | R7: =IF(AND(M7="SÍ",N7="NO"),HorasCalentamientoComp,IF(Q7>0,Q7,HorasCalentamientoComp)) -> 60 | S7: 24000 | T7: =S7*EURUSD/(3*HorasAnioPaver) -> 8.64 | U7: =Desgaste3aCompEUR*EURUSD/(3*HorasAnioPaver) -> 8.64 | V7: =IF(AND(M7="SÍ",N7="SÍ"),T7,IF(M7="SÍ",U7,IF(T7>0,T7,U7))) -> 8.64 | W7: =J7*HorasOperacion*PrecioDiesel -> 0 | X7: =HorasOperacion*(K7+L7) -> 48000 | Y7: =HorasOperacion/HorasTurno*P7*PrecioDiesel -> 3780 | Z7: =V7*HorasOperacion -> 25920 | AA7: 0 | AB7: =D7+W7+X7+Y7+Z7-AA7 -> 77700 | AC7: =J7*PrecioDiesel+K7+L7+P7/HorasTurno*PrecioDiesel+V7 -> 25.9 | AD7: =IF(HorasOperacion>0,AB7/HorasOperacion,0) -> 25.9 | AE7: =AB7*TasaMoneda -> 77700 | AF7: =IFERROR(AB7-INDEX($AB$5:$AB$8,MATCH("BOMAG",$B$5:$B$8,0)),0) -> 5206.8
A8: =B8&" | "&C8 -> DYNAPAC | SD2500CS | B8: ='Datos Pavimentadoras'!$B$5 -> DYNAPAC | C8: ='Datos Pavimentadoras'!$C$5 -> SD2500CS | D8: 0 | E8: 10.5 | F8: ='Datos Pavimentadoras'!$G$5 -> VarioSpeed | G8: NO | H8: NO | I8: =IF(H8="NO",1,IF(G8="SÍ",1-AhorroECOMODE,IF(ISNUMBER(SEARCH("ecoplus",F8)),FactorEcoPlus,IF(ISNUMBER(SEARCH("variospeed",F8)),FactorVarioSpeed,IF(ISNUMBER(SEARCH("eco-mode",F8)),FactorEcoMode,IF(ISNUMBER(SEARCH("eco mode",F8)),FactorEcoMode,1)))))) -> 1 | J8: =E8*I8 -> 10.5 | K8: 10 | L8: 6 | M8: NO | N8: SÍ | O8: 10.5 | P8: =IF(AND(M8="SÍ",N8="SÍ"),IF(O8>0,O8,SetupMagmaL),IF(M8="SÍ",SetupCompetidorL,IF(O8>0,O8,SetupCompetidorL))) -> 10.5 | Q8: 30 | R8: =IF(AND(M8="SÍ",N8="NO"),HorasCalentamientoComp,IF(Q8>0,Q8,HorasCalentamientoComp)) -> 30 | S8: 24000 | T8: =S8*EURUSD/(3*HorasAnioPaver) -> 8.64 | U8: =Desgaste3aCompEUR*EURUSD/(3*HorasAnioPaver) -> 8.64 | V8: =IF(AND(M8="SÍ",N8="SÍ"),T8,IF(M8="SÍ",U8,IF(T8>0,T8,U8))) -> 8.64 | W8: =J8*HorasOperacion*PrecioDiesel -> 37800 | X8: =HorasOperacion*(K8+L8) -> 48000 | Y8: =HorasOperacion/HorasTurno*P8*PrecioDiesel -> 3780 | Z8: =V8*HorasOperacion -> 25920 | AA8: 0 | AB8: =D8+W8+X8+Y8+Z8-AA8 -> 115500 | AC8: =J8*PrecioDiesel+K8+L8+P8/HorasTurno*PrecioDiesel+V8 -> 38.5 | AD8: =IF(HorasOperacion>0,AB8/HorasOperacion,0) -> 38.5 | AE8: =AB8*TasaMoneda -> 115500 | AF8: =IFERROR(AB8-INDEX($AB$5:$AB$8,MATCH("BOMAG",$B$5:$B$8,0)),0) -> 43006.8
B10: Ahorro BOMAG en el período (USD) | D10: =IFERROR(SUMPRODUCT(MAX(($B$5:$B$8<>"BOMAG")*$AB$5:$AB$8))-INDEX($AB$5:$AB$8,MATCH("BOMAG",$B$5:$B$8,0)),0) -> 55883.64

Sheet Junta Articulada
A1: Análisis de costo — Junta articulada libre de mantenimiento
A3: Tiempo de operación a analizar (h) | B3: =HorasOperacion -> 3000
A4: Tarifa técnico (USD/h) | B4: =JuntaTecnico -> 35
A5: Costo máquina parada (USD/h) | B5: =JuntaParada -> 120
A6: Costo grasa por intervención (USD) | B6: =JuntaGrasa -> 15
A8: Concepto | B8: Competidor | C8: BOMAG | D8: Ahorro
A9: Junta libre de mantenimiento? | B9: NO | C9: SÍ
A10: Intervenciones de engrase | B10: =IF(B9="SÍ",0,$B$3/JuntaIntervalo) -> 60 | C10: =IF(C9="SÍ",0,$B$3/JuntaIntervalo) -> 0 | D10: =B10-C10 -> 60
A11: Horas improductivas (h) | B11: =B10*JuntaHorasIntervencion -> 30 | C11: =C10*JuntaHorasIntervencion -> 0 | D11: =B11-C11 -> 30
A12: Mano de obra (USD) | B12: =B11*$B$4 -> 1050 | C12: =C11*$B$4 -> 0 | D12: =B12-C12 -> 1050
A13: Insumos / grasa (USD) | B13: =B10*$B$6 -> 900 | C13: =C10*$B$6 -> 0 | D13: =B13-C13 -> 900
A14: Productividad perdida (USD) | B14: =B11*$B$5 -> 3600 | C14: =C11*$B$5 -> 0 | D14: =B14-C14 -> 3600
A15: Total junta (USD) | B15: =SUM(B12:B14) -> 5550 | C15: =SUM(C12:C14) -> 0 | D15: =B15-C15 -> 5550

Sheet TCO Progresivo
A1: TCO progresivo por horas de operación (USD)
A2: TCO(h) = Precio (o TCO inicial editado) + h × Costo variable − Valor de reventa. Horas editables en la fila de encabezado (azul).
A4: Línea | B4: ID | C4: TCO inicial (USD) | D4: Costo variable (USD/h) | E4: Valor de reventa (USD) | F4: 0 | G4: 1000 | H4: 1500 | I4: 2000 | J4: 2500 | K4: 3000 | L4: 4000 | M4: 5000 | N4: 6000 | O4: 7000 | P4: 8000 | Q4: 9000 | R4: 10000
A5: SDR | B5: ='Análisis Compactación'!A5 -> SDR | BOMAG | BW211 D-5 SL (mat. 93500000) | C5: ='Análisis Compactación'!F5 -> 57592.78 | D5: ='Análisis Compactación'!AB5 -> 17.16 | E5: ='Análisis Compactación'!J5 -> 0 | F5: =$C5+F$4*$D5-$E5 -> 57592.78 | G5: =$C5+G$4*$D5-$E5 -> 74752.78 | H5: =$C5+H$4*$D5-$E5 -> 83332.78 | I5: =$C5+I$4*$D5-$E5 -> 91912.78 | J5: =$C5+J$4*$D5-$E5 -> 100492.78 | K5: =$C5+K$4*$D5-$E5 -> 109072.78 | L5: =$C5+L$4*$D5-$E5 -> 126232.78 | M5: =$C5+M$4*$D5-$E5 -> 143392.78 | ... R5: =$C5+R$4*$D5-$E5 -> 229192.78
A6: SDR | B6: ='Análisis Compactación'!A6 -> SDR | BOMAG | BW211 D-5 SL (mat. 93500004) | C6: ='Análisis Compactación'!F6 -> 59374 | D6: ='Análisis Compactación'!AB6 -> 17.16 | E6: ='Análisis Compactación'!J6 -> 0 | F6: =$C6+F$4*$D6-$E6 -> 59374 | G6: =$C6+G$4*$D6-$E6 -> 76534 | H6: =$C6+H$4*$D6-$E6 -> 85114 | I6: =$C6+I$4*$D6-$E6 -> 93694 | J6: =$C6+J$4*$D6-$E6 -> 102274 | K6: =$C6+K$4*$D6-$E6 -> 110854 | L6: =$C6+L$4*$D6-$E6 -> 128014 | M6: =$C6+M$4*$D6-$E6 -> 145174 | ... R6: =$C6+R$4*$D6-$E6 -> 230974
A7: SDR | B7: ='Análisis Compactación'!A7 -> SDR | BOMAG | BW211 D-5 SL (mat. 58400031) | C7: ='Análisis Compactación'!F7 -> 63530.18 | D7: ='Análisis Compactación'!AB7 -> 17.88 | E7: ='Análisis Compactación'!J7 -> 0 | F7: =$C7+F$4*$D7-$E7 -> 63530.18 | G7: =$C7+G$4*$D7-$E7 -> 81410.18 | H7: =$C7+H$4*$D7-$E7 -> 90350.18 | I7: =$C7+I$4*$D7-$E7 -> 99290.18 | J7: =$C7+J$4*$D7-$E7 -> 108230.18 | K7: =$C7+K$4*$D7-$E7 -> 117170.18 | L7: =$C7+L$4*$D7-$E7 -> 135050.18 | M7: =$C7+M$4*$D7-$E7 -> 152930.18 | ... R7: =$C7+R$4*$D7-$E7 -> 242330.18
A8: SDR | B8: ='Análisis Compactación'!A8 -> SDR | BOMAG | BW211 D-5 SL (mat. 58400033) | C8: ='Análisis Compactación'!F8 -> 66500 | D8: ='Análisis Compactación'!AB8 -> 17.88 | E8: ='Análisis Compactación'!J8 -> 0 | F8: =$C8+F$4*$D8-$E8 -> 66500 | G8: =$C8+G$4*$D8-$E8 -> 84380 | H8: =$C8+H$4*$D8-$E8 -> 93320 | I8: =$C8+I$4*$D8-$E8 -> 102260 | J8: =$C8+J$4*$D8-$E8 -> 111200 | K8: =$C8+K$4*$D8-$E8 -> 120140 | L8: =$C8+L$4*$D8-$E8 -> 138020 | M8: =$C8+M$4*$D8-$E8 -> 155900 | ... R8: =$C8+R$4*$D8-$E8 -> 245300
A9: SDR | B9: ='Análisis Compactación'!A9 -> SDR | BOMAG | BW212 D-5 SL | C9: ='Análisis Compactación'!F9 -> 68684 | D9: ='Análisis Compactación'!AB9 -> 17.88 | E9: ='Análisis Compactación'!J9 -> 0 | F9: =$C9+F$4*$D9-$E9 -> 68684 | G9: =$C9+G$4*$D9-$E9 -> 86564 | H9: =$C9+H$4*$D9-$E9 -> 95504 | I9: =$C9+I$4*$D9-$E9 -> 104444 | J9: =$C9+J$4*$D9-$E9 -> 113384 | K9: =$C9+K$4*$D9-$E9 -> 122324 | L9: =$C9+L$4*$D9-$E9 -> 140204 | M9: =$C9+M$4*$D9-$E9 -> 158084 | ... R9: =$C9+R$4*$D9-$E9 -> 247484
A10: SDR | B10: ='Análisis Compactación'!A10 -> SDR | BOMAG | BW213 D-5 SL | C10: ='Análisis Compactación'!F10 -> 72948 | D10: ='Análisis Compactación'!AB10 -> 17.88 | E10: ='Análisis Compactación'!J10 -> 0 | F10: =$C10+F$4*$D10-$E10 -> 72948 | G10: =$C10+G$4*$D10-$E10 -> 90828 | H10: =$C10+H$4*$D10-$E10 -> 99768 | I10: =$C10+I$4*$D10-$E10 -> 108708 | J10: =$C10+J$4*$D10-$E10 -> 117648 | K10: =$C10+K$4*$D10-$E10 -> 126588 | L10: =$C10+L$4*$D10-$E10 -> 144468 | M10: =$C10+M$4*$D10-$E10 -> 162348 | ... R10: =$C10+R$4*$D10-$E10 -> 251748
A11: SDR | B11: ='Análisis Compactación'!A11 -> SDR | BOMAG | BW213 D-5 SL TCD | C11: ='Análisis Compactación'!F11 -> 72948 | D11: ='Análisis Compactación'!AB11 -> 17.88 | E11: ='Análisis Compactación'!J11 -> 0 | F11: =$C11+F$4*$D11-$E11 -> 72948 | G11: =$C11+G$4*$D11-$E11 -> 90828 | H11: =$C11+H$4*$D11-$E11 -> 99768 | I11: =$C11+I$4*$D11-$E11 -> 108708 | J11: =$C11+J$4*$D11-$E11 -> 117648 | K11: =$C11+K$4*$D11-$E11 -> 126588 | L11: =$C11+L$4*$D11-$E11 -> 144468 | M11: =$C11+M$4*$D11-$E11 -> 162348 | ... R11: =$C11+R$4*$D11-$E11 -> 251748
A12: SDR | B12: ='Análisis Compactación'!A12 -> SDR | BOMAG | BW216 D-5 SL | C12: ='Análisis Compactación'!F12 -> 0 | D12: ='Análisis Compactación'!AB12 -> 3 | E12: ='Análisis Compactación'!J12 -> 0 | F12: =$C12+F$4*$D12-$E12 -> 0 | G12: =$C12+G$4*$D12-$E12 -> 3000 | H12: =$C12+H$4*$D12-$E12 -> 4500 | I12: =$C12+I$4*$D12-$E12 -> 6000 | J12: =$C12+J$4*$D12-$E12 -> 7500 | K12: =$C12+K$4*$D12-$E12 -> 9000 | L12: =$C12+L$4*$D12-$E12 -> 12000 | M12: =$C12+M$4*$D12-$E12 -> 15000 | ... R12: =$C12+R$4*$D12-$E12 -> 30000
A13: SDR | B13: ='Análisis Compactación'!A13 -> SDR | BOMAG | BW219 D-5 PL | C13: ='Análisis Compactación'!F13 -> 0 | D13: ='Análisis Compactación'!AB13 -> 3 | E13: ='Análisis Compactación'!J13 -> 0 | F13: =$C13+F$4*$D13-$E13 -> 0 | G13: =$C13+G$4*$D13-$E13 -> 3000 | H13: =$C13+H$4*$D13-$E13 -> 4500 | I13: =$C13+I$4*$D13-$E13 -> 6000 | J13: =$C13+J$4*$D13-$E13 -> 7500 | K13: =$C13+K$4*$D13-$E13 -> 9000 | L13: =$C13+L$4*$D13-$E13 -> 12000 | M13: =$C13+M$4*$D13-$E13 -> 15000 | ... R13: =$C13+R$4*$D13-$E13 -> 30000
A14: SDR | B14: ='Análisis Compactación'!A14 -> SDR | BOMAG | BW220 D-5 PL | C14: ='Análisis Compactación'!F14 -> 0 | D14: ='Análisis Compactación'!AB14 -> 3 | E14: ='Análisis Compactación'!J14 -> 0 | F14: =$C14+F$4*$D14-$E14 -> 0 | G14: =$C14+G$4*$D14-$E14 -> 3000 | H14: =$C14+H$4*$D14-$E14 -> 4500 | I14: =$C14+I$4*$D14-$E14 -> 6000 | J14: =$C14+J$4*$D14-$E14 -> 7500 | K14: =$C14+K$4*$D14-$E14 -> 9000 | L14: =$C14+L$4*$D14-$E14 -> 12000 | M14: =$C14+M$4*$D14-$E14 -> 15000 | ... R14: =$C14+R$4*$D14-$E14 -> 30000
A15: SDR | B15: ='Análisis Compactación'!A15 -> SDR | SAKAI | SV521D | C15: ='Análisis Compactación'!F15 -> 0 | D15: ='Análisis Compactación'!AB15 -> 4.85 | E15: ='Análisis Compactación'!J15 -> 0 | F15: =$C15+F$4*$D15-$E15 -> 0 | G15: =$C15+G$4*$D15-$E15 -> 4850 | H15: =$C15+H$4*$D15-$E15 -> 7275 | I15: =$C15+I$4*$D15-$E15 -> 9700 | J15: =$C15+J$4*$D15-$E15 -> 12125 | K15: =$C15+K$4*$D15-$E15 -> 14550 | L15: =$C15+L$4*$D15-$E15 -> 19400 | M15: =$C15+M$4*$D15-$E15 -> 24250 | ... R15: =$C15+R$4*$D15-$E15 -> 48500
A16: SDR | B16: ='Análisis Compactación'!A16 -> SDR | SAKAI | SV621D | C16: ='Análisis Compactación'!F16 -> 0 | D16: ='Análisis Compactación'!AB16 -> 4.85 | E16: ='Análisis Compactación'!J16 -> 0 | F16: =$C16+F$4*$D16-$E16 -> 0 | G16: =$C16+G$4*$D16-$E16 -> 4850 | H16: =$C16+H$4*$D16-$E16 -> 7275 | I16: =$C16+I$4*$D16-$E16 -> 9700 | J16: =$C16+J$4*$D16-$E16 -> 12125 | K16: =$C16+K$4*$D16-$E16 -> 14550 | L16: =$C16+L$4*$D16-$E16 -> 19400 | M16: =$C16+M$4*$D16-$E16 -> 24250 | ... R16: =$C16+R$4*$D16-$E16 -> 48500
... A64: HTR | B64: ='Análisis Compactación'!A64 -> HTR | HAMM | HD90 VV | C64: ='Análisis Compactación'!F64 -> 28000 | D64: ='Análisis Compactación'!AB64 -> 17.16 | E64: ='Análisis Compactación'!J64 -> 0 | F64: =$C64+F$4*$D64-$E64 -> 28000 | G64: =$C64+G$4*$D64-$E64 -> 45160 | H64: =$C64+H$4*$D64-$E64 -> 53740 | I64: =$C64+I$4*$D64-$E64 -> 62320 | J64: =$C64+J$4*$D64-$E64 -> 70900 | K64: =$C64+K$4*$D64-$E64 -> 79480 | L64: =$C64+L$4*$D64-$E64 -> 96640 | M64: =$C64+M$4*$D64-$E64 -> 113800 | ... R64: =$C64+R$4*$D64-$E64 -> 199600
A65: Fresadora | B65: ='Análisis Fresadoras'!A4 -> BOMAG | BM 1000/20 | C65: ='Análisis Fresadoras'!D4 -> 0 | D65: ='Análisis Fresadoras'!Y4 -> 47.2 | E65: ='Análisis Fresadoras'!W4 -> 0 | F65: =$C65+F$4*$D65-$E65 -> 0 | G65: =$C65+G$4*$D65-$E65 -> 47200 | H65: =$C65+H$4*$D65-$E65 -> 70800 | I65: =$C65+I$4*$D65-$E65 -> 94400 | J65: =$C65+J$4*$D65-$E65 -> 118000 | K65: =$C65+K$4*$D65-$E65 -> 141600 | L65: =$C65+L$4*$D65-$E65 -> 188800 | M65: =$C65+M$4*$D65-$E65 -> 236000 | ... R65: =$C65+R$4*$D65-$E65 -> 472000
A66: Fresadora | B66: ='Análisis Fresadoras'!A5 -> SANY | SCM1000C-8 | C66: ='Análisis Fresadoras'!D5 -> 0 | D66: ='Análisis Fresadoras'!Y5 -> 66.4 | E66: ='Análisis Fresadoras'!W5 -> 0 | F66: =$C66+F$4*$D66-$E66 -> 0 | G66: =$C66+G$4*$D66-$E66 -> 66400 | H66: =$C66+H$4*$D66-$E66 -> 99600 | I66: =$C66+I$4*$D66-$E66 -> 132800 | J66: =$C66+J$4*$D66-$E66 -> 166000 | K66: =$C66+K$4*$D66-$E66 -> 199200 | L66: =$C66+L$4*$D66-$E66 -> 265600 | M66: =$C66+M$4*$D66-$E66 -> 332000 | ... R66: =$C66+R$4*$D66-$E66 -> 664000
A67: Fresadora | B67: ='Análisis Fresadoras'!A6 -> XCMG | XM1005H | C67: ='Análisis Fresadoras'!D6 -> 0 | D67: ='Análisis Fresadoras'!Y6 -> 56.6 | E67: ='Análisis Fresadoras'!W6 -> 0 | F67: =$C67+F$4*$D67-$E67 -> 0 | G67: =$C67+G$4*$D67-$E67 -> 56600 | H67: =$C67+H$4*$D67-$E67 -> 84900 | I67: =$C67+I$4*$D67-$E67 -> 113200 | J67: =$C67+J$4*$D67-$E67 -> 141500 | K67: =$C67+K$4*$D67-$E67 -> 169800 | L67: =$C67+L$4*$D67-$E67 -> 226400 | M67: =$C67+M$4*$D67-$E67 -> 283000 | ... R67: =$C67+R$4*$D67-$E67 -> 566000
A68: Pavimentadora | B68: ='Análisis Pavimentadoras'!A5 -> CATERPILLAR | AP655 | C68: ='Análisis Pavimentadoras'!D5 -> 0 | D68: ='Análisis Pavimentadoras'!AC5 -> 42.79228 | E68: ='Análisis Pavimentadoras'!AA5 -> 0 | F68: =$C68+F$4*$D68-$E68 -> 0 | G68: =$C68+G$4*$D68-$E68 -> 42792.28 | H68: =$C68+H$4*$D68-$E68 -> 64188.42 | I68: =$C68+I$4*$D68-$E68 -> 85584.56 | J68: =$C68+J$4*$D68-$E68 -> 106980.7 | K68: =$C68+K$4*$D68-$E68 -> 128376.84 | L68: =$C68+L$4*$D68-$E68 -> 171169.12 | M68: =$C68+M$4*$D68-$E68 -> 213961.4 | ... R68: =$C68+R$4*$D68-$E68 -> 427922.8
A69: Pavimentadora | B69: ='Análisis Pavimentadoras'!A6 -> BOMAG | BF600 C-3 | C69: ='Análisis Pavimentadoras'!D6 -> 0 | D69: ='Análisis Pavimentadoras'!AC6 -> 24.1644 | E69: ='Análisis Pavimentadoras'!AA6 -> 0 | F69: =$C69+F$4*$D69-$E69 -> 0 | G69: =$C69+G$4*$D69-$E69 -> 24164.4 | H69: =$C69+H$4*$D69-$E69 -> 36246.6 | I69: =$C69+I$4*$D69-$E69 -> 48328.8 | J69: =$C69+J$4*$D69-$E69 -> 60411 | K69: =$C69+K$4*$D69-$E69 -> 72493.2 | L69: =$C69+L$4*$D69-$E69 -> 96657.6 | M69: =$C69+M$4*$D69-$E69 -> 120822 | ... R69: =$C69+R$4*$D69-$E69 -> 241644
A70: Pavimentadora | B70: ='Análisis Pavimentadoras'!A7 -> VÖGELE | Super 1800-3 | C70: ='Análisis Pavimentadoras'!D7 -> 0 | D70: ='Análisis Pavimentadoras'!AC7 -> 25.9 | E70: ='Análisis Pavimentadoras'!AA7 -> 0 | F70: =$C70+F$4*$D70-$E70 -> 0 | G70: =$C70+G$4*$D70-$E70 -> 25900 | H70: =$C70+H$4*$D70-$E70 -> 38850 | I70: =$C70+I$4*$D70-$E70 -> 51800 | J70: =$C70+J$4*$D70-$E70 -> 64750 | K70: =$C70+K$4*$D70-$E70 -> 77700 | L70: =$C70+L$4*$D70-$E70 -> 103600 | M70: =$C70+M$4*$D70-$E70 -> 129500 | ... R70: =$C70+R$4*$D70-$E70 -> 259000
A71: Pavimentadora | B71: ='Análisis Pavimentadoras'!A8 -> DYNAPAC | SD2500CS | C71: ='Análisis Pavimentadoras'!D8 -> 0 | D71: ='Análisis Pavimentadoras'!AC8 -> 38.5 | E71: ='Análisis Pavimentadoras'!AA8 -> 0 | F71: =$C71+F$4*$D71-$E71 -> 0 | G71: =$C71+G$4*$D71-$E71 -> 38500 | H71: =$C71+H$4*$D71-$E71 -> 57750 | I71: =$C71+I$4*$D71-$E71 -> 77000 | J71: =$C71+J$4*$D71-$E71 -> 96250 | K71: =$C71+K$4*$D71-$E71 -> 115500 | L71: =$C71+L$4*$D71-$E71 -> 154000 | M71: =$C71+M$4*$D71-$E71 -> 192500 | ... R71: =$C71+R$4*$D71-$E71 -> 385000

Sheet Comparador
A1: Comparador — Compactación (elija hasta 4 máquinas)
A2: Seleccione el ID en las celdas amarillas. Todos los valores se traen de la hoja Análisis Compactación.
A4: Máquina | B4: SDR | BOMAG | BW211 D-5 SL (mat. 93500000) | C4: SDR | DYNAPAC | CA25 D-Rhino | D4: SDR | DYNAPAC | CA35 D-Rhino | E4: SDR | DYNAPAC | CA3500D
A5: Marca | B5: =IF(B$4="","",INDEX('Análisis Compactación'!$C$5:$C$64,MATCH(B$4,'Análisis Compactación'!$A$5:$A$64,0))) -> BOMAG | C5: =IF(C$4="","",INDEX('Análisis Compactación'!$C$5:$C$64,MATCH(C$4,'Análisis Compactación'!$A$5:$A$64,0))) -> DYNAPAC | D5: =IF(D$4="","",INDEX('Análisis Compactación'!$C$5:$C$64,MATCH(D$4,'Análisis Compactación'!$A$5:$A$64,0))) -> DYNAPAC | E5: =IF(E$4="","",INDEX('Análisis Compactación'!$C$5:$C$64,MATCH(E$4,'Análisis Compactación'!$A$5:$A$64,0))) -> DYNAPAC
A6: Modelo | B6: =IF(B$4="","",INDEX('Análisis Compactación'!$D$5:$D$64,MATCH(B$4,'Análisis Compactación'!$A$5:$A$64,0))) -> BW211 D-5 SL | C6: =IF(C$4="","",INDEX('Análisis Compactación'!$D$5:$D$64,MATCH(C$4,'Análisis Compactación'!$A$5:$A$64,0))) -> CA25 D-Rhino | D6: =IF(D$4="","",INDEX('Análisis Compactación'!$D$5:$D$64,MATCH(D$4,'Análisis Compactación'!$A$5:$A$64,0))) -> CA35 D-Rhino | E6: =IF(E$4="","",INDEX('Análisis Compactación'!$D$5:$D$64,MATCH(E$4,'Análisis Compactación'!$A$5:$A$64,0))) -> CA3500D
A7: Peso (kg) | B7: =IF(B$4="","",INDEX('Análisis Compactación'!$E$5:$E$64,MATCH(B$4,'Análisis Compactación'!$A$5:$A$64,0))) -> 10630 | C7: =IF(C$4="","",INDEX('Análisis Compactación'!$E$5:$E$64,MATCH(C$4,'Análisis Compactación'!$A$5:$A$64,0))) -> 10400 | D7: =IF(D$4="","",INDEX('Análisis Compactación'!$E$5:$E$64,MATCH(D$4,'Análisis Compactación'!$A$5:$A$64,0))) -> 12200 | E7: =IF(E$4="","",INDEX('Análisis Compactación'!$E$5:$E$64,MATCH(E$4,'Análisis Compactación'!$A$5:$A$64,0))) -> 16000
A8: Precio (USD) | B8: =IF(B$4="","",INDEX('Análisis Compactación'!$F$5:$F$64,MATCH(B$4,'Análisis Compactación'!$A$5:$A$64,0))) -> 57592.78 | C8: =IF(C$4="","",INDEX('Análisis Compactación'!$F$5:$F$64,MATCH(C$4,'Análisis Compactación'!$A$5:$A$64,0))) -> 90000 | D8: =IF(D$4="","",INDEX('Análisis Compactación'!$F$5:$F$64,MATCH(D$4,'Análisis Compactación'!$A$5:$A$64,0))) -> 90000 | E8: =IF(E$4="","",INDEX('Análisis Compactación'!$F$5:$F$64,MATCH(E$4,'Análisis Compactación'!$A$5:$A$64,0))) -> 90000
A9: Consumo (L/h) | B9: =IF(B$4="","",INDEX('Análisis Compactación'!$G$5:$G$64,MATCH(B$4,'Análisis Compactación'!$A$5:$A$64,0))) -> 11.8 | C9: =IF(C$4="","",INDEX('Análisis Compactación'!$G$5:$G$64,MATCH(C$4,'Análisis Compactación'!$A$5:$A$64,0))) -> 13.6 | D9: =IF(D$4="","",INDEX('Análisis Compactación'!$G$5:$G$64,MATCH(D$4,'Análisis Compactación'!$A$5:$A$64,0))) -> 13.6 | E9: =IF(E$4="","",INDEX('Análisis Compactación'!$G$5:$G$64,MATCH(E$4,'Análisis Compactación'!$A$5:$A$64,0))) -> 13.6
A10: Mant. preventivo (USD/h) | B10: =IF(B$4="","",INDEX('Análisis Compactación'!$H$5:$H$64,MATCH(B$4,'Análisis Compactación'!$A$5:$A$64,0))) -> 1 | C10: =IF(C$4="","",INDEX('Análisis Compactación'!$H$5:$H$64,MATCH(C$4,'Análisis Compactación'!$A$5:$A$64,0))) -> 1 | D10: =IF(D$4="","",INDEX('Análisis Compactación'!$H$5:$H$64,MATCH(D$4,'Análisis Compactación'!$A$5:$A$64,0))) -> 1 | E10: =IF(E$4="","",INDEX('Análisis Compactación'!$H$5:$H$64,MATCH(E$4,'Análisis Compactación'!$A$5:$A$64,0))) -> 1
A11: Mant. correctivo (USD/h) | B11: =IF(B$4="","",INDEX('Análisis Compactación'!$I$5:$I$64,MATCH(B$4,'Análisis Compactación'!$A$5:$A$64,0))) -> 2 | C11: =IF(C$4="","",INDEX('Análisis Compactación'!$I$5:$I$64,MATCH(C$4,'Análisis Compactación'!$A$5:$A$64,0))) -> 2 | D11: =IF(D$4="","",INDEX('Análisis Compactación'!$I$5:$I$64,MATCH(D$4,'Análisis Compactación'!$A$5:$A$64,0))) -> 2 | E11: =IF(E$4="","",INDEX('Análisis Compactación'!$I$5:$I$64,MATCH(E$4,'Análisis Compactación'!$A$5:$A$64,0))) -> 2
A12: Junta libre de mant.? | B12: =IF(B$4="","",INDEX('Análisis Compactación'!$K$5:$K$64,MATCH(B$4,'Análisis Compactación'!$A$5:$A$64,0))) -> SÍ | C12: =IF(C$4="","",INDEX('Análisis Compactación'!$K$5:$K$64,MATCH(C$4,'Análisis Compactación'!$A$5:$A$64,0))) -> NO | D12: =IF(D$4="","",INDEX('Análisis Compactación'!$K$5:$K$64,MATCH(D$4,'Análisis Compactación'!$A$5:$A$64,0))) -> NO | E12: =IF(E$4="","",INDEX('Análisis Compactación'!$K$5:$K$64,MATCH(E$4,'Análisis Compactación'!$A$5:$A$64,0))) -> NO
A13: Tec. BOMAG activa? | B13: =IF(B$4="","",INDEX('Análisis Compactación'!$L$5:$L$64,MATCH(B$4,'Análisis Compactación'!$A$5:$A$64,0))) -> NO | C13: =IF(C$4="","",INDEX('Análisis Compactación'!$L$5:$L$64,MATCH(C$4,'Análisis Compactación'!$A$5:$A$64,0))) -> N/A | D13: =IF(D$4="","",INDEX('Análisis Compactación'!$L$5:$L$64,MATCH(D$4,'Análisis Compactación'!$A$5:$A$64,0))) -> N/A | E13: =IF(E$4="","",INDEX('Análisis Compactación'!$L$5:$L$64,MATCH(E$4,'Análisis Compactación'!$A$5:$A$64,0))) -> N/A
A14: Rend. base suelo sel. (m³/h) | B14: =IF(B$4="","",INDEX('Análisis Compactación'!$Q$5:$Q$64,MATCH(B$4,'Análisis Compactación'!$A$5:$A$64,0))) -> 417 | C14: =IF(C$4="","",INDEX('Análisis Compactación'!$Q$5:$Q$64,MATCH(C$4,'Análisis Compactación'!$A$5:$A$64,0))) -> 387 | D14: =IF(D$4="","",INDEX('Análisis Compactación'!$Q$5:$Q$64,MATCH(D$4,'Análisis Compactación'!$A$5:$A$64,0))) -> 540 | E14: =IF(E$4="","",INDEX('Análisis Compactación'!$Q$5:$Q$64,MATCH(E$4,'Análisis Compactación'!$A$5:$A$64,0))) -> 800
A15: Rend. efectivo (m³/h) | B15: =IF(B$4="","",INDEX('Análisis Compactación'!$R$5:$R$64,MATCH(B$4,'Análisis Compactación'!$A$5:$A$64,0))) -> 417 | C15: =IF(C$4="","",INDEX('Análisis Compactación'!$R$5:$R$64,MATCH(C$4,'Análisis Compactación'!$A$5:$A$64,0))) -> 387 | D15: =IF(D$4="","",INDEX('Análisis Compactación'!$R$5:$R$64,MATCH(D$4,'Análisis Compactación'!$A$5:$A$64,0))) -> 540 | E15: =IF(E$4="","",INDEX('Análisis Compactación'!$R$5:$R$64,MATCH(E$4,'Análisis Compactación'!$A$5:$A$64,0))) -> 800
A16: Rend. ajustado por eficiencia (m³/h) | B16: =IF(B$4="","",INDEX('Análisis Compactación'!$S$5:$S$64,MATCH(B$4,'Análisis Compactación'!$A$5:$A$64,0))) -> 417 | C16: =IF(C$4="","",INDEX('Análisis Compactación'!$S$5:$S$64,MATCH(C$4,'Análisis Compactación'!$A$5:$A$64,0))) -> 387 | D16: =IF(D$4="","",INDEX('Análisis Compactación'!$S$5:$S$64,MATCH(D$4,'Análisis Compactación'!$A$5:$A$64,0))) -> 540 | E16: =IF(E$4="","",INDEX('Análisis Compactación'!$S$5:$S$64,MATCH(E$4,'Análisis Compactación'!$A$5:$A$64,0))) -> 800
A17: Horas para el volumen (h) | B17: =IF(B$4="","",INDEX('Análisis Compactación'!$T$5:$T$64,MATCH(B$4,'Análisis Compactación'!$A$5:$A$64,0))) -> 0 | C17: =IF(C$4="","",INDEX('Análisis Compactación'!$T$5:$T$64,MATCH(C$4,'Análisis Compactación'!$A$5:$A$64,0))) -> 0 | D17: =IF(D$4="","",INDEX('Análisis Compactación'!$T$5:$T$64,MATCH(D$4,'Análisis Compactación'!$A$5:$A$64,0))) -> 0 | E17: =IF(E$4="","",INDEX('Análisis Compactación'!$T$5:$T$64,MATCH(E$4,'Análisis Compactación'!$A$5:$A$64,0))) -> 0
A18: Costo operación (USD/h) | B18: =IF(B$4="","",INDEX('Análisis Compactación'!$U$5:$U$64,MATCH(B$4,'Análisis Compactación'!$A$5:$A$64,0))) -> 17.16 | C18: =IF(C$4="","",INDEX('Análisis Compactación'!$U$5:$U$64,MATCH(C$4,'Análisis Compactación'!$A$5:$A$64,0))) -> 19.32 | D18: =IF(D$4="","",INDEX('Análisis Compactación'!$U$5:$U$64,MATCH(D$4,'Análisis Compactación'!$A$5:$A$64,0))) -> 19.32 | E18: =IF(E$4="","",INDEX('Análisis Compactación'!$U$5:$U$64,MATCH(E$4,'Análisis Compactación'!$A$5:$A$64,0))) -> 19.32
A19: Costo del trabajo (USD) | B19: =IF(B$4="","",INDEX('Análisis Compactación'!$V$5:$V$64,MATCH(B$4,'Análisis Compactación'!$A$5:$A$64,0))) -> 0 | C19: =IF(C$4="","",INDEX('Análisis Compactación'!$V$5:$V$64,MATCH(C$4,'Análisis Compactación'!$A$5:$A$64,0))) -> 0 | D19: =IF(D$4="","",INDEX('Análisis Compactación'!$V$5:$V$64,MATCH(D$4,'Análisis Compactación'!$A$5:$A$64,0))) -> 0 | E19: =IF(E$4="","",INDEX('Análisis Compactación'!$V$5:$V$64,MATCH(E$4,'Análisis Compactación'!$A$5:$A$64,0))) -> 0
A20: Costo combustible (USD) | B20: =IF(B$4="","",INDEX('Análisis Compactación'!$W$5:$W$64,MATCH(B$4,'Análisis Compactación'!$A$5:$A$64,0))) -> 42480 | C20: =IF(C$4="","",INDEX('Análisis Compactación'!$W$5:$W$64,MATCH(C$4,'Análisis Compactación'!$A$5:$A$64,0))) -> 48960 | D20: =IF(D$4="","",INDEX('Análisis Compactación'!$W$5:$W$64,MATCH(D$4,'Análisis Compactación'!$A$5:$A$64,0))) -> 48960 | E20: =IF(E$4="","",INDEX('Análisis Compactación'!$W$5:$W$64,MATCH(E$4,'Análisis Compactación'!$A$5:$A$64,0))) -> 48960
A21: Costo mantenimiento (USD) | B21: =IF(B$4="","",INDEX('Análisis Compactación'!$X$5:$X$64,MATCH(B$4,'Análisis Compactación'!$A$5:$A$64,0))) -> 9000 | C21: =IF(C$4="","",INDEX('Análisis Compactación'!$X$5:$X$64,MATCH(C$4,'Análisis Compactación'!$A$5:$A$64,0))) -> 9000 | D21: =IF(D$4="","",INDEX('Análisis Compactación'!$X$5:$X$64,MATCH(D$4,'Análisis Compactación'!$A$5:$A$64,0))) -> 9000 | E21: =IF(E$4="","",INDEX('Análisis Compactación'!$X$5:$X$64,MATCH(E$4,'Análisis Compactación'!$A$5:$A$64,0))) -> 9000
A22: Costo junta articulada (USD) | B22: =IF(B$4="","",INDEX('Análisis Compactación'!$Z$5:$Z$64,MATCH(B$4,'Análisis Compactación'!$A$5:$A$64,0))) -> 0 | C22: =IF(C$4="","",INDEX('Análisis Compactación'!$Z$5:$Z$64,MATCH(C$4,'Análisis Compactación'!$A$5:$A$64,0))) -> 5550 | D22: =IF(D$4="","",INDEX('Análisis Compactación'!$Z$5:$Z$64,MATCH(D$4,'Análisis Compactación'!$A$5:$A$64,0))) -> 5550 | E22: =IF(E$4="","",INDEX('Análisis Compactación'!$Z$5:$Z$64,MATCH(E$4,'Análisis Compactación'!$A$5:$A$64,0))) -> 5550
A23: Valor de reventa (USD) | B23: =IF(B$4="","",INDEX('Análisis Compactación'!$J$5:$J$64,MATCH(B$4,'Análisis Compactación'!$A$5:$A$64,0))) -> 0 | C23: =IF(C$4="","",INDEX('Análisis Compactación'!$J$5:$J$64,MATCH(C$4,'Análisis Compactación'!$A$5:$A$64,0))) -> 0 | D23: =IF(D$4="","",INDEX('Análisis Compactación'!$J$5:$J$64,MATCH(D$4,'Análisis Compactación'!$A$5:$A$64,0))) -> 0 | E23: =IF(E$4="","",INDEX('Análisis Compactación'!$J$5:$J$64,MATCH(E$4,'Análisis Compactación'!$A$5:$A$64,0))) -> 0
A24: TCO (USD) | B24: =IF(B$4="","",INDEX('Análisis Compactación'!$AA$5:$AA$64,MATCH(B$4,'Análisis Compactación'!$A$5:$A$64,0))) -> 109072.78 | C24: =IF(C$4="","",INDEX('Análisis Compactación'!$AA$5:$AA$64,MATCH(C$4,'Análisis Compactación'!$A$5:$A$64,0))) -> 153510 | D24: =IF(D$4="","",INDEX('Análisis Compactación'!$AA$5:$AA$64,MATCH(D$4,'Análisis Compactación'!$A$5:$A$64,0))) -> 153510 | E24: =IF(E$4="","",INDEX('Análisis Compactación'!$AA$5:$AA$64,MATCH(E$4,'Análisis Compactación'!$A$5:$A$64,0))) -> 153510
A25: TCO por hora (USD/h) | B25: =IF(B$4="","",INDEX('Análisis Compactación'!$AC$5:$AC$64,MATCH(B$4,'Análisis Compactación'!$A$5:$A$64,0))) -> 36.357593 | C25: =IF(C$4="","",INDEX('Análisis Compactación'!$AC$5:$AC$64,MATCH(C$4,'Análisis Compactación'!$A$5:$A$64,0))) -> 51.17 | D25: =IF(D$4="","",INDEX('Análisis Compactación'!$AC$5:$AC$64,MATCH(D$4,'Análisis Compactación'!$A$5:$A$64,0))) -> 51.17 | E25: =IF(E$4="","",INDEX('Análisis Compactación'!$AC$5:$AC$64,MATCH(E$4,'Análisis Compactación'!$A$5:$A$64,0))) -> 51.17
A26: TCO (moneda sel.) | B26: =IF(B$4="","",INDEX('Análisis Compactación'!$AD$5:$AD$64,MATCH(B$4,'Análisis Compactación'!$A$5:$A$64,0))) -> 109072.78 | C26: =IF(C$4="","",INDEX('Análisis Compactación'!$AD$5:$AD$64,MATCH(C$4,'Análisis Compactación'!$A$5:$A$64,0))) -> 153510 | D26: =IF(D$4="","",INDEX('Análisis Compactación'!$AD$5:$AD$64,MATCH(D$4,'Análisis Compactación'!$A$5:$A$64,0))) -> 153510 | E26: =IF(E$4="","",INDEX('Análisis Compactación'!$AD$5:$AD$64,MATCH(E$4,'Análisis Compactación'!$A$5:$A$64,0))) -> 153510
A27: Ahorro vs máquina 1 (USD) | B27: =IF(B$4="","",B24-$B24) -> 0 | C27: =IF(C$4="","",C24-$B24) -> 44437.22 | D27: =IF(D$4="","",D24-$B24) -> 44437.22 | E27: =IF(E$4="","",E24-$B24) -> 44437.22
A28: Positivo = la máquina 1 (normalmente BOMAG) es más económica.

Sheet Tablas Rendimiento
A1: Tablas de rendimiento de compactación
A3: Rendimiento corregido (m³/h) — base de la interpolación por peso
A4: Peso mín. (t) | B4: Peso máx. (t) | C4: Roca mín. | D4: Roca máx. | E4: Grava mín. | F4: Grava máx. | G4: Suelo mixto mín. | H4: Suelo mixto máx. | I4: Arcilla mín. | J4: Arcilla máx. | K4: Roca prom. | L4: Grava prom. | M4: Suelo mixto prom. | N4: Arcilla prom.
A5: 2 | B5: 3 | E5: 60 | F5: 180 | G5: 60 | H5: 180 | I5: 40 | J5: 100 | K5: =IF(COUNT(C5:D5)=2,AVERAGE(C5:D5),"-") -> - | L5: =IF(COUNT(E5:F5)=2,AVERAGE(E5:F5),"-") -> 120 | M5: =IF(COUNT(G5:H5)=2,AVERAGE(G5:H5),"-") -> 120 | N5: =IF(COUNT(I5:J5)=2,AVERAGE(I5:J5),"-") -> 70
A6: 6 | B6: 8 | C6: 200 | D6: 500 | E6: 100 | F6: 400 | G6: 100 | H6: 350 | I6: 70 | J6: 200 | K6: =IF(COUNT(C6:D6)=2,AVERAGE(C6:D6),"-") -> 350 | L6: =IF(COUNT(E6:F6)=2,AVERAGE(E6:F6),"-") -> 250 | M6: =IF(COUNT(G6:H6)=2,AVERAGE(G6:H6),"-") -> 225 | N6: =IF(COUNT(I6:J6)=2,AVERAGE(I6:J6),"-") -> 135
A7: 9 | B7: 12 | C7: 400 | D7: 900 | E7: 200 | F7: 700 | G7: 200 | H7: 600 | I7: 100 | J7: 300 | K7: =IF(COUNT(C7:D7)=2,AVERAGE(C7:D7),"-") -> 650 | L7: =IF(COUNT(E7:F7)=2,AVERAGE(E7:F7),"-") -> 450 | M7: =IF(COUNT(G7:H7)=2,AVERAGE(G7:H7),"-") -> 400 | N7: =IF(COUNT(I7:J7)=2,AVERAGE(I7:J7),"-") -> 200
A8: 13 | B8: 16 | C8: 500 | D8: 1400 | E8: 350 | F8: 1000 | G8: 300 | H8: 800 | I8: 150 | J8: 400 | K8: =IF(COUNT(C8:D8)=2,AVERAGE(C8:D8),"-") -> 950 | L8: =IF(COUNT(E8:F8)=2,AVERAGE(E8:F8),"-") -> 675 | M8: =IF(COUNT(G8:H8)=2,AVERAGE(G8:H8),"-") -> 550 | N8: =IF(COUNT(I8:J8)=2,AVERAGE(I8:J8),"-") -> 275
A9: 19 | B9: 25 | C9: 900 | D9: 2200 | E9: 500 | F9: 1600 | G9: 500 | H9: 1200 | I9: 300 | J9: 500 | K9: =IF(COUNT(C9:D9)=2,AVERAGE(C9:D9),"-") -> 1550 | L9: =IF(COUNT(E9:F9)=2,AVERAGE(E9:F9),"-") -> 1050 | M9: =IF(COUNT(G9:H9)=2,AVERAGE(G9:H9),"-") -> 850 | N9: =IF(COUNT(I9:J9)=2,AVERAGE(I9:J9),"-") -> 400
A11: Nota: dentro de un rango la app interpola linealmente: mín + (máx − mín) × (peso − peso mín.)/(peso máx. − peso mín.). Fuera de rango aplica escalado (peso/punto medio)^0,8 o extrapolación por tipo de suelo.
A13: Altura de capa compactada (m)
A14: Peso operativo (t) | B14: Roca | C14: Grava | D14: Suelo mixto | E14: Arcilla
A15: 2 – 3 | B15: - | C15: 0.20 – 0.35 | D15: 0.20 – 0.30 | E15: 0.15 – 0.20
A16: 6 – 8 | B16: 0.30 – 0.50 | C16: 0.30 – 0.40 | D16: 0.25 – 0.35 | E16: 0.15 – 0.20
A17: 9 – 12 | B17: 0.50 – 0.80 | C17: 0.50 – 0.80 | D17: 0.40 – 0.60 | E17: 0.20 – 0.30
A18: 13 – 16 | B18: 0.80 – 1.20 | C18: 0.80 – 1.20 | D18: 0.50 – 0.80 | E18: 0.20 – 0.35
A19: 19 – 25 | B19: 1.00 – 2.00 | C19: 0.80 – 1.50 | D19: 0.60 – 1.00 | E19: 0.30 – 0.50
A21: Rendimiento de compactación — tabla de referencia (m³/h)
A22: Peso operativo (t) | B22: Roca | C22: Grava | D22: Suelo mixto | E22: Arcilla
A23: 1.5 – 2.5 | B23: 30 – 80 | C23: 50 – 150 | D23: 50 – 120 | E23: 30 – 70
A24: 3.0 – 4.5 | B24: 50 – 120 | C24: 70 – 200 | D24: 60 – 150 | E24: 40 – 90
A25: 7 – 9 | B25: 80 – 200 | C25: 120 – 350 | D25: 100 – 250 | E25: 80 – 150
